Workbook
Name costerecursosbaselineactual: 'Cost Overview'!$G$8
Name costerecursostotalplanificado: costerecursosbaselineactual-'Cost Planning'!$I$5
Name FECHA: 'Project Infor'!$D$6
Name FIN: 'Project Infor'!$C$9
Name Inicio: 'Project Infor'!$C$8
Name margendirectobaselineactual: 'Cost Overview'!$F$8-'Cost Overview'!$M$8
Name margendirectofinal: margendirectobaselineactual+'Cost Planning'!$I$5+'Cost Planning'!$E$47+'Cost Planning'!$E$48+'Cost Planning'!$I$50+'Cost Planning'!$I$61
Name pedidobaselineactual: 'Cost Overview'!$F$8
Name UTILIZACION: 0.93

Sheet Project Infor
B3: CORE (COst REport) - PC
B5: Fecha Actual | C5: 46140
B6: Fecha Reporting | C6: =DATE(IF(EXACT(MONTH(EDATE(C5,0)),"12"),YEAR(C5)+1,YEAR(C5)),MONTH(EDATE(C5,1)),1) -> 46143 | D6: =DATE(YEAR(C6),MONTH(C6),1) -> 46143
B8: Fecha de Inicio CORE | C8: 45962
B9: Fecha Fin CORE | C9: 46326
B10: WBS-Element | C10: var2_SAP_PEP_WBS
B11: Descripción | C11: Smart Airport en la nueva terminal de Puerto Vallarta
B12: Práctica principal | C12: Software Development
B13: Otras prácticas relacionadas | C13: Compañía: Connectis-ICT | Unidad: ICT | Portfolio: Smart Spaces | Subpractice: Smart Spaces/EAI | Origen: Mobility
C15: CÓDIGO | D15: DESCRIPCIÓN
B16: Cliente | C16: var3_SAP_CodigoCliente | D16: GAP
B18: Contrato / Expediente | C18: SLFC 20250256445
B19: Pedido (Order) | C19: var4_SAP_PedidoSalesOrder
C21: COD EMPLEADO | D21: NOMBRE Y APELLIDOS
B22: Project Manager | C22: var5_SAP_CodEmpleadoPM | D22: var6_SAP_ProjectManager
B23: Practice Leader | C23: var7_SAP_CodEmpleadoPracticeLeader | D23: var8_SAP_PracticeLeader
B24: Sales Manager | C24: var9_SF_CodEmpleadoSalesManager | D24: Joan Marcer
B26: PRESUPUESTO INICIAL (PPO)
B28: Pedido | C28: 583896.55
B29: Horas estimadas | C29: 13570
B30: Coste Recursos | C30: 367515.14
B31: Riegos | C31: 18375.757
B32: Garantía | C32: 0
B33: Gastos | C33: 7400
B34: Compras | C34: 40000
B35: Coste Directo | C35: =SUM(C30:C34) -> 433290.9
B37: Margen Directo | C37: =IF(C28=0,0,(C28-C35)/C28) -> 0.25793208
B38: Margen Bruto | C38: =IF(C28=0,0,(C28-(SUM(C30,C31,C32)/UTILIZACION)-SUM(C34,C33))/C28) -> 0.20818774
B40: Comentarios adicionales Presupuesto inicial | C40: Pre-relleno generado desde PPO 20250256445. Tipo PPO: Fixed Price (services); PEP Type: PC; vencimiento factura: N060. Los campos con prefijo var*_SAP/var*_SF quedan pendientes de completar desde SAP/Salesforce/proceso previo.
B43: PRESUPUESTO YA CONSUMIDO
B45: Venta incurrida
B46: Horas realizadas
B47: Coste Recursos incurrido
B48: Gastos incurridos
B49: Compras incurridas
B50: Coste Directo | C50: =SUM(C47:C49) -> 0
B52: Margen Directo (To Date) | C52: =IF(C45=0,0,(C45-C50)/C45) -> 0
B54: Facturación ya emitida
B56: Comentarios adicionales Presupuesto ya consumido
B60: Prácticas
B61: Advanced Services
B62: Advanced Services (Data Analytics)
B63: Advanced Services (PMO)
B64: Advanced Services (Testing & QA)
B65: CAU
B66: EAI (Enterprise App Integration) & Cloud Native
B67: Infraestructure MS
B68: Manufacturing
B69: Mobility solutions
... B76: TIWORKS

Sheet Cost Overview
B2: WBS-Element | C2: ='Project Infor'!C10 -> var2_SAP_PEP_WBS | D2: ='Project Infor'!C11 -> Smart Airport en la nueva terminal de Puerto Vallarta
B5: BASELINE ACTUAL | U5: pneta | V5: operac | W5: coste r. | X5: reservas | Y5: gastos | Z5: compras | AA5: Venta
F6: PEDIDO IMPORTE NETO | G6: COSTE RECURSOS | H6: HORAS | I6: RIESGOS | J6: GARANTÍA | K6: GASTOS | L6: COMPRAS | M6: COSTE DIRECTO | N6: MARGEN DIRECTO | O6: MARGEN BRUTO
B7: PROYECCION DEL PROYECTO SIN REESTIMACIONES | F7: =SUM(F12,F36) -> 583896.55 | G7: =SUM(G12,G36) -> 367515.14 | H7: =SUM(H12,H36) -> 13570 | I7: =SUM(I12,I36) -> 18375.757 | J7: =SUM(J12,J36) -> 0 | K7: =SUM(K12,K36) -> 7400 | L7: =SUM(L12,L36) -> 40000 | M7: =SUM(G7,I7,J7,K7,L7) -> 433290.9 | N7: =IF(F7=0,0,(F7-G7-J7-K7-I7-L7)/F7) -> 0.25793208 | O7: =IF(F7=0,0,(F7-G7/UTILIZACION-I7/UTILIZACION-J7/UTILIZACION-K7-L7)/F7) -> 0.20818774
B8: LINEA BASE ACTUAL - PROYECCION DEL PROYECTO FINAL | F8: =F7 -> 583896.55 | G8: =G7+G37 -> 367515.14 | H8: =H7+H37 -> 13570 | I8: =I7+I37 -> 18375.757 | J8: =J7+J37 -> 0 | K8: =K7+K37 -> 7400 | L8: =L7+L37 -> 40000 | M8: =M7+M37 -> 433290.9 | N8: =IF(F8=0,0,(F8-G8-J8-K8-I8-L8)/F8) -> 0.25793208 | O8: =IF(F8=0,0,(F8-G8/UTILIZACION-I8/UTILIZACION-J8/UTILIZACION-K8-L8)/F8) -> 0.20818774 | P8: {=margendirectobaselineactual} -> 150605.65
B10: BASELINE INICIAL | U10: pneta | V10: operac | W10: coste r. | X10: reservas | Y10: gastos | Z10: compras | AA10: Venta
C11: FECHA | D11: LÍNEA DE PEDIDO | E11: DESCRIPCIÓN | F11: IMPORTE NETO | G11: COSTE RECURSOS | H11: HORAS | I11: RIESGOS | J11: GARANTÍA | K11: GASTOS | L11: COMPRAS | M11: COSTE DIRECTO | N11: MARGEN DIRECTO | O11: MARGEN BRUTO
D12: 10 | E12: Apertura contrato | F12: ='Project Infor'!C28 -> 583896.55 | G12: ='Project Infor'!C30 -> 367515.14 | H12: ='Project Infor'!C29 -> 13570 | I12: ='Project Infor'!C31 -> 18375.757 | J12: ='Project Infor'!C32 -> 0 | K12: ='Project Infor'!C33 -> 7400 | L12: ='Project Infor'!C34 -> 40000 | M12: =SUM(G12,I12,J12,K12,L12) -> 433290.9 | N12: =IF(F12=0,0,(F12-G12-J12-K12-I12-L12)/F12) -> 0.25793208 | O12: =IF(F12=0,0,(F12-G12/UTILIZACION-I12/UTILIZACION-J12/UTILIZACION-K12-L12)/F12) -> 0.20818774 | T12: *** Ocultar estos datos en la versión definitiva
B14: Cambios sobre la BASELINE INICIAL | U14: pneta | V14: operac | W14: coste r. | X14: reservas | Y14: gastos | Z14: compras | AA14: Venta
B15: TIPO CAMBIO | C15: FECHA | D15: LÍNEA DE PEDIDO | E15: DESCRIPCIÓN | F15: PEDIDO IMPORTE NETO | G15: COSTE RECURSOS | H15: HORAS | I15: RIESGOS | J15: GARANTÍA | K15: GASTOS | L15: COMPRAS | M15: COSTE DIRECTO | N15: MARGEN DIRECTO | O15: MARGEN BRUTO | P15: AUTORIZADO POR CCO | R15: DATOS ADICIONALES AMPLIACION
M16: =SUM(G16,I16,J16,K16,L16) -> 0 | N16: =IF(F16=0,0,(F16-G16-J16-K16-I16-L16)/F16) -> 0 | O16: =IF(F16=0,0,(F16-G16/UTILIZACION-I16/UTILIZACION-J16/UTILIZACION-K16-L16)/F16) -> 0 | T16: =IF(C16<>"",IF((YEAR(C16)&MONTH(C16))<(YEAR(Inicio)&MONTH(Inicio)),YEAR(Inicio)&MONTH(Inicio),YEAR(C16)&MONTH(C16)),YEAR(C16)&MONTH(C16)) -> 19001 | U16: =AA16-Y16-X16-W16 -> 190605.65 | W16: =$G$12+SUM($G$16:G16) -> 367515.14 | X16: =$I$12+SUM($I$16:I16)+$J$12+SUM($J$16:J16) -> 18375.757 | Y16: =$K$12+SUM($K$16:K16) -> 7400 | Z16: =$L$12+SUM($L$16:L16) -> 40000 | AA16: =$F$12+SUM($F$16:F16) -> 583896.55
M17: =SUM(G17,I17,J17,K17,L17) -> 0 | N17: =IF(F17=0,0,(F17-G17-J17-K17-I17-L17)/F17) -> 0 | O17: =IF(F17=0,0,(F17-G17/UTILIZACION-I17/UTILIZACION-J17/UTILIZACION-K17-L17)/F17) -> 0 | T17: =IF(C17<>"",IF((YEAR(C17)&MONTH(C17))<(YEAR(Inicio)&MONTH(Inicio)),YEAR(Inicio)&MONTH(Inicio),YEAR(C17)&MONTH(C17)),YEAR(C17)&MONTH(C17)) -> 19001 | U17: =AA17-Y17-X17-W17 -> 190605.65 | W17: =$G$12+SUM($G$16:G17) -> 367515.14 | X17: =$I$12+SUM($I$16:I17)+$J$12+SUM($J$16:J17) -> 18375.757 | Y17: =$K$12+SUM($K$16:K17) -> 7400 | Z17: =$L$12+SUM($L$16:L17) -> 40000 | AA17: =$F$12+SUM($F$16:F17) -> 583896.55
M18: =SUM(G18,I18,J18,K18,L18) -> 0 | N18: =IF(F18=0,0,(F18-G18-J18-K18-I18-L18)/F18) -> 0 | O18: =IF(F18=0,0,(F18-G18/UTILIZACION-I18/UTILIZACION-J18/UTILIZACION-K18-L18)/F18) -> 0 | T18: =IF(C18<>"",IF((YEAR(C18)&MONTH(C18))<(YEAR(Inicio)&MONTH(Inicio)),YEAR(Inicio)&MONTH(Inicio),YEAR(C18)&MONTH(C18)),YEAR(C18)&MONTH(C18)) -> 19001 | U18: =AA18-Y18-X18-W18 -> 190605.65 | W18: =$G$12+SUM($G$16:G18) -> 367515.14 | X18: =$I$12+SUM($I$16:I18)+$J$12+SUM($J$16:J18) -> 18375.757 | Y18: =$K$12+SUM($K$16:K18) -> 7400 | Z18: =$L$12+SUM($L$16:L18) -> 40000 | AA18: =$F$12+SUM($F$16:F18) -> 583896.55
M19: =SUM(G19,I19,J19,K19,L19) -> 0 | N19: =IF(F19=0,0,(F19-G19-J19-K19-I19-L19)/F19) -> 0 | O19: =IF(F19=0,0,(F19-G19/UTILIZACION-I19/UTILIZACION-J19/UTILIZACION-K19-L19)/F19) -> 0 | T19: =IF(C19<>"",IF((YEAR(C19)&MONTH(C19))<(YEAR(Inicio)&MONTH(Inicio)),YEAR(Inicio)&MONTH(Inicio),YEAR(C19)&MONTH(C19)),YEAR(C19)&MONTH(C19)) -> 19001 | U19: =AA19-Y19-X19-W19 -> 190605.65 | W19: =$G$12+SUM($G$16:G19) -> 367515.14 | X19: =$I$12+SUM($I$16:I19)+$J$12+SUM($J$16:J19) -> 18375.757 | Y19: =$K$12+SUM($K$16:K19) -> 7400 | Z19: =$L$12+SUM($L$16:L19) -> 40000 | AA19: =$F$12+SUM($F$16:F19) -> 583896.55
M20: =SUM(G20,I20,J20,K20,L20) -> 0 | N20: =IF(F20=0,0,(F20-G20-J20-K20-I20-L20)/F20) -> 0 | O20: =IF(F20=0,0,(F20-G20/UTILIZACION-I20/UTILIZACION-J20/UTILIZACION-K20-L20)/F20) -> 0 | T20: =IF(C20<>"",IF((YEAR(C20)&MONTH(C20))<(YEAR(Inicio)&MONTH(Inicio)),YEAR(Inicio)&MONTH(Inicio),YEAR(C20)&MONTH(C20)),YEAR(C20)&MONTH(C20)) -> 19001 | U20: =AA20-Y20-X20-W20 -> 190605.65 | W20: =$G$12+SUM($G$16:G20) -> 367515.14 | X20: =$I$12+SUM($I$16:I20)+$J$12+SUM($J$16:J20) -> 18375.757 | Y20: =$K$12+SUM($K$16:K20) -> 7400 | Z20: =$L$12+SUM($L$16:L20) -> 40000 | AA20: =$F$12+SUM($F$16:F20) -> 583896.55
M21: =SUM(G21,I21,J21,K21,L21) -> 0 | N21: =IF(F21=0,0,(F21-G21-J21-K21-I21-L21)/F21) -> 0 | O21: =IF(F21=0,0,(F21-G21/UTILIZACION-I21/UTILIZACION-J21/UTILIZACION-K21-L21)/F21) -> 0 | T21: =IF(C21<>"",IF((YEAR(C21)&MONTH(C21))<(YEAR(Inicio)&MONTH(Inicio)),YEAR(Inicio)&MONTH(Inicio),YEAR(C21)&MONTH(C21)),YEAR(C21)&MONTH(C21)) -> 19001 | U21: =AA21-Y21-X21-W21 -> 190605.65 | W21: =$G$12+SUM($G$16:G21) -> 367515.14 | X21: =$I$12+SUM($I$16:I21)+$J$12+SUM($J$16:J21) -> 18375.757 | Y21: =$K$12+SUM($K$16:K21) -> 7400 | Z21: =$L$12+SUM($L$16:L21) -> 40000 | AA21: =$F$12+SUM($F$16:F21) -> 583896.55
M22: =SUM(G22,I22,J22,K22,L22) -> 0 | N22: =IF(F22=0,0,(F22-G22-J22-K22-I22-L22)/F22) -> 0 | O22: =IF(F22=0,0,(F22-G22/UTILIZACION-I22/UTILIZACION-J22/UTILIZACION-K22-L22)/F22) -> 0 | T22: =IF(C22<>"",IF((YEAR(C22)&MONTH(C22))<(YEAR(Inicio)&MONTH(Inicio)),YEAR(Inicio)&MONTH(Inicio),YEAR(C22)&MONTH(C22)),YEAR(C22)&MONTH(C22)) -> 19001 | U22: =AA22-Y22-X22-W22 -> 190605.65 | W22: =$G$12+SUM($G$16:G22) -> 367515.14 | X22: =$I$12+SUM($I$16:I22)+$J$12+SUM($J$16:J22) -> 18375.757 | Y22: =$K$12+SUM($K$16:K22) -> 7400 | Z22: =$L$12+SUM($L$16:L22) -> 40000 | AA22: =$F$12+SUM($F$16:F22) -> 583896.55
M23: =SUM(G23,I23,J23,K23,L23) -> 0 | N23: =IF(F23=0,0,(F23-G23-J23-K23-I23-L23)/F23) -> 0 | O23: =IF(F23=0,0,(F23-G23/UTILIZACION-I23/UTILIZACION-J23/UTILIZACION-K23-L23)/F23) -> 0 | T23: =IF(C23<>"",IF((YEAR(C23)&MONTH(C23))<(YEAR(Inicio)&MONTH(Inicio)),YEAR(Inicio)&MONTH(Inicio),YEAR(C23)&MONTH(C23)),YEAR(C23)&MONTH(C23)) -> 19001 | U23: =AA23-Y23-X23-W23 -> 190605.65 | W23: =$G$12+SUM($G$16:G23) -> 367515.14 | X23: =$I$12+SUM($I$16:I23)+$J$12+SUM($J$16:J23) -> 18375.757 | Y23: =$K$12+SUM($K$16:K23) -> 7400 | Z23: =$L$12+SUM($L$16:L23) -> 40000 | AA23: =$F$12+SUM($F$16:F23) -> 583896.55
M24: =SUM(G24,I24,J24,K24,L24) -> 0 | N24: =IF(F24=0,0,(F24-G24-J24-K24-I24-L24)/F24) -> 0 | O24: =IF(F24=0,0,(F24-G24/UTILIZACION-I24/UTILIZACION-J24/UTILIZACION-K24-L24)/F24) -> 0 | T24: =IF(C24<>"",IF((YEAR(C24)&MONTH(C24))<(YEAR(Inicio)&MONTH(Inicio)),YEAR(Inicio)&MONTH(Inicio),YEAR(C24)&MONTH(C24)),YEAR(C24)&MONTH(C24)) -> 19001 | U24: =AA24-Y24-X24-W24 -> 190605.65 | W24: =$G$12+SUM($G$16:G24) -> 367515.14 | X24: =$I$12+SUM($I$16:I24)+$J$12+SUM($J$16:J24) -> 18375.757 | Y24: =$K$12+SUM($K$16:K24) -> 7400 | Z24: =$L$12+SUM($L$16:L24) -> 40000 | AA24: =$F$12+SUM($F$16:F24) -> 583896.55
M25: =SUM(G25,I25,J25,K25,L25) -> 0 | N25: =IF(F25=0,0,(F25-G25-J25-K25-I25-L25)/F25) -> 0 | O25: =IF(F25=0,0,(F25-G25/UTILIZACION-I25/UTILIZACION-J25/UTILIZACION-K25-L25)/F25) -> 0 | T25: =IF(C25<>"",IF((YEAR(C25)&MONTH(C25))<(YEAR(Inicio)&MONTH(Inicio)),YEAR(Inicio)&MONTH(Inicio),YEAR(C25)&MONTH(C25)),YEAR(C25)&MONTH(C25)) -> 19001 | U25: =AA25-Y25-X25-W25 -> 190605.65 | W25: =$G$12+SUM($G$16:G25) -> 367515.14 | X25: =$I$12+SUM($I$16:I25)+$J$12+SUM($J$16:J25) -> 18375.757 | Y25: =$K$12+SUM($K$16:K25) -> 7400 | Z25: =$L$12+SUM($L$16:L25) -> 40000 | AA25: =$F$12+SUM($F$16:F25) -> 583896.55
M26: =SUM(G26,I26,J26,K26,L26) -> 0 | N26: =IF(F26=0,0,(F26-G26-J26-K26-I26-L26)/F26) -> 0 | O26: =IF(F26=0,0,(F26-G26/UTILIZACION-I26/UTILIZACION-J26/UTILIZACION-K26-L26)/F26) -> 0 | T26: =IF(C26<>"",IF((YEAR(C26)&MONTH(C26))<(YEAR(Inicio)&MONTH(Inicio)),YEAR(Inicio)&MONTH(Inicio),YEAR(C26)&MONTH(C26)),YEAR(C26)&MONTH(C26)) -> 19001 | U26: =AA26-Y26-X26-W26 -> 190605.65 | W26: =$G$12+SUM($G$16:G26) -> 367515.14 | X26: =$I$12+SUM($I$16:I26)+$J$12+SUM($J$16:J26) -> 18375.757 | Y26: =$K$12+SUM($K$16:K26) -> 7400 | Z26: =$L$12+SUM($L$16:L26) -> 40000 | AA26: =$F$12+SUM($F$16:F26) -> 583896.55
M27: =SUM(G27,I27,J27,K27,L27) -> 0 | N27: =IF(F27=0,0,(F27-G27-J27-K27-I27-L27)/F27) -> 0 | O27: =IF(F27=0,0,(F27-G27/UTILIZACION-I27/UTILIZACION-J27/UTILIZACION-K27-L27)/F27) -> 0 | T27: =IF(C27<>"",IF((YEAR(C27)&MONTH(C27))<(YEAR(Inicio)&MONTH(Inicio)),YEAR(Inicio)&MONTH(Inicio),YEAR(C27)&MONTH(C27)),YEAR(C27)&MONTH(C27)) -> 19001 | U27: =AA27-Y27-X27-W27 -> 190605.65 | W27: =$G$12+SUM($G$16:G27) -> 367515.14 | X27: =$I$12+SUM($I$16:I27)+$J$12+SUM($J$16:J27) -> 18375.757 | Y27: =$K$12+SUM($K$16:K27) -> 7400 | Z27: =$L$12+SUM($L$16:L27) -> 40000 | AA27: =$F$12+SUM($F$16:F27) -> 583896.55
... M35: =SUM(G35,I35,J35,K35,L35) -> 0 | N35: =IF(F35=0,0,(F35-G35-J35-K35-I35-L35)/F35) -> 0 | O35: =IF(F35=0,0,(F35-G35/UTILIZACION-I35/UTILIZACION-J35/UTILIZACION-K35-L35)/F35) -> 0 | T35: =IF(C35<>"",IF((YEAR(C35)&MONTH(C35))<(YEAR(Inicio)&MONTH(Inicio)),YEAR(Inicio)&MONTH(Inicio),YEAR(C35)&MONTH(C35)),YEAR(C35)&MONTH(C35)) -> 19001 | U35: =AA35-Y35-X35-W35 -> 190605.65 | W35: =$G$12+SUM($G$16:G35) -> 367515.14 | X35: =$I$12+SUM($I$16:I35)+$J$12+SUM($J$16:J35) -> 18375.757 | Y35: =$K$12+SUM($K$16:K35) -> 7400 | Z35: =$L$12+SUM($L$16:L35) -> 40000 | AA35: =$F$12+SUM($F$16:F35) -> 583896.55
B36: TOTAL AMPLIACIONES | F36: =SUMIF(B16:B35,"AMPLIACION",F16:F35) -> 0 | G36: =SUMIF(B16:B35,"AMPLIACION",G16:G35) -> 0 | H36: =SUMIF(B16:B35,"AMPLIACION",H16:H35) -> 0 | I36: =SUMIF(B16:B35,"AMPLIACION",I16:I35) -> 0 | J36: =SUMIF(B16:B35,"AMPLIACION",J16:J35) -> 0 | K36: =SUMIF(B16:B35,"AMPLIACION",K16:K35) -> 0 | L36: =SUMIF(B16:B35,"AMPLIACION",L16:L35) -> 0 | M36: =SUM(G36,I36,J36,K36,L36) -> 0 | N36: =IF(F36=0,0,(F36-G36-J36-K36-I36-L36)/F36) -> 0 | O36: =IF(F36=0,0,(F36-G36/0.93-I36/0.93-J36/0.93-K36-L36)/F36) -> 0
B37: TOTAL REESTIMACIONES | F37: =SUMIF(B16:B35,"REESTIMACION",F16:F35) -> 0 | G37: =SUMIF(B16:B35,"REESTIMACION",G16:G35) -> 0 | H37: =SUMIF(B16:B35,"REESTIMACION",H16:H35) -> 0 | I37: =SUMIF(B16:B35,"REESTIMACION",I16:I35) -> 0 | J37: =SUMIF(B16:B35,"REESTIMACION",J16:J35) -> 0 | K37: =SUMIF(B16:B35,"REESTIMACION",K16:K35) -> 0 | L37: =SUMIF(B16:B35,"REESTIMACION",L16:L35) -> 0 | M37: =SUM(G37,I37,J37,K37,L37) -> 0 | N37: =IF(F37=0,0,(F37-G37-J37-K37-I37-L37)/F37) -> 0 | O37: =IF(F37=0,0,(F37-G37/0.93-I37/0.93-J37/0.93-K37-L37)/F37) -> 0
B48: Comentarios adicionales Cost Overview
B49: 28/04/2026 CORE pre-rellenado automáticamente desde PPO 20250256445. Variables SAP/SF pendientes documentadas en hoja Trazabilidad_RPA.

Sheet Resources
B2: WBS-Element | C2: ='Project Infor'!C10 -> var2_SAP_PEP_WBS | D2: ='Project Infor'!C11 -> Smart Airport en la nueva terminal de Puerto Vallarta
B5: Equipo GETRONICS. Costes hora por perfil. | E5: (!) IMPORTANTE: se debe indicar si cada perfil es o no INTERCO
B6: COD EMPLEADO | C6: INICIALES | D6: INTERCO | E6: ROL | F6: ='Project Infor'!C8 -> 45962 | G6: =EOMONTH(F6,1) -> 46022 | H6: =EOMONTH(G6,1) -> 46053 | I6: =EOMONTH(H6,1) -> 46081 | J6: =EOMONTH(I6,1) -> 46112 | K6: =EOMONTH(J6,1) -> 46142 | L6: =EOMONTH(K6,1) -> 46173 | M6: =EOMONTH(L6,1) -> 46203 | N6: =EOMONTH(M6,1) -> 46234 | ... AD6: =EOMONTH(AC6,1) -> 46721
B7: var10_SAP_CodEmpleado_JP | C7: JP | D7: NO | E7: Jefe Proyecto | F7: 40 | G7: 40 | H7: 40 | I7: 40 | J7: 40 | K7: 40 | L7: 40 | M7: 40 | N7: 40 | O7: 40 | P7: 40 | Q7: 40
B8: var11_SAP_CodEmpleado_CSS | C8: CSS | D8: INTERCO | E8: Consultor Smart Spaces | F8: 26 | G8: 26 | H8: 26 | I8: 26 | J8: 26 | K8: 26 | L8: 26 | M8: 26 | N8: 26 | O8: 26 | P8: 26 | Q8: 26
B9: var12_SAP_CodEmpleado_CJSS | C9: CJSS | D9: INTERCO | E9: Consultor Junior Smart Spaces | F9: 16 | G9: 16 | H9: 16 | I9: 16 | J9: 16 | K9: 16 | L9: 16 | M9: 16 | N9: 16 | O9: 16 | P9: 16 | Q9: 16
B10: var13_SAP_CodEmpleado_A | C10: A | D10: INTERCO | E10: Arquitecto | F10: 38.75 | G10: 38.75 | H10: 38.75 | I10: 38.75 | J10: 38.75 | K10: 38.75 | L10: 38.75 | M10: 38.75 | N10: 38.75 | O10: 38.75 | P10: 38.75 | Q10: 38.75
B11: var14_SAP_CodEmpleado_II | C11: II | D11: INTERCO | E11: Ingeniero Integración | F11: 27 | G11: 27 | H11: 27 | I11: 27 | J11: 27 | K11: 27 | L11: 27 | M11: 27 | N11: 27 | O11: 27 | P11: 27 | Q11: 27
B12: var15_SAP_CodEmpleado_P | C12: P | D12: INTERCO | E12: Configuración Portal | F12: 20 | G12: 20 | H12: 20 | I12: 20 | J12: 20 | K12: 20 | L12: 20 | M12: 20 | N12: 20 | O12: 20 | P12: 20 | Q12: 20
B13: var16_SAP_CodEmpleado_DG | C13: DG | D13: INTERCO | E13: Diseñador gráfico | F13: 25 | G13: 25 | H13: 25 | I13: 25 | J13: 25 | K13: 25 | L13: 25 | M13: 25 | N13: 25 | O13: 25 | P13: 25 | Q13: 25
B45: Tipo de Roles
B46: COD | C46: DESCRIPCION
B47: PM | C47: Project Manager
B48: CO | C48: Consultor
B49: ANF | C49: Analista Funcional
B50: AP | C50: Analista Programador
B51: PR | C51: Programador
B52: TEST | C52: Tester
B53: ARQ | C53: Arquitecto
B54: SO | C54: Soporte
B55: TS | C55: Tecnico de sistemas
B56: INST | C56: Tecnico Instalaciones
B57: CAU | C57: Soporte CAU
... B61: DG | C61: Diseño Gráfico

Sheet Cost Planning
B2: WBS-Element | C2: ='Project Infor'!C10 -> var2_SAP_PEP_WBS | D2: ='Project Infor'!C11 -> Smart Airport en la nueva terminal de Puerto Vallarta
B5: Equipo GETRONICS | D5: COSTE TOTAL RECURSOS BASELINE | F5: =costerecursosbaselineactual -> 367515.14 | G5: PENDIENTE DE PLANIFICAR | I5: =F5-SUM(F40:AE41) -> 51845.141 | K5: (!) El coste de RECURSOS planificado es mayor que el de la BASELINE
G7: =IF(G8>EOMONTH(FIN,0),"Fin",IF(G8>FECHA,"Prev","Real")) -> Real | H7: =IF(H8>EOMONTH(FIN,0),"Fin",IF(H8>FECHA,"Prev","Real")) -> Real | I7: =IF(I8>EOMONTH(FIN,0),"Fin",IF(I8>FECHA,"Prev","Real")) -> Real | J7: =IF(J8>EOMONTH(FIN,0),"Fin",IF(J8>FECHA,"Prev","Real")) -> Real | K7: =IF(K8>EOMONTH(FIN,0),"Fin",IF(K8>FECHA,"Prev","Real")) -> Real | L7: =IF(L8>EOMONTH(FIN,0),"Fin",IF(L8>FECHA,"Prev","Real")) -> Real | M7: =IF(M8>EOMONTH(FIN,0),"Fin",IF(M8>FECHA,"Prev","Real")) -> Prev | N7: =IF(N8>EOMONTH(FIN,0),"Fin",IF(N8>FECHA,"Prev","Real")) -> Prev | ... AE7: =IF(AE8>EOMONTH(FIN,0),"Fin",IF(AE8>FECHA,"Prev","Real")) -> Fin
B8: COD EMPLEADO | C8: INICIALES | D8: INTERCO | E8: ROL | F8: CODIGO INTERCO | G8: ='Project Infor'!C8 -> 45962 | H8: =EOMONTH(G8,1) -> 46022 | I8: =EOMONTH(H8,1) -> 46053 | J8: =EOMONTH(I8,1) -> 46081 | K8: =EOMONTH(J8,1) -> 46112 | L8: =EOMONTH(K8,1) -> 46142 | M8: =EOMONTH(L8,1) -> 46173 | N8: =EOMONTH(M8,1) -> 46203 | O8: =EOMONTH(N8,1) -> 46234 | ... AE8: =EOMONTH(AD8,1) -> 46721
B9: HORAS TOTALES RECURSOS entidad PROYECTO + INTERCO | F9: ='Project Infor'!C46 -> 0 | G9: =SUM(G10:G39) -> 610 | H9: =SUM(H10:H39) -> 610 | I9: =SUM(I10:I39) -> 1063 | J9: =SUM(J10:J39) -> 1063 | K9: =SUM(K10:K39) -> 1063 | L9: =SUM(L10:L39) -> 1063 | M9: =SUM(M10:M39) -> 1063 | N9: =SUM(N10:N39) -> 1063 | ... AE9: =SUM(AE10:AE39) -> 0
B10: =IF(Resources!B7="","",Resources!B7) -> var10_SAP_CodEmpleado_JP | C10: =IF(Resources!C7="","",Resources!C7) -> JP | D10: =IF(Resources!D7="","",Resources!D7) -> NO | E10: =IF(Resources!E7="","",Resources!E7) -> Jefe Proyecto | G10: 10 | H10: 10 | I10: 46 | J10: 46 | K10: 46 | L10: 46 | M10: 46 | N10: 46 | O10: 46 | P10: 46 | Q10: 46 | R10: 46
B11: =IF(Resources!B8="","",Resources!B8) -> var11_SAP_CodEmpleado_CSS | C11: =IF(Resources!C8="","",Resources!C8) -> CSS | D11: =IF(Resources!D8="","",Resources!D8) -> INTERCO | E11: =IF(Resources!E8="","",Resources!E8) -> Consultor Smart Spaces | G11: 150 | H11: 150 | I11: 144 | J11: 144 | K11: 144 | L11: 144 | M11: 144 | N11: 144 | O11: 144 | P11: 144 | Q11: 144 | R11: 144
B12: =IF(Resources!B9="","",Resources!B9) -> var12_SAP_CodEmpleado_CJSS | C12: =IF(Resources!C9="","",Resources!C9) -> CJSS | D12: =IF(Resources!D9="","",Resources!D9) -> INTERCO | E12: =IF(Resources!E9="","",Resources!E9) -> Consultor Junior Smart Spaces | G12: 60 | H12: 60 | I12: 147 | J12: 147 | K12: 147 | L12: 147 | M12: 147 | N12: 147 | O12: 147 | P12: 147 | Q12: 147 | R12: 147
B13: =IF(Resources!B10="","",Resources!B10) -> var13_SAP_CodEmpleado_A | C13: =IF(Resources!C10="","",Resources!C10) -> A | D13: =IF(Resources!D10="","",Resources!D10) -> INTERCO | E13: =IF(Resources!E10="","",Resources!E10) -> Arquitecto | G13: 210 | H13: 210 | I13: 154 | J13: 154 | K13: 154 | L13: 154 | M13: 154 | N13: 154 | O13: 154 | P13: 154 | Q13: 154 | R13: 154
B14: =IF(Resources!B11="","",Resources!B11) -> var14_SAP_CodEmpleado_II | C14: =IF(Resources!C11="","",Resources!C11) -> II | D14: =IF(Resources!D11="","",Resources!D11) -> INTERCO | E14: =IF(Resources!E11="","",Resources!E11) -> Ingeniero Integración | G14: 60 | H14: 60 | I14: 380 | J14: 380 | K14: 380 | L14: 380 | M14: 380 | N14: 380 | O14: 380 | P14: 380 | Q14: 380 | R14: 380
B15: =IF(Resources!B12="","",Resources!B12) -> var15_SAP_CodEmpleado_P | C15: =IF(Resources!C12="","",Resources!C12) -> P | D15: =IF(Resources!D12="","",Resources!D12) -> INTERCO | E15: =IF(Resources!E12="","",Resources!E12) -> Configuración Portal | G15: 120 | H15: 120 | I15: 176 | J15: 176 | K15: 176 | L15: 176 | M15: 176 | N15: 176 | O15: 176 | P15: 176 | Q15: 176 | R15: 176
B16: =IF(Resources!B13="","",Resources!B13) -> var16_SAP_CodEmpleado_DG | C16: =IF(Resources!C13="","",Resources!C13) -> DG | D16: =IF(Resources!D13="","",Resources!D13) -> INTERCO | E16: =IF(Resources!E13="","",Resources!E13) -> Diseñador gráfico | I16: 16 | J16: 16 | K16: 16 | L16: 16 | M16: 16 | N16: 16 | O16: 16 | P16: 16 | Q16: 16 | R16: 16
B17: =IF(Resources!B14="","",Resources!B14) | C17: =IF(Resources!C14="","",Resources!C14) | D17: =IF(Resources!D14="","",Resources!D14) | E17: =IF(Resources!E14="","",Resources!E14)
B18: =IF(Resources!B15="","",Resources!B15) | C18: =IF(Resources!C15="","",Resources!C15) | D18: =IF(Resources!D15="","",Resources!D15) | E18: =IF(Resources!E15="","",Resources!E15)
B19: =IF(Resources!B16="","",Resources!B16) | C19: =IF(Resources!C16="","",Resources!C16) | D19: =IF(Resources!D16="","",Resources!D16) | E19: =IF(Resources!E16="","",Resources!E16)
B20: =IF(Resources!B17="","",Resources!B17) | C20: =IF(Resources!C17="","",Resources!C17) | D20: =IF(Resources!D17="","",Resources!D17) | E20: =IF(Resources!E17="","",Resources!E17)
B21: =IF(Resources!B18="","",Resources!B18) | C21: =IF(Resources!C18="","",Resources!C18) | D21: =IF(Resources!D18="","",Resources!D18) | E21: =IF(Resources!E18="","",Resources!E18)
B22: =IF(Resources!B19="","",Resources!B19) | C22: =IF(Resources!C19="","",Resources!C19) | D22: =IF(Resources!D19="","",Resources!D19) | E22: =IF(Resources!E19="","",Resources!E19)
B23: =IF(Resources!B20="","",Resources!B20) | C23: =IF(Resources!C20="","",Resources!C20) | D23: =IF(Resources!D20="","",Resources!D20) | E23: =IF(Resources!E20="","",Resources!E20)
B24: =IF(Resources!B21="","",Resources!B21) | C24: =IF(Resources!C21="","",Resources!C21) | D24: =IF(Resources!D21="","",Resources!D21) | E24: =IF(Resources!E21="","",Resources!E21)
B25: =IF(Resources!B22="","",Resources!B22) | C25: =IF(Resources!C22="","",Resources!C22) | D25: =IF(Resources!D22="","",Resources!D22) | E25: =IF(Resources!E22="","",Resources!E22)
B26: =IF(Resources!B23="","",Resources!B23) | C26: =IF(Resources!C23="","",Resources!C23) | D26: =IF(Resources!D23="","",Resources!D23) | E26: =IF(Resources!E23="","",Resources!E23)
B27: =IF(Resources!B24="","",Resources!B24) | C27: =IF(Resources!C24="","",Resources!C24) | D27: =IF(Resources!D24="","",Resources!D24) | E27: =IF(Resources!E24="","",Resources!E24)
B28: =IF(Resources!B25="","",Resources!B25) | C28: =IF(Resources!C25="","",Resources!C25) | D28: =IF(Resources!D25="","",Resources!D25) | E28: =IF(Resources!E25="","",Resources!E25)
... B39: =IF(Resources!B36="","",Resources!B36) | C39: =IF(Resources!C36="","",Resources!C36) | D39: =IF(Resources!D36="","",Resources!D36) | E39: =IF(Resources!E36="","",Resources!E36)
B40: COSTE TOTAL RECURSOS entidad PROYECTO (euros) | F40: ='Project Infor'!C47 -> 0 | G40: {=SUMPRODUCT(($D$10:$D$39="NO")*1,G$10:G$39,Resources!F7:F36)+G42} -> 400 | H40: {=SUMPRODUCT(($D$10:$D$39="NO")*1,H$10:H$39,Resources!G7:G36)+H42} -> 400 | I40: {=SUMPRODUCT(($D$10:$D$39="NO")*1,I$10:I$39,Resources!H7:H36)+I42} -> 1840 | J40: {=SUMPRODUCT(($D$10:$D$39="NO")*1,J$10:J$39,Resources!I7:I36)+J42} -> 1840 | K40: {=SUMPRODUCT(($D$10:$D$39="NO")*1,K$10:K$39,Resources!J7:J36)+K42} -> 1840 | L40: {=SUMPRODUCT(($D$10:$D$39="NO")*1,L$10:L$39,Resources!K7:K36)+L42} -> 1840 | M40: {=SUMPRODUCT(($D$10:$D$39="NO")*1,M$10:M$39,Resources!L7:L36)+M42} -> 1840 | N40: {=SUMPRODUCT(($D$10:$D$39="NO")*1,N$10:N$39,Resources!M7:M36)+N42} -> 1840 | ... AE40: {=SUMPRODUCT(($D$10:$D$39="NO")*1,AE$10:AE$39,Resources!AD7:AD36)+AE42} -> 0
B41: COSTE TOTAL RECURSOS INTERCO (euros) | G41: {=SUMPRODUCT(($D$10:$D$39="INTERCO")*1,G$10:G$39,Resources!F7:F36)+G43} -> 17017.5 | H41: {=SUMPRODUCT(($D$10:$D$39="INTERCO")*1,H$10:H$39,Resources!G7:G36)+H43} -> 17017.5 | I41: {=SUMPRODUCT(($D$10:$D$39="INTERCO")*1,I$10:I$39,Resources!H7:H36)+I43} -> 26243.5 | J41: {=SUMPRODUCT(($D$10:$D$39="INTERCO")*1,J$10:J$39,Resources!I7:I36)+J43} -> 26243.5 | K41: {=SUMPRODUCT(($D$10:$D$39="INTERCO")*1,K$10:K$39,Resources!J7:J36)+K43} -> 26243.5 | L41: {=SUMPRODUCT(($D$10:$D$39="INTERCO")*1,L$10:L$39,Resources!K7:K36)+L43} -> 26243.5 | M41: {=SUMPRODUCT(($D$10:$D$39="INTERCO")*1,M$10:M$39,Resources!L7:L36)+M43} -> 26243.5 | N41: {=SUMPRODUCT(($D$10:$D$39="INTERCO")*1,N$10:N$39,Resources!M7:M36)+N43} -> 26243.5 | ... AE41: {=SUMPRODUCT(($D$10:$D$39="INTERCO")*1,AE$10:AE$39,Resources!AD7:AD36)+AE43} -> 0
C42: AJUSTE con SAP (en EUROS) para perfiles NO INTERCO
C43: AJUSTE con SAP (en EUROS) para perfiles INTERCO
D46: PLANIFICADO BASELINE | E46: PENDIENTE DE PLANIFICAR | G46: ='Project Infor'!C8 -> 45962 | H46: =EOMONTH(G46,1) -> 46022 | I46: =EOMONTH(H46,1) -> 46053 | J46: =EOMONTH(I46,1) -> 46081 | K46: =EOMONTH(J46,1) -> 46112 | L46: =EOMONTH(K46,1) -> 46142 | M46: =EOMONTH(L46,1) -> 46173 | N46: =EOMONTH(M46,1) -> 46203 | O46: =EOMONTH(N46,1) -> 46234 | ... AE46: =EOMONTH(AD46,1) -> 46721
B47: RIESGOS | C47: "accrual future loss" | D47: ='Cost Overview'!I8 -> 18375.757 | E47: =D47-SUM(G47:AE47) -> 0 | R47: 18375.757
B48: GARANTIA | C48: "Warranty Provisions" | D48: ='Cost Overview'!J8 -> 0 | E48: =D48-SUM(G48:AE48) -> 0
B50: GASTOS | D50: COSTE TOTAL GASTOS BASELINE | F50: ='Cost Overview'!K8 -> 7400 | G50: PENDIENTE DE PLANIFICAR | I50: =F50-SUM(F59:AE59) -> 0 | K50: (!) El coste de GASTOS planificado es mayor que el de la BASELINE
B52: TIPO GASTO | C52: DESCRIPCION GASTO | D52: INFORMACION ADICIONAL | G52: ='Project Infor'!C8 -> 45962 | H52: =EOMONTH(G52,1) -> 46022 | I52: =EOMONTH(H52,1) -> 46053 | J52: =EOMONTH(I52,1) -> 46081 | K52: =EOMONTH(J52,1) -> 46112 | L52: =EOMONTH(K52,1) -> 46142 | M52: =EOMONTH(L52,1) -> 46173 | N52: =EOMONTH(M52,1) -> 46203 | O52: =EOMONTH(N52,1) -> 46234 | ... AE52: =EOMONTH(AD52,1) -> 46721
B53: Travelling Expenses | C53: Agencia de Viajes | D53: PPO | I53: 650 | J53: 650 | K53: 650 | L53: 650 | M53: 650 | N53: 650 | O53: 650 | P53: 650 | Q53: 650 | R53: 650
B54: Otros | C54: Expenses/Gastos | D54: PPO | I54: 90 | J54: 90 | K54: 90 | L54: 90 | M54: 90 | N54: 90 | O54: 90 | P54: 90 | Q54: 90 | R54: 90
B59: TOTAL GASTOS | F59: ='Project Infor'!C48 -> 0 | G59: =SUM(G53:G58) -> 0 | H59: =SUM(H53:H58) -> 0 | I59: =SUM(I53:I58) -> 740 | J59: =SUM(J53:J58) -> 740 | K59: =SUM(K53:K58) -> 740 | L59: =SUM(L53:L58) -> 740 | M59: =SUM(M53:M58) -> 740 | N59: =SUM(N53:N58) -> 740 | ... AE59: =SUM(AE53:AE58) -> 0
B61: COMPRAS | D61: COSTE TOTAL COMPRAS BASELINE | F61: ='Cost Overview'!L8 -> 40000 | G61: PENDIENTE DE PLANIFICAR | I61: =F61-SUM(F74:AE74) -> 0 | K61: (!) El coste de COMPRAS planificado es mayor que el de la BASELINE
B63: PROVEEDOR | C63: DESCRIPCION COMPRA | D63: PO COMPRA | E63: INFOR ARIBA | G63: ='Project Infor'!C8 -> 45962 | H63: =EOMONTH(G63,1) -> 46022 | I63: =EOMONTH(H63,1) -> 46053 | J63: =EOMONTH(I63,1) -> 46081 | K63: =EOMONTH(J63,1) -> 46112 | L63: =EOMONTH(K63,1) -> 46142 | M63: =EOMONTH(L63,1) -> 46173 | N63: =EOMONTH(M63,1) -> 46203 | O63: =EOMONTH(N63,1) -> 46234 | ... AE63: =EOMONTH(AD63,1) -> 46721
B64: var20_SAP_Proveedor_Subcontrataciones | C64: Trabajos on site | D64: var30_SAP_PO_Compra | E64: var40_SAP_Ariba | G64: 20000 | H64: 20000
B74: TOTAL COMPRAS | F74: ='Project Infor'!C49 -> 0 | G74: =SUM(G64:G73) -> 20000 | H74: =SUM(H64:H73) -> 20000 | I74: =SUM(I64:I73) -> 0 | J74: =SUM(J64:J73) -> 0 | K74: =SUM(K64:K73) -> 0 | L74: =SUM(L64:L73) -> 0 | M74: =SUM(M64:M73) -> 0 | N74: =SUM(N64:N73) -> 0 | ... AE74: =SUM(AE64:AE73) -> 0
B85: Tipos Gasto
B86: Travelling Expenses
B87: Recruitment Fees
B88: Trainning Costs
B89: Salaries varios (becas,…)
B90: Fees
B91: Otros

Sheet Monthly View
B2: WBS-Element | C2: ='Project Infor'!C10 -> var2_SAP_PEP_WBS | D2: ='Project Infor'!C11 -> Smart Airport en la nueva terminal de Puerto Vallarta
E4: =IF(E5>EOMONTH(FIN,0),"Fin",IF(E5>FECHA,"Prev","Real")) -> Real | F4: =IF(F5>EOMONTH(FIN,0),"Fin",IF(F5>FECHA,"Prev","Real")) -> Real | G4: =IF(G5>EOMONTH(FIN,0),"Fin",IF(G5>FECHA,"Prev","Real")) -> Real | H4: =IF(H5>EOMONTH(FIN,0),"Fin",IF(H5>FECHA,"Prev","Real")) -> Real | I4: =IF(I5>EOMONTH(FIN,0),"Fin",IF(I5>FECHA,"Prev","Real")) -> Real | J4: =IF(J5>EOMONTH(FIN,0),"Fin",IF(J5>FECHA,"Prev","Real")) -> Real | K4: =IF(K5>EOMONTH(FIN,0),"Fin",IF(K5>FECHA,"Prev","Real")) -> Prev | L4: =IF(L5>EOMONTH(FIN,0),"Fin",IF(L5>FECHA,"Prev","Real")) -> Prev | ... AC4: =IF(AC5>EOMONTH(FIN,0),"Fin",IF(AC5>FECHA,"Prev","Real")) -> Fin
B5: LINEA BASE ACTUAL | D5: INICIAL | E5: ='Project Infor'!C8 -> 45962 | F5: =EOMONTH(E5,1) -> 46022 | G5: =EOMONTH(F5,1) -> 46053 | H5: =EOMONTH(G5,1) -> 46081 | I5: =EOMONTH(H5,1) -> 46112 | J5: =EOMONTH(I5,1) -> 46142 | K5: =EOMONTH(J5,1) -> 46173 | L5: =EOMONTH(K5,1) -> 46203 | M5: =EOMONTH(L5,1) -> 46234 | ... AC5: =EOMONTH(AB5,1) -> 46721
B6: + INGRESOS PREVISTOS | D6: ='Project Infor'!C28 -> 583896.55 | E6: =D6+SUMIF('Cost Overview'!$T$16:$T$35,(YEAR(E$5)&MONTH(E$5)),'Cost Overview'!$F$16:$F$35) -> 583896.55 | F6: =E6+SUMIF('Cost Overview'!$T$16:$T$35,(YEAR(F$5)&MONTH(F$5)),'Cost Overview'!$F$16:$F$35) -> 583896.55 | G6: =F6+SUMIF('Cost Overview'!$T$16:$T$35,(YEAR(G$5)&MONTH(G$5)),'Cost Overview'!$F$16:$F$35) -> 583896.55 | H6: =G6+SUMIF('Cost Overview'!$T$16:$T$35,(YEAR(H$5)&MONTH(H$5)),'Cost Overview'!$F$16:$F$35) -> 583896.55 | I6: =H6+SUMIF('Cost Overview'!$T$16:$T$35,(YEAR(I$5)&MONTH(I$5)),'Cost Overview'!$F$16:$F$35) -> 583896.55 | J6: =I6+SUMIF('Cost Overview'!$T$16:$T$35,(YEAR(J$5)&MONTH(J$5)),'Cost Overview'!$F$16:$F$35) -> 583896.55 | K6: =J6+SUMIF('Cost Overview'!$T$16:$T$35,(YEAR(K$5)&MONTH(K$5)),'Cost Overview'!$F$16:$F$35) -> 583896.55 | L6: =K6+SUMIF('Cost Overview'!$T$16:$T$35,(YEAR(L$5)&MONTH(L$5)),'Cost Overview'!$F$16:$F$35) -> 583896.55 | ... AC6: =AB6+SUMIF('Cost Overview'!$T$16:$T$35,(YEAR(AC$5)&MONTH(AC$5)),'Cost Overview'!$F$16:$F$35) -> 583896.55
B7: HORAS | D7: ='Project Infor'!C29 -> 13570 | E7: =D7+SUMIF('Cost Overview'!$T$16:$T$35,(YEAR(E$5)&MONTH(E$5)),'Cost Overview'!$H$16:$H$35) -> 13570 | F7: =E7+SUMIF('Cost Overview'!$T$16:$T$35,(YEAR(F$5)&MONTH(F$5)),'Cost Overview'!$H$16:$H$35) -> 13570 | G7: =F7+SUMIF('Cost Overview'!$T$16:$T$35,(YEAR(G$5)&MONTH(G$5)),'Cost Overview'!$H$16:$H$35) -> 13570 | H7: =G7+SUMIF('Cost Overview'!$T$16:$T$35,(YEAR(H$5)&MONTH(H$5)),'Cost Overview'!$H$16:$H$35) -> 13570 | I7: =H7+SUMIF('Cost Overview'!$T$16:$T$35,(YEAR(I$5)&MONTH(I$5)),'Cost Overview'!$H$16:$H$35) -> 13570 | J7: =I7+SUMIF('Cost Overview'!$T$16:$T$35,(YEAR(J$5)&MONTH(J$5)),'Cost Overview'!$H$16:$H$35) -> 13570 | K7: =J7+SUMIF('Cost Overview'!$T$16:$T$35,(YEAR(K$5)&MONTH(K$5)),'Cost Overview'!$H$16:$H$35) -> 13570 | L7: =K7+SUMIF('Cost Overview'!$T$16:$T$35,(YEAR(L$5)&MONTH(L$5)),'Cost Overview'!$H$16:$H$35) -> 13570 | ... AC7: =AB7+SUMIF('Cost Overview'!$T$16:$T$35,(YEAR(AC$5)&MONTH(AC$5)),'Cost Overview'!$H$16:$H$35) -> 13570
B8: - COSTE RECURSOS | D8: ='Project Infor'!C30 -> 367515.14 | E8: =D8+SUMIF('Cost Overview'!$T$16:$T$35,(YEAR(E$5)&MONTH(E$5)),'Cost Overview'!$G$16:$G$35) -> 367515.14 | F8: =E8+SUMIF('Cost Overview'!$T$16:$T$35,(YEAR(F$5)&MONTH(F$5)),'Cost Overview'!$G$16:$G$35) -> 367515.14 | G8: =F8+SUMIF('Cost Overview'!$T$16:$T$35,(YEAR(G$5)&MONTH(G$5)),'Cost Overview'!$G$16:$G$35) -> 367515.14 | H8: =G8+SUMIF('Cost Overview'!$T$16:$T$35,(YEAR(H$5)&MONTH(H$5)),'Cost Overview'!$G$16:$G$35) -> 367515.14 | I8: =H8+SUMIF('Cost Overview'!$T$16:$T$35,(YEAR(I$5)&MONTH(I$5)),'Cost Overview'!$G$16:$G$35) -> 367515.14 | J8: =I8+SUMIF('Cost Overview'!$T$16:$T$35,(YEAR(J$5)&MONTH(J$5)),'Cost Overview'!$G$16:$G$35) -> 367515.14 | K8: =J8+SUMIF('Cost Overview'!$T$16:$T$35,(YEAR(K$5)&MONTH(K$5)),'Cost Overview'!$G$16:$G$35) -> 367515.14 | L8: =K8+SUMIF('Cost Overview'!$T$16:$T$35,(YEAR(L$5)&MONTH(L$5)),'Cost Overview'!$G$16:$G$35) -> 367515.14 | ... AC8: =AB8+SUMIF('Cost Overview'!$T$16:$T$35,(YEAR(AC$5)&MONTH(AC$5)),'Cost Overview'!$G$16:$G$35) -> 367515.14
B9: - RIESGOS | D9: ='Project Infor'!C31 -> 18375.757 | E9: =D9+SUMIF('Cost Overview'!$T$16:$T$35,(YEAR(E$5)&MONTH(E$5)),'Cost Overview'!$I$16:$I$35) -> 18375.757 | F9: =E9+SUMIF('Cost Overview'!$T$16:$T$35,(YEAR(F$5)&MONTH(F$5)),'Cost Overview'!$I$16:$I$35) -> 18375.757 | G9: =F9+SUMIF('Cost Overview'!$T$16:$T$35,(YEAR(G$5)&MONTH(G$5)),'Cost Overview'!$I$16:$I$35) -> 18375.757 | H9: =G9+SUMIF('Cost Overview'!$T$16:$T$35,(YEAR(H$5)&MONTH(H$5)),'Cost Overview'!$I$16:$I$35) -> 18375.757 | I9: =H9+SUMIF('Cost Overview'!$T$16:$T$35,(YEAR(I$5)&MONTH(I$5)),'Cost Overview'!$I$16:$I$35) -> 18375.757 | J9: =I9+SUMIF('Cost Overview'!$T$16:$T$35,(YEAR(J$5)&MONTH(J$5)),'Cost Overview'!$I$16:$I$35) -> 18375.757 | K9: =J9+SUMIF('Cost Overview'!$T$16:$T$35,(YEAR(K$5)&MONTH(K$5)),'Cost Overview'!$I$16:$I$35) -> 18375.757 | L9: =K9+SUMIF('Cost Overview'!$T$16:$T$35,(YEAR(L$5)&MONTH(L$5)),'Cost Overview'!$I$16:$I$35) -> 18375.757 | ... AC9: =AB9+SUMIF('Cost Overview'!$T$16:$T$35,(YEAR(AC$5)&MONTH(AC$5)),'Cost Overview'!$I$16:$I$35) -> 18375.757
B10: - GARANTIA | D10: ='Project Infor'!C32 -> 0 | E10: =D10+SUMIF('Cost Overview'!$T$16:$T$35,(YEAR(E$5)&MONTH(E$5)),'Cost Overview'!$J$16:$J$35) -> 0 | F10: =E10+SUMIF('Cost Overview'!$T$16:$T$35,(YEAR(F$5)&MONTH(F$5)),'Cost Overview'!$J$16:$J$35) -> 0 | G10: =F10+SUMIF('Cost Overview'!$T$16:$T$35,(YEAR(G$5)&MONTH(G$5)),'Cost Overview'!$J$16:$J$35) -> 0 | H10: =G10+SUMIF('Cost Overview'!$T$16:$T$35,(YEAR(H$5)&MONTH(H$5)),'Cost Overview'!$J$16:$J$35) -> 0 | I10: =H10+SUMIF('Cost Overview'!$T$16:$T$35,(YEAR(I$5)&MONTH(I$5)),'Cost Overview'!$J$16:$J$35) -> 0 | J10: =I10+SUMIF('Cost Overview'!$T$16:$T$35,(YEAR(J$5)&MONTH(J$5)),'Cost Overview'!$J$16:$J$35) -> 0 | K10: =J10+SUMIF('Cost Overview'!$T$16:$T$35,(YEAR(K$5)&MONTH(K$5)),'Cost Overview'!$J$16:$J$35) -> 0 | L10: =K10+SUMIF('Cost Overview'!$T$16:$T$35,(YEAR(L$5)&MONTH(L$5)),'Cost Overview'!$J$16:$J$35) -> 0 | ... AC10: =AB10+SUMIF('Cost Overview'!$T$16:$T$35,(YEAR(AC$5)&MONTH(AC$5)),'Cost Overview'!$J$16:$J$35) -> 0
B11: - GASTOS | D11: ='Project Infor'!C33 -> 7400 | E11: =D11+SUMIF('Cost Overview'!$T$16:$T$35,(YEAR(E$5)&MONTH(E$5)),'Cost Overview'!$K$16:$K$35) -> 7400 | F11: =E11+SUMIF('Cost Overview'!$T$16:$T$35,(YEAR(F$5)&MONTH(F$5)),'Cost Overview'!$K$16:$K$35) -> 7400 | G11: =F11+SUMIF('Cost Overview'!$T$16:$T$35,(YEAR(G$5)&MONTH(G$5)),'Cost Overview'!$K$16:$K$35) -> 7400 | H11: =G11+SUMIF('Cost Overview'!$T$16:$T$35,(YEAR(H$5)&MONTH(H$5)),'Cost Overview'!$K$16:$K$35) -> 7400 | I11: =H11+SUMIF('Cost Overview'!$T$16:$T$35,(YEAR(I$5)&MONTH(I$5)),'Cost Overview'!$K$16:$K$35) -> 7400 | J11: =I11+SUMIF('Cost Overview'!$T$16:$T$35,(YEAR(J$5)&MONTH(J$5)),'Cost Overview'!$K$16:$K$35) -> 7400 | K11: =J11+SUMIF('Cost Overview'!$T$16:$T$35,(YEAR(K$5)&MONTH(K$5)),'Cost Overview'!$K$16:$K$35) -> 7400 | L11: =K11+SUMIF('Cost Overview'!$T$16:$T$35,(YEAR(L$5)&MONTH(L$5)),'Cost Overview'!$K$16:$K$35) -> 7400 | ... AC11: =AB11+SUMIF('Cost Overview'!$T$16:$T$35,(YEAR(AC$5)&MONTH(AC$5)),'Cost Overview'!$K$16:$K$35) -> 7400
B12: - COMPRAS | D12: ='Project Infor'!C34 -> 40000 | E12: =D12+SUMIF('Cost Overview'!$T$16:$T$35,(YEAR(E$5)&MONTH(E$5)),'Cost Overview'!$L$16:$L$35) -> 40000 | F12: =E12+SUMIF('Cost Overview'!$T$16:$T$35,(YEAR(F$5)&MONTH(F$5)),'Cost Overview'!$L$16:$L$35) -> 40000 | G12: =F12+SUMIF('Cost Overview'!$T$16:$T$35,(YEAR(G$5)&MONTH(G$5)),'Cost Overview'!$L$16:$L$35) -> 40000 | H12: =G12+SUMIF('Cost Overview'!$T$16:$T$35,(YEAR(H$5)&MONTH(H$5)),'Cost Overview'!$L$16:$L$35) -> 40000 | I12: =H12+SUMIF('Cost Overview'!$T$16:$T$35,(YEAR(I$5)&MONTH(I$5)),'Cost Overview'!$L$16:$L$35) -> 40000 | J12: =I12+SUMIF('Cost Overview'!$T$16:$T$35,(YEAR(J$5)&MONTH(J$5)),'Cost Overview'!$L$16:$L$35) -> 40000 | K12: =J12+SUMIF('Cost Overview'!$T$16:$T$35,(YEAR(K$5)&MONTH(K$5)),'Cost Overview'!$L$16:$L$35) -> 40000 | L12: =K12+SUMIF('Cost Overview'!$T$16:$T$35,(YEAR(L$5)&MONTH(L$5)),'Cost Overview'!$L$16:$L$35) -> 40000 | ... AC12: =AB12+SUMIF('Cost Overview'!$T$16:$T$35,(YEAR(AC$5)&MONTH(AC$5)),'Cost Overview'!$L$16:$L$35) -> 40000
B13: COSTE DIRECTO | D13: =SUM(D8:D12) -> 433290.9 | E13: =SUM(E8:E12) -> 433290.9 | F13: =SUM(F8:F12) -> 433290.9 | G13: =SUM(G8:G12) -> 433290.9 | H13: =SUM(H8:H12) -> 433290.9 | I13: =SUM(I8:I12) -> 433290.9 | J13: =SUM(J8:J12) -> 433290.9 | K13: =SUM(K8:K12) -> 433290.9 | ... AC13: =SUM(AC8:AC12) -> 433290.9
B14: MARGEN DIRECTO (euros) | D14: =D6-D13 -> 150605.65 | E14: =E6-E13 -> 150605.65 | F14: =F6-F13 -> 150605.65 | G14: =G6-G13 -> 150605.65 | H14: =H6-H13 -> 150605.65 | I14: =I6-I13 -> 150605.65 | J14: =J6-J13 -> 150605.65 | K14: =K6-K13 -> 150605.65 | ... AC14: =AC6-AC13 -> 150605.65
B15: MARGEN DIRECTO (%) | D15: =IF(D6=0,0,(D6-D13)/D6) -> 0.25793208 | E15: =IF(E6=0,0,(E6-E13)/E6) -> 0.25793208 | F15: =IF(F6=0,0,(F6-F13)/F6) -> 0.25793208 | G15: =IF(G6=0,0,(G6-G13)/G6) -> 0.25793208 | H15: =IF(H6=0,0,(H6-H13)/H6) -> 0.25793208 | I15: =IF(I6=0,0,(I6-I13)/I6) -> 0.25793208 | J15: =IF(J6=0,0,(J6-J13)/J6) -> 0.25793208 | K15: =IF(K6=0,0,(K6-K13)/K6) -> 0.25793208 | ... AC15: =IF(AC6=0,0,(AC6-AC13)/AC6) -> 0.25793208
B17: REALIZADO + PREVISTO MES | E17: ='Project Infor'!C8 -> 45962 | F17: =EOMONTH(E17,1) -> 46022 | G17: =EOMONTH(F17,1) -> 46053 | H17: =EOMONTH(G17,1) -> 46081 | I17: =EOMONTH(H17,1) -> 46112 | J17: =EOMONTH(I17,1) -> 46142 | K17: =EOMONTH(J17,1) -> 46173 | L17: =EOMONTH(K17,1) -> 46203 | M17: =EOMONTH(L17,1) -> 46234 | ... AC17: =EOMONTH(AB17,1) -> 46721
B18: VENTA | E18: =E30-D30 -> 50423.282 | F18: =F30-E30 -> 50423.282 | G18: =G30-F30 -> 38842.132 | H18: =H30-G30 -> 38842.132 | I18: =I30-H30 -> 38842.132 | J18: =J30-I30 -> 38842.132 | K18: =K30-J30 -> 38842.132 | L18: =L30-K30 -> 38842.132 | ... AC18: =AC30-AB30 -> -69865.762
B19: HORAS | E19: =E31-D31 -> 610 | F19: =F31-E31 -> 610 | G19: =G31-F31 -> 1063 | H19: =H31-G31 -> 1063 | I19: =I31-H31 -> 1063 | J19: =J31-I31 -> 1063 | K19: =K31-J31 -> 1063 | L19: =L31-K31 -> 1063 | ... AC19: =AC31-AB31 -> 0
B20: - COSTE RECURSOS | E20: =E32-D32 -> 17417.5 | F20: =F32-E32 -> 17417.5 | G20: =G32-F32 -> 28083.5 | H20: =H32-G32 -> 28083.5 | I20: =I32-H32 -> 28083.5 | J20: =J32-I32 -> 28083.5 | K20: =K32-J32 -> 28083.5 | L20: =L32-K32 -> 28083.5 | ... AC20: =AC32-AB32 -> 0
B21: - RIESGOS | E21: =E33-D33 -> 0 | F21: =F33-E33 -> 0 | G21: =G33-F33 -> 0 | H21: =H33-G33 -> 0 | I21: =I33-H33 -> 0 | J21: =J33-I33 -> 0 | K21: =K33-J33 -> 0 | L21: =L33-K33 -> 0 | ... AC21: =AC33-AB33 -> 0
B22: - GARANTIA | E22: =E34-D34 -> 0 | F22: =F34-E34 -> 0 | G22: =G34-F34 -> 0 | H22: =H34-G34 -> 0 | I22: =I34-H34 -> 0 | J22: =J34-I34 -> 0 | K22: =K34-J34 -> 0 | L22: =L34-K34 -> 0 | ... AC22: =AC34-AB34 -> 0
B23: - GASTOS | E23: =E35-D35 -> 0 | F23: =F35-E35 -> 0 | G23: =G35-F35 -> 740 | H23: =H35-G35 -> 740 | I23: =I35-H35 -> 740 | J23: =J35-I35 -> 740 | K23: =K35-J35 -> 740 | L23: =L35-K35 -> 740 | ... AC23: =AC35-AB35 -> 0
B24: - COMPRAS | E24: =E36-D36 -> 20000 | F24: =F36-E36 -> 20000 | G24: =G36-F36 -> 0 | H24: =H36-G36 -> 0 | I24: =I36-H36 -> 0 | J24: =J36-I36 -> 0 | K24: =K36-J36 -> 0 | L24: =L36-K36 -> 0 | ... AC24: =AC36-AB36 -> 0
B25: COSTE DIRECTO | E25: =SUM(E20:E24) -> 37417.5 | F25: =SUM(F20:F24) -> 37417.5 | G25: =SUM(G20:G24) -> 28823.5 | H25: =SUM(H20:H24) -> 28823.5 | I25: =SUM(I20:I24) -> 28823.5 | J25: =SUM(J20:J24) -> 28823.5 | K25: =SUM(K20:K24) -> 28823.5 | L25: =SUM(L20:L24) -> 28823.5 | ... AC25: =SUM(AC20:AC24) -> 0
B26: MARGEN DIRECTO (euros) | E26: =E18-E25 -> 13005.782 | F26: =F18-F25 -> 13005.782 | G26: =G18-G25 -> 10018.632 | H26: =H18-H25 -> 10018.632 | I26: =I18-I25 -> 10018.632 | J26: =J18-J25 -> 10018.632 | K26: =K18-K25 -> 10018.632 | L26: =L18-L25 -> 10018.632 | ... AC26: =AC18-AC25 -> -69865.762
B27: MARGEN DIRECTO (%) | E27: =IF(E18=0,0,(E18-SUM(E20,E21,E22,E23,E24))/E18) -> 0.25793208 | F27: =IF(F18=0,0,(F18-SUM(F20,F21,F22,F23,F24))/F18) -> 0.25793208 | G27: =IF(G18=0,0,(G18-SUM(G20,G21,G22,G23,G24))/G18) -> 0.25793208 | H27: =IF(H18=0,0,(H18-SUM(H20,H21,H22,H23,H24))/H18) -> 0.25793208 | I27: =IF(I18=0,0,(I18-SUM(I20,I21,I22,I23,I24))/I18) -> 0.25793208 | J27: =IF(J18=0,0,(J18-SUM(J20,J21,J22,J23,J24))/J18) -> 0.25793208 | K27: =IF(K18=0,0,(K18-SUM(K20,K21,K22,K23,K24))/K18) -> 0.25793208 | L27: =IF(L18=0,0,(L18-SUM(L20,L21,L22,L23,L24))/L18) -> 0.25793208 | ... AC27: =IF(AC18=0,0,(AC18-SUM(AC20,AC21,AC22,AC23,AC24))/AC18) -> 1
B29: REALIZADO + PREVISTO ACUMULADO | D29: ANTERIOR | E29: ='Project Infor'!C8 -> 45962 | F29: =EOMONTH(E29,1) -> 46022 | G29: =EOMONTH(F29,1) -> 46053 | H29: =EOMONTH(G29,1) -> 46081 | I29: =EOMONTH(H29,1) -> 46112 | J29: =EOMONTH(I29,1) -> 46142 | K29: =EOMONTH(J29,1) -> 46173 | L29: =EOMONTH(K29,1) -> 46203 | M29: =EOMONTH(L29,1) -> 46234 | ... AC29: =EOMONTH(AB29,1) -> 46721
B30: VENTA ACUMULADA | D30: ='Project Infor'!C45 -> 0 | E30: {=IF(E40,E40,E6*((E32+E33+E34+E35+E36)/(IF(E14<margendirectofinal,E6-E14,pedidobaselineactual-margendirectofinal))))} -> 50423.282 | F30: {=IF(F40,F40,F6*((F32+F33+F34+F35+F36)/(IF(F14<margendirectofinal,F6-F14,pedidobaselineactual-margendirectofinal))))} -> 100846.56 | G30: {=IF(G40,G40,G6*((G32+G33+G34+G35+G36)/(IF(G14<margendirectofinal,G6-G14,pedidobaselineactual-margendirectofinal))))} -> 139688.7 | H30: {=IF(H40,H40,H6*((H32+H33+H34+H35+H36)/(IF(H14<margendirectofinal,H6-H14,pedidobaselineactual-margendirectofinal))))} -> 178530.83 | I30: {=IF(I40,I40,I6*((I32+I33+I34+I35+I36)/(IF(I14<margendirectofinal,I6-I14,pedidobaselineactual-margendirectofinal))))} -> 217372.96 | J30: {=IF(J40,J40,J6*((J32+J33+J34+J35+J36)/(IF(J14<margendirectofinal,J6-J14,pedidobaselineactual-margendirectofinal))))} -> 256215.09 | K30: {=IF(K40,K40,K6*((K32+K33+K34+K35+K36)/(IF(K14<margendirectofinal,K6-K14,pedidobaselineactual-margendirectofinal))))} -> 295057.22 | L30: {=IF(L40,L40,L6*((L32+L33+L34+L35+L36)/(IF(L14<margendirectofinal,L6-L14,pedidobaselineactual-margendirectofinal))))} -> 333899.36 | ... AC30: {=IF(AC40,AC40,AC6*((AC32+AC33+AC34+AC35+AC36)/(IF(AC14<margendirectofinal,AC6-AC14,pedidobaselineactual-margendirectofinal))))} -> 514030.79
B31: HORAS | D31: ='Project Infor'!C46 -> 0 | E31: =D31+LOOKUP(E$5,'Cost Planning'!$G$8:$AE$8,'Cost Planning'!$G$9:$AE$9) -> 610 | F31: =E31+LOOKUP(F$5,'Cost Planning'!$G$8:$AE$8,'Cost Planning'!$G$9:$AE$9) -> 1220 | G31: =F31+LOOKUP(G$5,'Cost Planning'!$G$8:$AE$8,'Cost Planning'!$G$9:$AE$9) -> 2283 | H31: =G31+LOOKUP(H$5,'Cost Planning'!$G$8:$AE$8,'Cost Planning'!$G$9:$AE$9) -> 3346 | I31: =H31+LOOKUP(I$5,'Cost Planning'!$G$8:$AE$8,'Cost Planning'!$G$9:$AE$9) -> 4409 | J31: =I31+LOOKUP(J$5,'Cost Planning'!$G$8:$AE$8,'Cost Planning'!$G$9:$AE$9) -> 5472 | K31: =J31+LOOKUP(K$5,'Cost Planning'!$G$8:$AE$8,'Cost Planning'!$G$9:$AE$9) -> 6535 | L31: =K31+LOOKUP(L$5,'Cost Planning'!$G$8:$AE$8,'Cost Planning'!$G$9:$AE$9) -> 7598 | ... AC31: =AB31+LOOKUP(AC$5,'Cost Planning'!$G$8:$AE$8,'Cost Planning'!$G$9:$AE$9) -> 11850
B32: - COSTE RECURSOS ACUMULADO | D32: ='Project Infor'!C47 -> 0 | E32: =D32+LOOKUP(E$5,'Cost Planning'!$G$8:$AE$8,'Cost Planning'!$G$40:$AE$40)+LOOKUP(E$5,'Cost Planning'!$G$8:$AE$8,'Cost Planning'!$G$41:$AE$41) -> 17417.5 | F32: =E32+LOOKUP(F$5,'Cost Planning'!$G$8:$AE$8,'Cost Planning'!$G$40:$AE$40)+LOOKUP(F$5,'Cost Planning'!$G$8:$AE$8,'Cost Planning'!$G$41:$AE$41) -> 34835 | G32: =F32+LOOKUP(G$5,'Cost Planning'!$G$8:$AE$8,'Cost Planning'!$G$40:$AE$40)+LOOKUP(G$5,'Cost Planning'!$G$8:$AE$8,'Cost Planning'!$G$41:$AE$41) -> 62918.5 | H32: =G32+LOOKUP(H$5,'Cost Planning'!$G$8:$AE$8,'Cost Planning'!$G$40:$AE$40)+LOOKUP(H$5,'Cost Planning'!$G$8:$AE$8,'Cost Planning'!$G$41:$AE$41) -> 91002 | I32: =H32+LOOKUP(I$5,'Cost Planning'!$G$8:$AE$8,'Cost Planning'!$G$40:$AE$40)+LOOKUP(I$5,'Cost Planning'!$G$8:$AE$8,'Cost Planning'!$G$41:$AE$41) -> 119085.5 | J32: =I32+LOOKUP(J$5,'Cost Planning'!$G$8:$AE$8,'Cost Planning'!$G$40:$AE$40)+LOOKUP(J$5,'Cost Planning'!$G$8:$AE$8,'Cost Planning'!$G$41:$AE$41) -> 147169 | K32: =J32+LOOKUP(K$5,'Cost Planning'!$G$8:$AE$8,'Cost Planning'!$G$40:$AE$40)+LOOKUP(K$5,'Cost Planning'!$G$8:$AE$8,'Cost Planning'!$G$41:$AE$41) -> 175252.5 | L32: =K32+LOOKUP(L$5,'Cost Planning'!$G$8:$AE$8,'Cost Planning'!$G$40:$AE$40)+LOOKUP(L$5,'Cost Planning'!$G$8:$AE$8,'Cost Planning'!$G$41:$AE$41) -> 203336 | ... AC32: =AB32+LOOKUP(AC$5,'Cost Planning'!$G$8:$AE$8,'Cost Planning'!$G$40:$AE$40)+LOOKUP(AC$5,'Cost Planning'!$G$8:$AE$8,'Cost Planning'!$G$41:$AE$41) -> 315670
B33: - RIESGOS | E33: =D33+LOOKUP(E$5,'Cost Planning'!$G$8:$AE$8,'Cost Planning'!$G$47:$AE$47) -> 0 | F33: =E33+LOOKUP(F$5,'Cost Planning'!$G$8:$AE$8,'Cost Planning'!$G$47:$AE$47) -> 0 | G33: =F33+LOOKUP(G$5,'Cost Planning'!$G$8:$AE$8,'Cost Planning'!$G$47:$AE$47) -> 0 | H33: =G33+LOOKUP(H$5,'Cost Planning'!$G$8:$AE$8,'Cost Planning'!$G$47:$AE$47) -> 0 | I33: =H33+LOOKUP(I$5,'Cost Planning'!$G$8:$AE$8,'Cost Planning'!$G$47:$AE$47) -> 0 | J33: =I33+LOOKUP(J$5,'Cost Planning'!$G$8:$AE$8,'Cost Planning'!$G$47:$AE$47) -> 0 | K33: =J33+LOOKUP(K$5,'Cost Planning'!$G$8:$AE$8,'Cost Planning'!$G$47:$AE$47) -> 0 | L33: =K33+LOOKUP(L$5,'Cost Planning'!$G$8:$AE$8,'Cost Planning'!$G$47:$AE$47) -> 0 | ... AC33: =AB33+LOOKUP(AC$5,'Cost Planning'!$G$8:$AE$8,'Cost Planning'!$G$47:$AE$47) -> 18375.757
B34: - GARANTIA | E34: =D34+LOOKUP(E$5,'Cost Planning'!$G$8:$AE$8,'Cost Planning'!$G$48:$AE$48) -> 0 | F34: =E34+LOOKUP(F$5,'Cost Planning'!$G$8:$AE$8,'Cost Planning'!$G$48:$AE$48) -> 0 | G34: =F34+LOOKUP(G$5,'Cost Planning'!$G$8:$AE$8,'Cost Planning'!$G$48:$AE$48) -> 0 | H34: =G34+LOOKUP(H$5,'Cost Planning'!$G$8:$AE$8,'Cost Planning'!$G$48:$AE$48) -> 0 | I34: =H34+LOOKUP(I$5,'Cost Planning'!$G$8:$AE$8,'Cost Planning'!$G$48:$AE$48) -> 0 | J34: =I34+LOOKUP(J$5,'Cost Planning'!$G$8:$AE$8,'Cost Planning'!$G$48:$AE$48) -> 0 | K34: =J34+LOOKUP(K$5,'Cost Planning'!$G$8:$AE$8,'Cost Planning'!$G$48:$AE$48) -> 0 | L34: =K34+LOOKUP(L$5,'Cost Planning'!$G$8:$AE$8,'Cost Planning'!$G$48:$AE$48) -> 0 | ... AC34: =AB34+LOOKUP(AC$5,'Cost Planning'!$G$8:$AE$8,'Cost Planning'!$G$48:$AE$48) -> 0
B35: - GASTOS | D35: ='Project Infor'!C48 -> 0 | E35: =D35+LOOKUP(E$5,'Cost Planning'!$G$8:$AE$8,'Cost Planning'!$G$59:$AE$59) -> 0 | F35: =E35+LOOKUP(F$5,'Cost Planning'!$G$8:$AE$8,'Cost Planning'!$G$59:$AE$59) -> 0 | G35: =F35+LOOKUP(G$5,'Cost Planning'!$G$8:$AE$8,'Cost Planning'!$G$59:$AE$59) -> 740 | H35: =G35+LOOKUP(H$5,'Cost Planning'!$G$8:$AE$8,'Cost Planning'!$G$59:$AE$59) -> 1480 | I35: =H35+LOOKUP(I$5,'Cost Planning'!$G$8:$AE$8,'Cost Planning'!$G$59:$AE$59) -> 2220 | J35: =I35+LOOKUP(J$5,'Cost Planning'!$G$8:$AE$8,'Cost Planning'!$G$59:$AE$59) -> 2960 | K35: =J35+LOOKUP(K$5,'Cost Planning'!$G$8:$AE$8,'Cost Planning'!$G$59:$AE$59) -> 3700 | L35: =K35+LOOKUP(L$5,'Cost Planning'!$G$8:$AE$8,'Cost Planning'!$G$59:$AE$59) -> 4440 | ... AC35: =AB35+LOOKUP(AC$5,'Cost Planning'!$G$8:$AE$8,'Cost Planning'!$G$59:$AE$59) -> 7400
B36: - COMPRAS | D36: ='Project Infor'!C49 -> 0 | E36: =D36+LOOKUP(E$5,'Cost Planning'!$G$8:$AE$8,'Cost Planning'!$G$74:$AE$74) -> 20000 | F36: =E36+LOOKUP(F$5,'Cost Planning'!$G$8:$AE$8,'Cost Planning'!$G$74:$AE$74) -> 40000 | G36: =F36+LOOKUP(G$5,'Cost Planning'!$G$8:$AE$8,'Cost Planning'!$G$74:$AE$74) -> 40000 | H36: =G36+LOOKUP(H$5,'Cost Planning'!$G$8:$AE$8,'Cost Planning'!$G$74:$AE$74) -> 40000 | I36: =H36+LOOKUP(I$5,'Cost Planning'!$G$8:$AE$8,'Cost Planning'!$G$74:$AE$74) -> 40000 | J36: =I36+LOOKUP(J$5,'Cost Planning'!$G$8:$AE$8,'Cost Planning'!$G$74:$AE$74) -> 40000 | K36: =J36+LOOKUP(K$5,'Cost Planning'!$G$8:$AE$8,'Cost Planning'!$G$74:$AE$74) -> 40000 | L36: =K36+LOOKUP(L$5,'Cost Planning'!$G$8:$AE$8,'Cost Planning'!$G$74:$AE$74) -> 40000 | ... AC36: =AB36+LOOKUP(AC$5,'Cost Planning'!$G$8:$AE$8,'Cost Planning'!$G$74:$AE$74) -> 40000
B37: COSTE DIRECTO | D37: =SUM(D32:D36) -> 0 | E37: =SUM(E32:E36) -> 37417.5 | F37: =SUM(F32:F36) -> 74835 | G37: =SUM(G32:G36) -> 103658.5 | H37: =SUM(H32:H36) -> 132482 | I37: =SUM(I32:I36) -> 161305.5 | J37: =SUM(J32:J36) -> 190129 | K37: =SUM(K32:K36) -> 218952.5 | ... AC37: =SUM(AC32:AC36) -> 381445.76
B38: MARGEN DIRECTO ACUMULADO (euros) | D38: =D30-D32-D33-D34-D35-D36 -> 0 | E38: =E30-E32-E33-E34-E35-E36 -> 13005.782 | F38: =F30-F32-F33-F34-F35-F36 -> 26011.564 | G38: =G30-G32-G33-G34-G35-G36 -> 36030.196 | H38: =H30-H32-H33-H34-H35-H36 -> 46048.828 | I38: =I30-I32-I33-I34-I35-I36 -> 56067.46 | J38: =J30-J32-J33-J34-J35-J36 -> 66086.092 | K38: =K30-K32-K33-K34-K35-K36 -> 76104.724 | ... AC38: =AC30-AC32-AC33-AC34-AC35-AC36 -> 132585.03
B40: VENTA ACUMULADA REPORTADA SAP | E40: =IF(OFFSET(E4,0,1)="Fin",E6) -> FALSE | F40: =IF(OFFSET(F4,0,1)="Fin",F6) -> FALSE | G40: =IF(OFFSET(G4,0,1)="Fin",G6) -> FALSE | H40: =IF(OFFSET(H4,0,1)="Fin",H6) -> FALSE | I40: =IF(OFFSET(I4,0,1)="Fin",I6) -> FALSE | J40: =IF(OFFSET(J4,0,1)="Fin",J6) -> FALSE | K40: =IF(OFFSET(K4,0,1)="Fin",K6) -> FALSE | L40: =IF(OFFSET(L4,0,1)="Fin",L6) -> FALSE | ... AC40: =IF(OFFSET(AC4,0,1)="Fin",AC6) -> FALSE
B42: FACTURACION EMITIDA/PLANIFICADA | D42: ='Project Infor'!C54 -> 0
B43: FACTURACION ACUMULADA | D43: =D42 -> 0 | E43: =E42+D43 -> 0 | F43: =F42+E43 -> 0 | G43: =G42+F43 -> 0 | H43: =H42+G43 -> 0 | I43: =I42+H43 -> 0 | J43: =J42+I43 -> 0 | K43: =K42+J43 -> 0 | L43: =L42+K43 -> 0 | ... AC43: =AC42+AB43 -> 0
B44: FACTURACION vs VENTA | E44: =E43-E30 -> -50423.282 | F44: =F43-F30 -> -100846.56 | G44: =G43-G30 -> -139688.7 | H44: =H43-H30 -> -178530.83 | I44: =I43-I30 -> -217372.96 | J44: =J43-J30 -> -256215.09 | K44: =K43-K30 -> -295057.22 | L44: =L43-L30 -> -333899.36 | ... AC44: =AC43-AC30 -> -514030.79

Sheet Cost Summary
B2: WBS-Element | C2: ='Project Infor'!C10 -> var2_SAP_PEP_WBS | D2: ='Project Infor'!C11 -> Smart Airport en la nueva terminal de Puerto Vallarta
D5: PEDIDO IMPORTE NETO | E5: COSTE RECURSOS | F5: HORAS | G5: RIESGOS | H5: GARANTÍA | I5: GASTOS | J5: COMPRAS | K5: COSTE DIRECTO | L5: MARGEN DIRECTO (euros) | M5: MARGEN DIRECTO (%) | N5: MARGEN BRUTO
B6: LINEA BASE INICIAL | D6: ='Cost Overview'!F12 -> 583896.55 | E6: ='Cost Overview'!G12 -> 367515.14 | F6: ='Cost Overview'!H12 -> 13570 | G6: ='Cost Overview'!I12 -> 18375.757 | H6: ='Cost Overview'!J12 -> 0 | I6: ='Cost Overview'!K12 -> 7400 | J6: ='Cost Overview'!L12 -> 40000 | K6: =SUM(E6,G6,H6,I6,J6) -> 433290.9 | L6: =D6-K6 -> 150605.65 | M6: =IF(D6=0,0,(D6-E6-H6-I6-G6-J6)/D6) -> 0.25793208 | N6: =IF(D6=0,0,(D6-E6/UTILIZACION-G6/UTILIZACION-H6/UTILIZACION-I6-J6)/D6) -> 0.20818774
B7: LINEA BASE ACTUAL | D7: ='Cost Overview'!F8 -> 583896.55 | E7: ='Cost Overview'!G8 -> 367515.14 | F7: ='Cost Overview'!H8 -> 13570 | G7: ='Cost Overview'!I8 -> 18375.757 | H7: ='Cost Overview'!J8 -> 0 | I7: ='Cost Overview'!K8 -> 7400 | J7: ='Cost Overview'!L8 -> 40000 | K7: =SUM(E7,G7,H7,I7,J7) -> 433290.9 | L7: =D7-K7 -> 150605.65 | M7: =IF(D7=0,0,(D7-E7-H7-I7-G7-J7)/D7) -> 0.25793208 | N7: =IF(D7=0,0,(D7-E7/UTILIZACION-G7/UTILIZACION-H7/UTILIZACION-I7-J7)/D7) -> 0.20818774
B8: PROYECCIÓN PROYECTO (REAL + ESTIMADO) | D8: =D7 -> 583896.55 | E8: =SUM('Cost Planning'!F40:AE41) -> 315670 | F8: =SUM('Cost Planning'!F9:AE9) -> 11850 | G8: =SUM('Cost Planning'!G47:AE47) -> 18375.757 | H8: =SUM('Cost Planning'!G48:AE48) -> 0 | I8: =SUM('Cost Planning'!F59:AE59) -> 7400 | J8: =SUM('Cost Planning'!F74:AE74) -> 40000 | K8: =SUM(E8,G8,H8,I8,J8) -> 381445.76 | L8: =D8-K8 -> 202450.79 | M8: =IF(D8=0,0,(D8-E8-H8-I8-G8-J8)/D8) -> 0.34672374 | N8: =IF(D8=0,0,(D8-E8/UTILIZACION-G8/UTILIZACION-H8/UTILIZACION-I8-J8)/D8) -> 0.30366263
B9: Diferencia de PROYECCION DEL PROYECTO con BASELINE ACTUAL | D9: =IF(D8=0,1,(D8-D7)/D8) -> 0 | E9: =IF(E8=0,1,(E8-E7)/E8) -> -0.16423842 | F9: =IF(F8=0,1,(F8-F7)/F8) -> -0.14514768 | G9: =IF(G8=0,1,(G8-G7)/G8) -> 0 | H9: =IF(H8=0,1,(H8-H7)/H8) -> 1 | I9: =IF(I8=0,1,(I8-I7)/I8) -> 0 | J9: =IF(J8=0,1,(J8-J7)/J8) -> 0 | K9: =IF(K8=0,1,(K8-K7)/K8) -> -0.13591747 | L9: =IF(L8=0,1,(L8-L7)/L8) -> 0.25608762 | M9: =M8-M7 -> 0.088791655
B11: REALIZADO | D11: =SUMIF('Monthly View'!$E$4:$AC$4,"Real",'Monthly View'!$E$18:$AC$18)+'Project Infor'!C45 -> 256215.09 | E11: =SUMIF('Monthly View'!$E$4:$AC$4,"Real",'Monthly View'!$E$20:$AC$20)+'Project Infor'!C47 -> 147169 | F11: =SUMIF('Monthly View'!$E$4:$AC$4,"Real",'Monthly View'!$E$19:$AC$19)+'Project Infor'!C46 -> 5472 | G11: =SUMIF('Monthly View'!$E$4:$AC$4,"Real",'Monthly View'!$E$21:$AC$21) -> 0 | H11: =SUMIF('Monthly View'!$E$4:$AC$4,"Real",'Monthly View'!$E$22:$AC$22) -> 0 | I11: =SUMIF('Monthly View'!$E$4:$AC$4,"Real",'Monthly View'!$E$23:$AC$23)+'Project Infor'!C48 -> 2960 | J11: =SUMIF('Monthly View'!$E$4:$AC$4,"Real",'Monthly View'!$E$24:$AC$24)+'Project Infor'!C49 -> 40000 | K11: =SUM(E11,G11,H11,I11,J11) -> 190129 | L11: =D11-K11 -> 66086.092 | M11: =IF(D11=0,0,(D11-E11-H11-I11-G11-J11)/D11) -> 0.25793208 | N11: =IF(D11=0,0,(D11-E11/UTILIZACION-G11/UTILIZACION-H11/UTILIZACION-I11-J11)/D11) -> 0.21469795
B12: % Avance | D12: =IF(D11=0,1,(D11/D8)) -> 0.4388022 | E12: =IF(E11=0,1,(E11/E8)) -> 0.46621155 | F12: =IF(F11=0,1,(F11/F8)) -> 0.46177215
B17: Comentarios adicionales Cost Summary

Sheet Ayuda
B2: CORE PC - VENTA POR AVANCE DE COSTES
B4: Pasos para completar el CORE en la apertura de un proyecto
B5: 1) Completar "Project Infor" incluyendo los datos del PPO
B6: 2) Revisar "Cost Overview" con la información de la Baseline Inicial (Fila 10) para que esté ok con PPO
B7: 3) Completar los coste del personal que va a ejecutar el proyecto en "Resources". IMPORTANTE: No indicar Nombre y Apellidos, solo Iniciales. También se debe indicar para cada perfil si es o no INTERCO porque ese dato se utiliza para calcular en coste de cada tipo de perfil y si no se completa no se tiene en cuenta el coste.
B8: 4) Completar el Planning de Horas, Riesgos, Garantía, Gastos y Compras en "Cost Planning". Tendremos avisos sobre lo que no hayamos planificado en cada una de las secciones
B9: 5) En "Monthly View" y "Cost Summary" tendremos la información de arranque del proyecto
B11: Pasos para completar la información mensual
B12: 1) Introducir la Fecha de Reporting en "Project Infor", celda C8
B13: 2) Introducir Ampliaciones y Reestimaciones en "Cost Overview"
B14: 3) Actualizar Costes de Recursos en "Resources". Importante: como nuestros costes puede que no cuadren 100% con los de SAP, si tenemos el dato de los costes mensuales del mes pasado en SAP, metemos la diferencia en "Cost Planning" en las celdas amarillas. Así vamos corrigiendo las diferencias mes a mes. Si la diferencia es signiticativa tendremos que revisar los costes de los recursos por si alguno no está como en SAP.
B15: 4) Actualizar el Planning de Horas, Riesgos, Garantía, Gastos y Compras en "Cost Planning". Tendremos avisos sobre lo que no hayamos planificado en cada una de las secciones. Si por ejemplo nos vamos a gastar más en Horas y queremos reestimar Riesgos, tendremos que volver a la pestaña "Cost Overview" para ver qué reestimación sería necesaria. Las Reestimaciones tienen que tener validación por parte de Cost Control & Optimization (CCO).
... B25: Los datos del FORECAST de VENTA aparecen en "Monthly View" - Fila 19. En la pestaña Aux Forecast se puede ir guardando el forecast proporcionado cada mes para tener una vista de la evolución de Forecast.

Sheet aux Billing Plan
B2: WBS-Element | C2: ='Project Infor'!C10 -> var2_SAP_PEP_WBS | D2: ='Project Infor'!C11 -> Smart Airport en la nueva terminal de Puerto Vallarta
B5: IMPORTE NETO A FACTURAR | E5: ='Cost Overview'!F8 -> 583896.55 | F5: (!) Faltan HITOS de FACTURACION por planificar | J5: =E5-F41 -> 583896.55
B7: TIPO FACTURA | C7: FECHA ESTIMADA FACTURA | D7: DCat | E7: CONCEPTO FACTURA | F7: IMPORTE FACTURA | G7: Currency | H7: IMPUESTOS (%) | I7: IMPORTE más IMPUESTOS | J7: LINEA/S DE PEDIDO | K7: CLIENTE | L7: Ticket support BILLING & COLLECTION | M7: FECHA FACTURA | N7: ENVIO FACTURA | O7: OTRA INFOR FACTURACION | P7: COBRADA
D8: =IF(C8=0," ","Z2") | I8: =IF(F8=0," ",F8+F8*H8)
D9: =IF(C9=0," ","Z2") | I9: =IF(F9=0," ",F9+F9*H9)
D10: =IF(C10=0," ","Z2") | I10: =IF(F10=0," ",F10+F10*H10)
D11: =IF(C11=0," ","Z2") | I11: =IF(F11=0," ",F11+F11*H11)
D12: =IF(C12=0," ","Z2") | I12: =IF(F12=0," ",F12+F12*H12)
D13: =IF(C13=0," ","Z2") | I13: =IF(F13=0," ",F13+F13*H13)
D14: =IF(C14=0," ","Z2") | I14: =IF(F14=0," ",F14+F14*H14)
D15: =IF(C15=0," ","Z2") | I15: =IF(F15=0," ",F15+F15*H15)
D16: =IF(C16=0," ","Z2") | I16: =IF(F16=0," ",F16+F16*H16)
D17: =IF(C17=0," ","Z2") | I17: =IF(F17=0," ",F17+F17*H17)
D18: =IF(C18=0," ","Z2") | I18: =IF(F18=0," ",F18+F18*H18)
D19: =IF(C19=0," ","Z2") | I19: =IF(F19=0," ",F19+F19*H19)
... D40: =IF(C40=0," ","Z2") | I40: =IF(F40=0," ",F40+F40*H40)
B41: TOTAL FACTURACION | F41: =SUM(F8:F40) -> 0 | I41: =SUM(I8:I40) -> 0
B50: Comentarios adicionales Billing Plan
B51: <dd/mm/aaaa> comentario <dd/mm/aaaa> comentario <dd/mm/aaaa> comentario

Sheet aux Forecast
B2: WBS-Element | C2: ='Project Infor'!C10 -> var2_SAP_PEP_WBS | D2: ='Project Infor'!C11 -> Smart Airport en la nueva terminal de Puerto Vallarta
B4: Mes Forecast | C4: 44197 | D4: =EOMONTH(C4,1) -> 44255 | E4: =EOMONTH(D4,1) -> 44286 | F4: =EOMONTH(E4,1) -> 44316 | G4: =EOMONTH(F4,1) -> 44347 | H4: =EOMONTH(G4,1) -> 44377 | I4: =EOMONTH(H4,1) -> 44408 | J4: =EOMONTH(I4,1) -> 44439 | K4: =EOMONTH(J4,1) -> 44469 | ... Z4: =EOMONTH(Y4,1) -> 44926
B5: 44197
B6: =EOMONTH(B5,1) -> 44255
B7: =EOMONTH(B6,1) -> 44286
B8: =EOMONTH(B7,1) -> 44316
B9: =EOMONTH(B8,1) -> 44347
B10: =EOMONTH(B9,1) -> 44377
B11: =EOMONTH(B10,1) -> 44408
B12: =EOMONTH(B11,1) -> 44439
B13: =EOMONTH(B12,1) -> 44469
B14: =EOMONTH(B13,1) -> 44500
B15: =EOMONTH(B14,1) -> 44530
B16: =EOMONTH(B15,1) -> 44561
B19: Comentarios adicionales Forecast
B20: <dd/mm/aaaa> comentario <dd/mm/aaaa> comentario <dd/mm/aaaa> comentario

Sheet aux UTE
B2: WBS-Element | C2: ='Project Infor'!C10 -> var2_SAP_PEP_WBS | D2: ='Project Infor'!C11 -> Smart Airport en la nueva terminal de Puerto Vallarta
B4: CLIENTE | C4: MINISTERIO | F4: ENTIDADES que forman la UTE | H4: PORCENTAJE | I4: IMPORTE (sin IVA) | J4: INTERLOCUTOR | K4: INFOR ADICIONAL
B5: GERENTE UTE | C5: Nombre Apellidos | F5: Entidad 1 | H5: 0.5 | I5: 5000 | J5: Nombre Apellidos
B6: DENOMINACION UTE | C6: UTE CONNECTIS --- | F6: Entidad 2 | H6: 0.1 | I6: 1000
B7: IMPORTE CONTRATACION (SIN iva) | C7: 10000 | E7: (!) Los IMPORTES por ENTIDADES no coinciden con el TOTAL | F7: Entidad 3 | H7: 0.2 | I7: 2000
F8: Entidad 4 | H8: 0.1 | I8: 1000
F9: Entidad 5 | H9: 0.1 | I9: 1000
C10: (!) Faltan HITOS de FACTURACION por planificar
B12: TIPO FACTURA | C12: FECHA ESTIMADA FACTURA | D12: ENTIDAD que FACTURA | E12: CONCEPTO FACTURA | F12: IMPORTE FACTURA | G12: Currency | H12: IMPUESTOS (%) | I12: IMPORTE más IMPUESTOS | J12: CLIENTE | K12: ENVIADA a utes@getronics.com | L12: FECHA FACTURA | M12: ENVIO FACTURA | N12: OTRA INFOR FACTURACION | O12: COBRADA
B13: FACTURA | C13: 44286 | D13: Entidad 1 | E13: Factura Hito 1 | F13: 3000 | G13: EUR | H13: 0.21 | I13: =IF(F13=0," ",F13+F13*H13) -> 3630 | J13: MINISTERIO | M13: Portal efacturación
D14: =IF(C14=0," ","Z2") | I14: =IF(F14=0," ",F14+F14*H14)
D15: =IF(C15=0," ","Z2") | I15: =IF(F15=0," ",F15+F15*H15)
D16: =IF(C16=0," ","Z2") | I16: =IF(F16=0," ",F16+F16*H16)
D17: =IF(C17=0," ","Z2") | I17: =IF(F17=0," ",F17+F17*H17)
D18: =IF(C18=0," ","Z2") | I18: =IF(F18=0," ",F18+F18*H18)
D19: =IF(C19=0," ","Z2") | I19: =IF(F19=0," ",F19+F19*H19)
D20: =IF(C20=0," ","Z2") | I20: =IF(F20=0," ",F20+F20*H20)
D21: =IF(C21=0," ","Z2") | I21: =IF(F21=0," ",F21+F21*H21)
D22: =IF(C22=0," ","Z2") | I22: =IF(F22=0," ",F22+F22*H22)
D23: =IF(C23=0," ","Z2") | I23: =IF(F23=0," ",F23+F23*H23)
D24: =IF(C24=0," ","Z2") | I24: =IF(F24=0," ",F24+F24*H24)
D25: =IF(C25=0," ","Z2") | I25: =IF(F25=0," ",F25+F25*H25)
... D45: =IF(C45=0," ","Z2") | I45: =IF(F45=0," ",F45+F45*H45)
B46: TOTAL FACTURACION | F46: =SUM(F13:F45) -> 3000 | I46: =SUM(I13:I45) -> 3630
B55: Comentarios adicionales Gestión UTE
B56: <dd/mm/aaaa> comentario <dd/mm/aaaa> comentario <dd/mm/aaaa> comentario

Sheet aux Calendarios
B2: WBS-Element | C2: ='Project Infor'!C10 -> var2_SAP_PEP_WBS | D2: ='Project Infor'!C11 -> Smart Airport en la nueva terminal de Puerto Vallarta
B5: CALENDARIO 1 | D5: Madrid + GS
B6: HORAS/JORNADA | C6: HORAS JORNADA | D6: ='Project Infor'!$C$8 -> 45962 | E6: =EOMONTH(D6,1) -> 46022 | F6: =EOMONTH(E6,1) -> 46053 | G6: =EOMONTH(F6,1) -> 46081 | H6: =EOMONTH(G6,1) -> 46112 | I6: =EOMONTH(H6,1) -> 46142 | J6: =EOMONTH(I6,1) -> 46173 | K6: =EOMONTH(J6,1) -> 46203 | L6: =EOMONTH(K6,1) -> 46234 | ... AB6: =EOMONTH(AA6,1) -> 46721
B7: 8.5 | C7: =IF(B7=0,"",CONCATENATE("Jornadas de ",B7," horas: ")) -> Jornadas de 8,5 horas: | D7: 16 | E7: 16 | F7: 16 | G7: 16 | J7: 16
B8: 7 | C8: =IF(B8=0,"",CONCATENATE("Jornadas de ",B8," horas: ")) -> Jornadas de 7 horas: | D8: 3 | E8: 2 | F8: 1 | G8: 4 | H8: 22 | I8: 22 | J8: 5
B9: 6 | C9: =IF(B9=0,"",CONCATENATE("Jornadas de ",B9," horas: ")) -> Jornadas de 6 horas: | D9: 1 | E9: 3 | F9: 1 | G9: 2 | J9: 9
B10: 7.25 | C10: =IF(B10=0,"",CONCATENATE("Jornadas de ",B10," horas: ")) -> Jornadas de 7,25 horas:
B11: 5.25 | C11: =IF(B11=0,"",CONCATENATE("Jornadas de ",B11," horas: ")) -> Jornadas de 5,25 horas: | D11: 2 | F11: 2
C12: TOTAL HORAS MES | D12: =SUMPRODUCT(D7:D11,$B$7:$B$11) -> 173.5 | E12: =SUMPRODUCT(E7:E11,$B$7:$B$11) -> 168 | F12: =SUMPRODUCT(F7:F11,$B$7:$B$11) -> 159.5 | G12: =SUMPRODUCT(G7:G11,$B$7:$B$11) -> 176 | H12: =SUMPRODUCT(H7:H11,$B$7:$B$11) -> 154 | I12: =SUMPRODUCT(I7:I11,$B$7:$B$11) -> 154 | J12: =SUMPRODUCT(J7:J11,$B$7:$B$11) -> 225 | K12: =SUMPRODUCT(K7:K11,$B$7:$B$11) -> 0 | ... AB12: =SUMPRODUCT(AB7:AB11,$B$7:$B$11) -> 0
B15: CALENDARIO 2 | D15: Descripción calendario
B16: HORAS/JORNADA | C16: HORAS JORNADA | D16: ='Project Infor'!$C$8 -> 45962 | E16: =EOMONTH(D16,1) -> 46022 | F16: =EOMONTH(E16,1) -> 46053 | G16: =EOMONTH(F16,1) -> 46081 | H16: =EOMONTH(G16,1) -> 46112 | I16: =EOMONTH(H16,1) -> 46142 | J16: =EOMONTH(I16,1) -> 46173 | K16: =EOMONTH(J16,1) -> 46203 | L16: =EOMONTH(K16,1) -> 46234 | ... AB16: =EOMONTH(AA16,1) -> 46721
B17: 8 | C17: =IF(B17=0,"",CONCATENATE("Jornadas de ",B17," horas: ")) -> Jornadas de 8 horas: | D17: 16
B18: 6 | C18: =IF(B18=0,"",CONCATENATE("Jornadas de ",B18," horas: ")) -> Jornadas de 6 horas: | D18: 3
C19: =IF(B19=0,"",CONCATENATE("Jornadas de ",B19," horas: "))
C21: =IF(B21=0,"",CONCATENATE("Jornadas de ",B21," horas: "))
C22: TOTAL HORAS MES | D22: =SUMPRODUCT(D17:D21,$B$17:$B$21) -> 146 | E22: =SUMPRODUCT(E17:E21,$B$17:$B$21) -> 0 | F22: =SUMPRODUCT(F17:F21,$B$17:$B$21) -> 0 | G22: =SUMPRODUCT(G17:G21,$B$17:$B$21) -> 0 | H22: =SUMPRODUCT(H17:H21,$B$17:$B$21) -> 0 | I22: =SUMPRODUCT(I17:I21,$B$17:$B$21) -> 0 | J22: =SUMPRODUCT(J17:J21,$B$17:$B$21) -> 0 | K22: =SUMPRODUCT(K17:K21,$B$17:$B$21) -> 0 | ... AB22: =SUMPRODUCT(AB17:AB21,$B$17:$B$21) -> 0
B25: CALENDARIO 3 | D25: Descripción calendario
B26: HORAS/JORNADA | C26: HORAS JORNADA | D26: ='Project Infor'!$C$8 -> 45962 | E26: =EOMONTH(D26,1) -> 46022 | F26: =EOMONTH(E26,1) -> 46053 | G26: =EOMONTH(F26,1) -> 46081 | H26: =EOMONTH(G26,1) -> 46112 | I26: =EOMONTH(H26,1) -> 46142 | J26: =EOMONTH(I26,1) -> 46173 | K26: =EOMONTH(J26,1) -> 46203 | L26: =EOMONTH(K26,1) -> 46234 | ... AB26: =EOMONTH(AA26,1) -> 46721
B27: 7 | C27: =IF(B27=0,"",CONCATENATE("Jornadas de ",B27," horas: ")) -> Jornadas de 7 horas: | D27: 22 | E27: 20 | F27: 21 | G27: 21 | H27: 22 | I27: 22 | J27: 22 | K27: 21 | L27: 22 | M27: 16
C28: =IF(B28=0,"",CONCATENATE("Jornadas de ",B28," horas: "))
C29: =IF(B29=0,"",CONCATENATE("Jornadas de ",B29," horas: "))
C31: =IF(B31=0,"",CONCATENATE("Jornadas de ",B31," horas: "))
C32: TOTAL HORAS MES | D32: =SUMPRODUCT(D27:D31,$B$27:$B$31) -> 154 | E32: =SUMPRODUCT(E27:E31,$B$27:$B$31) -> 140 | F32: =SUMPRODUCT(F27:F31,$B$27:$B$31) -> 147 | G32: =SUMPRODUCT(G27:G31,$B$27:$B$31) -> 147 | H32: =SUMPRODUCT(H27:H31,$B$27:$B$31) -> 154 | I32: =SUMPRODUCT(I27:I31,$B$27:$B$31) -> 154 | J32: =SUMPRODUCT(J27:J31,$B$27:$B$31) -> 154 | K32: =SUMPRODUCT(K27:K31,$B$27:$B$31) -> 147 | ... AB32: =SUMPRODUCT(AB27:AB31,$B$27:$B$31) -> 0
B35: CALENDARIO 4 | D35: Descripción calendario
B36: HORAS/JORNADA | C36: HORAS JORNADA | D36: ='Project Infor'!$C$8 -> 45962 | E36: =EOMONTH(D36,1) -> 46022 | F36: =EOMONTH(E36,1) -> 46053 | G36: =EOMONTH(F36,1) -> 46081 | H36: =EOMONTH(G36,1) -> 46112 | I36: =EOMONTH(H36,1) -> 46142 | J36: =EOMONTH(I36,1) -> 46173 | K36: =EOMONTH(J36,1) -> 46203 | L36: =EOMONTH(K36,1) -> 46234 | ... AB36: =EOMONTH(AA36,1) -> 46721
B37: 7 | C37: =IF(B37=0,"",CONCATENATE("Jornadas de ",B37," horas: ")) -> Jornadas de 7 horas: | D37: 22 | E37: 20
C38: =IF(B38=0,"",CONCATENATE("Jornadas de ",B38," horas: "))
C39: =IF(B39=0,"",CONCATENATE("Jornadas de ",B39," horas: "))
C41: =IF(B41=0,"",CONCATENATE("Jornadas de ",B41," horas: "))
C42: TOTAL HORAS MES | D42: =SUMPRODUCT(D37:D41,$B$37:$B$41) -> 154 | E42: =SUMPRODUCT(E37:E41,$B$37:$B$41) -> 140 | F42: =SUMPRODUCT(F37:F41,$B$37:$B$41) -> 0 | G42: =SUMPRODUCT(G37:G41,$B$37:$B$41) -> 0 | H42: =SUMPRODUCT(H37:H41,$B$37:$B$41) -> 0 | I42: =SUMPRODUCT(I37:I41,$B$37:$B$41) -> 0 | J42: =SUMPRODUCT(J37:J41,$B$37:$B$41) -> 0 | K42: =SUMPRODUCT(K37:K41,$B$37:$B$41) -> 0 | ... AB42: =SUMPRODUCT(AB37:AB41,$B$37:$B$41) -> 0
B45: CALENDARIO 5 | D45: Descripción calendario
B46: HORAS/JORNADA | C46: HORAS JORNADA | D46: ='Project Infor'!$C$8 -> 45962 | E46: =EOMONTH(D46,1) -> 46022 | F46: =EOMONTH(E46,1) -> 46053 | G46: =EOMONTH(F46,1) -> 46081 | H46: =EOMONTH(G46,1) -> 46112 | I46: =EOMONTH(H46,1) -> 46142 | J46: =EOMONTH(I46,1) -> 46173 | K46: =EOMONTH(J46,1) -> 46203 | L46: =EOMONTH(K46,1) -> 46234 | ... AB46: =EOMONTH(AA46,1) -> 46721
B47: 7 | C47: =IF(B47=0,"",CONCATENATE("Jornadas de ",B47," horas: ")) -> Jornadas de 7 horas: | D47: 22 | E47: 20
C48: =IF(B48=0,"",CONCATENATE("Jornadas de ",B48," horas: "))
C49: =IF(B49=0,"",CONCATENATE("Jornadas de ",B49," horas: "))
C51: =IF(B51=0,"",CONCATENATE("Jornadas de ",B51," horas: "))
C52: TOTAL HORAS MES | D52: =SUMPRODUCT(D47:D51,$B$47:$B$51) -> 154 | E52: =SUMPRODUCT(E47:E51,$B$47:$B$51) -> 140 | F52: =SUMPRODUCT(F47:F51,$B$47:$B$51) -> 0 | G52: =SUMPRODUCT(G47:G51,$B$47:$B$51) -> 0 | H52: =SUMPRODUCT(H47:H51,$B$47:$B$51) -> 0 | I52: =SUMPRODUCT(I47:I51,$B$47:$B$51) -> 0 | J52: =SUMPRODUCT(J47:J51,$B$47:$B$51) -> 0 | K52: =SUMPRODUCT(K47:K51,$B$47:$B$51) -> 0 | ... AB52: =SUMPRODUCT(AB47:AB51,$B$47:$B$51) -> 0
B55: CALENDARIO 6 | D55: Descripción calendario
B56: HORAS/JORNADA | C56: HORAS JORNADA | D56: ='Project Infor'!$C$8 -> 45962 | E56: =EOMONTH(D56,1) -> 46022 | F56: =EOMONTH(E56,1) -> 46053 | G56: =EOMONTH(F56,1) -> 46081 | H56: =EOMONTH(G56,1) -> 46112 | I56: =EOMONTH(H56,1) -> 46142 | J56: =EOMONTH(I56,1) -> 46173 | K56: =EOMONTH(J56,1) -> 46203 | L56: =EOMONTH(K56,1) -> 46234 | ... AB56: =EOMONTH(AA56,1) -> 46721
C58: =IF(B58=0,"",CONCATENATE("Jornadas de ",B58," horas: "))
C59: =IF(B59=0,"",CONCATENATE("Jornadas de ",B59," horas: "))
C61: =IF(B61=0,"",CONCATENATE("Jornadas de ",B61," horas: "))
C62: TOTAL HORAS MES | D62: =SUMPRODUCT(D57:D61,$B$57:$B$61) -> 0 | E62: =SUMPRODUCT(E57:E61,$B$57:$B$61) -> 0 | F62: =SUMPRODUCT(F57:F61,$B$57:$B$61) -> 0 | G62: =SUMPRODUCT(G57:G61,$B$57:$B$61) -> 0 | H62: =SUMPRODUCT(H57:H61,$B$57:$B$61) -> 0 | I62: =SUMPRODUCT(I57:I61,$B$57:$B$61) -> 0 | J62: =SUMPRODUCT(J57:J61,$B$57:$B$61) -> 0 | K62: =SUMPRODUCT(K57:K61,$B$57:$B$61) -> 0 | ... AB62: =SUMPRODUCT(AB57:AB61,$B$57:$B$61) -> 0

Sheet Trazabilidad_RPA
A1: Trazabilidad de pre-relleno CORE PC
A2: PPO: 20250256445 · Proyecto: Smart Airport en la nueva terminal de Puerto Vallarta
A4: Resumen de reglas aplicadas
A5: Regla | B5: Aplicación | C5: Detalle
A6: Tipo plantilla | B6: CORE PC | C6: PEP Type PPO = PC / Project Service Type = Fixed Price (services)
A7: Fuente principal | B7: PPO | C7: Cabecera, importes, perfiles, costes, horas por anualidad, gastos, compras, riesgos y garantías.
A8: Variables externas | B8: SAP/Salesforce/proceso previo | C8: PEP/WBS, código cliente, pedido/Sales Order, códigos de empleado y PM/Practice Leader.
A9: Recursos | B9: Prorrateo plano | C9: Horas anuales repartidas entre meses del año dentro de la duración PPO.
A10: Coste hora | B10: 2025 flat | C10: Coste hora 2025 copiado en los meses de planificación, dejando incrementos interanuales para revisión posterior.
A11: Intercompany | B11: Derivado por entidad | C11: Proyecto Connectis-ICT; recursos Global Rosetta marcados INTERCO y Connectis-ICT como NO.
A12: Gastos/compras | B12: Prorrateo plano | C12: Importes por anualidad repartidos entre meses aplicables.
A13: Riesgos/garantía | B13: Último mes | C13: Totales imputados al último mes del proyecto.
A14: Facturación emitida | B14: Vacía | C14: No se informa porque refleja ejecución real, no previsión.
A17: Variables pendientes SAP/Salesforce/proceso previo
A18: Variable | B18: Hoja | C18: Celda | D18: Campo | E18: Origen | F18: Valor provisional / comentario | G18: Acción requerida | H18: Estado
A19: var1_SAP_FechaInicio | B19: Project Infor | C19: C8 | D19: Fecha de Inicio CORE | E19: SAP | F19: 45962 | G19: Validar si debe reemplazar a fecha PPO provisional. | H19: Provisional PPO
A20: var2_SAP_PEP_WBS | B20: Project Infor | C20: C10 | D20: WBS-Element / PEP | E20: SAP | G20: Rellenar PEP/WBS real del proyecto. | H20: Pendiente
A21: var3_SAP_CodigoCliente | B21: Project Infor | C21: C16 | D21: Código cliente | E21: SAP/Salesforce | F21: GAP | G21: Rellenar código cliente; nombre ya informado desde PPO. | H21: Pendiente
A22: var4_SAP_PedidoSalesOrder | B22: Project Infor | C22: C19 | D22: Pedido / Sales Order | E22: SAP | G22: Rellenar pedido cuando exista alta en SAP. | H22: Pendiente
A23: var5_SAP_CodEmpleadoPM | B23: Project Infor | C23: C22 | D23: Código empleado Project Manager | E23: SAP/SF | G23: Rellenar código empleado. | H23: Pendiente
A24: var6_SAP_ProjectManager | B24: Project Infor | C24: D22 | D24: Project Manager | E24: SAP/SF | G24: Rellenar nombre. | H24: Pendiente
A25: var7_SAP_CodEmpleadoPracticeLeader | B25: Project Infor | C25: C23 | D25: Código empleado Practice Leader | E25: SAP/SF | G25: Rellenar código empleado. | H25: Pendiente
A26: var8_SAP_PracticeLeader | B26: Project Infor | C26: D23 | D26: Practice Leader | E26: SAP/SF | G26: Rellenar nombre. | H26: Pendiente
A27: var9_SF_CodEmpleadoSalesManager | B27: Project Infor | C27: C24 | D27: Código empleado Sales Manager | E27: Salesforce | F27: Joan Marcer | G27: Rellenar código; nombre informado desde PPO Account Manager. | H27: Pendiente código
A28: var10_SAP_CodEmpleado_JP | B28: Resources | C28: B7 | D28: Código empleado recurso Jefe Proyecto (JP) | E28: SAP/SF | G28: Rellenar si se conoce persona nominal. | H28: Pendiente
A29: var11_SAP_CodEmpleado_CSS | B29: Resources | C29: B8 | D29: Código empleado recurso Consultor Smart Spaces (CSS) | E29: SAP/SF | G29: Rellenar si se conoce persona nominal. | H29: Pendiente
A30: var12_SAP_CodEmpleado_CJSS | B30: Resources | C30: B9 | D30: Código empleado recurso Consultor Junior Smart Spaces (CJSS) | E30: SAP/SF | G30: Rellenar si se conoce persona nominal. | H30: Pendiente
A31: var13_SAP_CodEmpleado_A | B31: Resources | C31: B10 | D31: Código empleado recurso Arquitecto (A) | E31: SAP/SF | G31: Rellenar si se conoce persona nominal. | H31: Pendiente
A32: var14_SAP_CodEmpleado_II | B32: Resources | C32: B11 | D32: Código empleado recurso Ingeniero Integración (II) | E32: SAP/SF | G32: Rellenar si se conoce persona nominal. | H32: Pendiente
A33: var15_SAP_CodEmpleado_P | B33: Resources | C33: B12 | D33: Código empleado recurso Configuración Portal (P) | E33: SAP/SF | G33: Rellenar si se conoce persona nominal. | H33: Pendiente
A34: var16_SAP_CodEmpleado_DG | B34: Resources | C34: B13 | D34: Código empleado recurso Diseñador gráfico (DG) | E34: SAP/SF | G34: Rellenar si se conoce persona nominal. | H34: Pendiente
A35: var20_SAP_Proveedor_Subcontrataciones | B35: Cost Planning | C35: B64 | D35: Proveedor compra Subcontrataciones | E35: SAP/Ariba | G35: Rellenar proveedor si aplica. | H35: Pendiente
A36: var30_SAP_PO_Compra | B36: Cost Planning | C36: D64 | D36: PO compra Subcontrataciones | E36: SAP/Ariba | G36: Rellenar PO si aplica. | H36: Pendiente
A37: var40_SAP_Ariba | B37: Cost Planning | C37: E64 | D37: Referencia Ariba Subcontrataciones | E37: SAP/Ariba | G37: Rellenar si aplica. | H37: Pendiente
A40: Advertencias de calidad de dato
A41: ID | B41: Advertencia | C41: Impacto | D41: Recomendación
A42: W-01 | B42: El PPO contiene horas/importes fuera del rango 11/2025-10/2026: II/Ingeniero Integración 2027: 500; II/Ingeniero Integración 2028: 360; P/Configuración Portal 2027: 500; P/Configuración Portal 2028: 360. | C42: No se han imputado en Cost Planning por estar fuera de la duración PPO utilizada para redimensionar el CORE. | D42: Validar duración real en Salesforce/SAP o corregir anualidades del PPO antes del cierre de planificación.
A43: W-02 | B43: Horas totales PPO = 13570; horas planificadas dentro de duración CORE = 11850. | C43: Queda diferencia pendiente de planificación por anualidades fuera de duración o inconsistencia del PPO. | D43: Revisar duración PPO vs. anualidades presupuestadas; ajustar Project Infor!C9 si procede.
A44: W-03 | B44: Fecha de inicio CORE informada con valor provisional del PPO para conservar fórmulas y cabeceras mensuales. | C44: Si negocio exige fecha SAP de adjudicación/alta, debe sustituirse por var1_SAP_FechaInicio. | D44: Validar fecha con SAP/proceso previo antes de entregar al JP.
A45: W-04 | B45: Los códigos de empleado se han dejado como variables porque el PPO no contiene asignación nominal fiable. | C45: La planificación usa perfiles/roles, no personas reales. | D45: El JP puede sustituirlos cuando el equipo esté asignado.
