Workbook

Sheet Invoice Request
B2: Please select options from the drop down menus.
B3: Request Type | C3: Invoice
C4: =IF(C3="Credit Note", "The Bill Type should match original invoice type"," ")
B6: Bill Type
B8: Company Issuer | C8: Connectis ICT Services SAU
B10: Billing Detail
B11: Customer | C11: SERVICIOS A LA INFRAESTRUCTURA | E11: Sold - to number | F11: 461530
B14: Contract number | D14: =IF($C$6="Adhoc","NO INPUT REQUIRED","") | E14: PO
B16: Requested by | C16: Luis Guerra Gonzalez | D16: =IF($C$6="Fixed - no changes","NO INPUT REQUIRED","") | E16: Currency | F16: USD $
F17: Please select currency from drop down menu.
B18: Billing Address | C18: Accounts Payable
C19: [Line 1]
C20: [Line 2]
C21: [Line 3]
C22: [Line 4]
C23: [Line 5]
C24: [Line 6]
B26: Summary Text | C26: Hito 1 :Integración de las Bandas de Reclamo
B28: Text Narrative | C28: Invoice Breakdown: | D28: Qty/Days/Hrs | E28: Rate | F28: Amt | G28: =IF($C$6="Fixed - no changes","NO INPUT REQUIRED", " ")
C30: Pedido : PVR-OC-0005647
C31: Concepto :
C32: Hito 1 : Integración de las Bandas de Reclamo | F32: 22320.4
F34: =D34*E34 -> 0
F35: 0
F36: =D36*E36 -> 0
F37: =D37*E37 -> 0
F38: =D38*E38 -> 0
C40: Is VAT applicable? | D40: No
C41: VAT Rate | D41: 0.21 | E41: Net Value | F41: =SUM(F29:F36) -> 22320.4
E42: VAT | F42: =IF(D40="Yes",(+F41*D41),0) -> 0
E43: Gross Value | F43: =SUM(F41:F42) -> 22320.4
C46: Sales Order: | D46: 714603126 | F46: Comments:
C47: WBS Code: | D47: ZEV-PCE0012-1001 | F47: Invoice Date: 10/02/2026 Enviar Copia de las Facturas a : lluis.guerra@getronics.com ipro@getronics.com
C49: WBS breakdown | D49: Value
C52: LINE 10 | D52: =F41 -> 22320.4
B59: =IF($C$6= "Fixed","Reason for request","")
B61: Please send to: | C61: Iberiabilling @getronics.com | G61: Version : 05.06.2018

Sheet UC Maint Contract+Inv Request
B2: Please select options from the drop down menus.
B3: Request Type | C3: New SAP Contract + Invoice
B5: Requested by | C5: Steph Seekings | D5: Input required
B6: Account Mgr / SDM | C6: Richard Smiles | D6: Input required
C7: =IF(C3="Credit Note", "The Bill Type should match original invoice type"," ")
B8: Header Information
B9: Bill Type | C9: Fixed
C11: Top 11 Customers | F11: Other Customers
B12: Customer | D12: Select from drop down | E12: Customer | F12: Philips Electronics UK Ltd | H12: =IF(C12="","Input Required","No Input Required") -> Input Required
B13: Sold - to number | C13: =Lists!B17 | E13: Sold - to number | H13: =IF(C12="","Input Required","No Input Required") -> Input Required
B14: Ship to number | D14: Include only if different to sold-to | E14: Ship to number | H14: Include only if different to sold-to
B15: Payer ID number | D15: Include only if different to sold-to | E15: Payer ID number | H15: Include only if different to sold-to
B18: Billing Address | C18: Accounts Payable | D18: Optional input | E18: PO / Customer Ref | H18: Input required
C19: [Line 1] | E19: Our Ref | H19: Include CMDB/SV contract ref
C20: [Line 2]
C21: [Line 3]
C22: [Line 4] | F22: TCV | H22: Input required
C23: [Line 5] | F23: Currency | G23: GBP | H23: Please select from drop down
C24: [Line 6]
B26: AP Email address
B28: Header Description
B30: Line Item Information
B31: Billing Duration | D31: Please select from drop down | F31: Billing timing | G31: In advance | H31: Please select from drop down
B33: Contract Start Date | C33: 01.01.2015 | D33: =IF($C$9="Fixed - no changes","NO INPUT REQUIRED","")
B34: Contract End Date | C34: 31.12.2015 | D34: =IF($C$9="Fixed - no changes","NO INPUT REQUIRED","")
B36: WBS Code | C36: Top 11 Customer | E36: Other Customer
C37: =IF(C12=0,"",Lists!B18) | E37: =IF(F12=0,"No Input Required",'UC WBS codes'!C18) -> ZGC-Z001635-U1F1
B39: Billing Information
B40: Invoice Narrative | C40: Invoice Breakdown: | D40: Site | E40: Agreement Ref | F40: Start Date | G40: End Date | H40: Amt
C42: Maintenance support Mth x | D42: Guildford/82454 | E42: MCA - XXXXXXXX | H42: 100000
C52: Is VAT applicable? | D52: Yes
G53: Net Value | H53: =SUM(H41:H50) -> 100000
G54: VAT | H54: =IF(D52="Yes",(+H53*0.2),0) -> 20000
G55: Gross Value | H55: =SUM(H53:H54) -> 120000
B58: Please send to: | C58: Uk.Billing@Getronics.com | H58: Version : 21.10.2015

Sheet Billing template instructions
B3: Request Type | C3: Invoice | E3: =IF(C3="Credit Note", "Has Approval been requested from Simon Goodwin?"," ")
B4: Please select request type from the drop down menu.
B5: Bill Type | E5: =IF(C3="Credit Note", "The Bill Type should match original invoice type"," ")
B6: Please select billing type from the drop down menu.
C7: =IF($C$5="Fixed","If changes are required to contract setup - complete details below e.g. Indexation, PO Ref?", " ")
B10: Billing Detail
B11: Customer | C11: [Customer name] | E11: Sold - to number | F11: [Customer Sold-to, where applicable]
B13: Contract number | C13: [The contract number in SAP, where applicable] | D13: =IF($C$5="Adhoc","NO INPUT REQUIRED","") | E13: PO | F13: [PO Number]
B15: Requested by | C15: [Your name] | D15: =IF($C$5="Fixed - no changes","NO INPUT REQUIRED","") | E15: Currency | F15: GBP
F16: Please select currency from drop down menu.
B17: Billing Address | C17: FAO: [Joe Bloggs]
C18: [Line 1 of address]
C19: [Line 2 of address]
C20: [Line 3 of address]
C21: [Line 4 of address]
C22: [Line 5 of address]
C23: [Line 6 of address]
B25: Summary Text | G25: =IF($C$5="Adhoc", "", IF($C$3="Credit Note","","NO INPUT REQUIRED")) -> NO INPUT REQUIRED
B27: Text Narrative | C27: Invoice Breakdown: | D27: Qty/Days/Hrs | E27: Rate | F27: Amt | G27: =IF($C$5="Fixed - no changes","NO INPUT REQUIRED", " ")
C28: EXAMPLE 1 | D28: 10 | E28: 100 | F28: =D28*E28 -> 1000
C29: EXAMPLE 2 | D29: 1 | E29: 5430 | F29: =D29*E29 -> 5430
F30: =D30*E30 -> 0
F31: =D31*E31 -> 0
F32: =D32*E32 -> 0
F33: =D33*E33 -> 0
F34: =D34*E34 -> 0
F35: =D35*E35 -> 0
C37: Is VAT applicable? | D37: Yes
E38: Net Value | F38: =SUM(F28:F35) -> 6430
E39: VAT | F39: =IF(D37="Yes",(+F38*0.2),0) -> 1286
E40: Gross Value | F40: =SUM(F38:F39) -> 7716
C43: WBS Code
C44: [Please enter WBS code]
C45: WBS breakdown | D45: Value
B55: =IF($C$5= "Adhoc","","Reason for request") -> Reason for request
B57: Please send to: | C57: Uk.Billing@Getronics.com | G57: Version : 02.12.2013

Sheet Lists
A4: Invoice request | B4: Invoice | C4: Fixed | D4: GBP | F4: Yes | H4: 0.1 | L4: Uk.Billing@Getronics.com | P4: SAP Company Code | Q4: Company Name | R4: Hyperion Trading Partner
B5: Credit Note | C5: Variable | D5: EUR | F5: No | H5: 0.15 | L5: Iberiabilling @getronics.com | P5: BE | Q5: NV GETRONICS BELGIUM SA | R5: L_BEL002
C6: Adhoc | D6: USD $ | H6: 0.19 | L6: Belgium Billing | P6: DH | Q6: ICT Solutions & Service GmbH | R6: L_DEU002
C7: Contract | D7: CAN $ | H7: 0.2 | L7: Germany Billing | P7: DF | Q7: Getronics Help U Desk / SAP Getronics HelpYouDesk GmbH | R7: L_DEU003
H8: 0.21 | L8: Int. Billing | P8: GC | Q8: Getronics Services UK Ltd. | R8: L_GBR016
H9: 0 | L9: APAC billing | P9: x | Q9: GSC UK | R9: GBR316
A10: Contract request | C10: Fixed | D10: Monthly | E10: In advance | L10: Other | P10: HU | Q10: Getronics Hungary Kft. | R10: L_HUN001
C11: Variable | D11: Quarterly | E11: In arrears | P11: IE | Q11: Getronics Ireland Ltd. | R11: L_IRL001
D12: Annual | P12: LU | Q12: Getronics PSF Luxembourg SA | R12: L_LUX006
P13: HV | Q13: EMEA TAVOLSAGI SZOLGALTATO ZRT. | R13: L_HUN003
P14: MY | Q14: GETRONICS SOLUTION (M) SDN BHD | R14: L_MYS002
P15: MZ | Q15: Getronics Technology (MZ) (GSC Malaysia) | R15: MYS301
A16: Calcs | P16: MZ | Q16: Getronics Technology (MZ) | R16: L_MYS003
A17: sold to | B17: =IF('UC Maint Contract+Inv Request'!C12="","",VLOOKUP('UC Maint Contract+Inv Request'!$C$12,'UC WBS codes'!$A$3:$C$13,2,FALSE)) | P17: NQ | Q17: Getronics Global Services BV | R17: L_NLD125
A18: wbs code | B18: =IF('UC Maint Contract+Inv Request'!C12="","",VLOOKUP('UC Maint Contract+Inv Request'!$C$12,'UC WBS codes'!$A$3:$C$13,3,FALSE)) | P18: SG | Q18: Getronic(s) Solutions Pte Limited | R18: L_SGP002
P19: X | Q19: Getronics Thailand Ltd | R19: L_THA001
P20: X | Q20: Getronics Korea | R20: L_KOR002
P21: X | Q21: Getronics Solutions India Pte Ltd | R21: L_INR001
P22: EV | Q22: Connectis ICT Services SAU | R22: connectis_sau
P23: X | Q23: Connectis Argentina | R23: Connectis_arg
P24: DY | Q24: Connectis Holding GmbH | R24: L_DEU008
P25: DP | Q25: Getronics Premium IT Services GmbH | R25: L_DEU006
P26: DX | Q26: Getronics ICT Management GmbH | R26: L_DEU007
P27: NS | Q27: Getronics Services BV | R27: Getr_serv_sac
P28: X | Q28: Getronics Global BV | R28: Getr_global_sac
P29: X | Q29: Getronics IT Services BV | R29: Getr_itserv_sac
P30: GE | Q30: Getronics Unified Communications UK LTD | R30: L_GBR017
... P43: DY | Q43: GTN Field Services GmbH | R43: AUR655

Sheet UC WBS codes
A1: Description | B1: Sold-to | C1: WBS number | D1: Type
A3: UC - Tata Steel Maint/Managed Service | B3: 458314 | C3: ZGC-Z001637-U1F1 | D3: UC Top 10 Customers
A4: UC - Univ of Essex Maint/Managed Service | B4: 193568 | C4: ZGC-Z001638-U1F1 | D4: UC Top 10 Customers
A5: UC - Dorset Police Maint/Managed Service | B5: 458270 | C5: ZGC-Z001639-U1F1 | D5: UC Top 10 Customers
A6: UC - Univ of Nottingham Maint/Managed Service | B6: 194293 | C6: ZGC-Z001640-U1F1 | D6: UC Top 10 Customers
A7: UC - Aberdeen City Council Maint/Managed Service | B7: 259607 | C7: ZGC-Z001641-U1F1 | D7: UC Top 10 Customers
A8: UC - Royal Marsden NHS Maint/Managed Service | B8: 458247 | C8: ZGC-Z001642-U1F1 | D8: UC Top 10 Customers
A9: UC - Univ of Edinburgh Maint/Managed Service | B9: 215070 | C9: ZGC-Z001643-U1F1 | D9: UC Top 10 Customers
A10: UC - Tameside Maint/Managed Service | B10: 458203 | C10: ZGC-Z001644-U1F1 | D10: UC Top 10 Customers
A11: UC - Fife Health Maint/Managed Service | B11: 458199 | C11: ZGC-Z001645-U1F1 | D11: UC Top 10 Customers
A12: UC - Interserve Maint/Managed Service | B12: 458294 | C12: ZGC-Z001646-U1F1 | D12: UC Top 10 Customers
A13: UC - RDASH Maint/Managed Service | B13: 458336 | C13: ZGC-Z001647-U1F1 | D13: UC Top 10 Customers
A18: UC - Maint/Managed Service | B18: 458493 | C18: ZGC-Z001635-U1F1 | D18: UC Generic
