Workbook
Name costerecursosbaselineactual: 'Cost Overview'!$G$8
Name costerecursostotalplanificado: costerecursosbaselineactual-'Cost Planning'!$J$5
Name FECHA: 'Project Infor'!$D$6
Name FIN: 'Project Infor'!$C$9
Name Inicio: 'Project Infor'!$C$8
Name margendirectobaselineactual: 'Cost Overview'!$F$8-'Cost Overview'!$M$8
Name margendirectofinal: margendirectobaselineactual+'Cost Planning'!$J$5+'Cost Planning'!$E$47+'Cost Planning'!$E$48+'Cost Planning'!$J$50+'Cost Planning'!$J$64
Name pedidobaselineactual: 'Cost Overview'!$F$8
Name UTILIZACION: 0.93

Sheet Project Infor
B3: CORE (COst REport) - AT
B5: Fecha Actual | C5: 46153
B6: Fecha Reporting | C6: =DATE(IF(EXACT(MONTH(EDATE(C5,0)),"12"),YEAR(C5)+1,YEAR(C5)),MONTH(EDATE(C5,1)),1) -> 46174 | D6: =DATE(YEAR(C6),MONTH(C6),1) -> 46174
B8: Fecha de Inicio CORE | C8: 46023
B9: Fecha Fin CORE | C9: 47483
B10: WBS-Element | C10: ZEV-ATE0012-1001
B11: Descripción | C11: Lote 2: Núcleo Estructural Java
B12: Práctica principal | C12: AMS
B13: Otras prácticas relacionadas
C15: CÓDIGO | D15: DESCRIPCIÓN
B16: Cliente | C16: CUST-CE-TEST | D16: Comunidad Educacion
B18: Contrato / Expediente | C18: SLFC 20251160543
B19: Pedido (Order) | C19: SO-TEST-20251160543
C21: COD EMPLEADO | D21: NOMBRE Y APELLIDOS
B22: Project Manager | C22: E92001 | D22: PM AT Test
B23: Practice Leader | C23: E92002 | D23: Practice Leader AT Test
B24: Sales Manager | C24: E92003 | D24: Sales Manager AT Test
B26: PRESUPUESTO INICIAL (PPO)
B28: Pedido | C28: 465000
B29: Horas estimadas | C29: 14256
B30: Coste Recursos | C30: 356584.84
B31: Riegos | C31: 3565.85
B32: Garantía | C32: 0
B33: Gastos | C33: 0
B34: Compras | C34: 0
B35: Coste Directo | C35: =SUM(C30:C34) -> 360150.69
B37: Margen Directo | C37: =IF(C28=0,0,(C28-C35)/C28) -> 0.22548239
B38: Margen Bruto | C38: =IF(C28=0,0,(C28-(SUM(C30,C31,C32)/UTILIZACION)-SUM(C34,C33))/C28) -> 0.16718536
B40: Comentarios adicionales Presupuesto inicial
B43: PRESUPUESTO YA CONSUMIDO
B45: Venta incurrida
B46: Horas realizadas
B47: Coste Recursos incurrido
B48: Gastos incurridos
B49: Compras incurridas
B50: Coste Directo | C50: =SUM(C47:C49) -> 0
B52: Margen Directo (To Date) | C52: =IF(C45=0,0,(C45-C50)/C45) -> 0
B54: Facturación ya emitida
B56: Comentarios adicionales Presupuesto ya consumido
B60: Prácticas
B61: Advanced Services
B62: Advanced Services (Data Analytics)
B63: Advanced Services (PMO)
B64: Advanced Services (Testing & QA)
B65: CAU
B66: EAI (Enterprise App Integration) & Cloud Native
B67: Infraestructure MS
B68: Manufacturing
B69: Mobility solutions
... B76: TIWORKS

Sheet Cost Overview
B2: WBS-Element | C2: ='Project Infor'!C10 -> ZEV-ATE0012-1001 | D2: ='Project Infor'!C11 -> Lote 2: Núcleo Estructural Java
B5: BASELINE ACTUAL | U5: pneta | V5: operac | W5: coste r. | X5: reservas | Y5: gastos | Z5: compras | AA5: Venta
F6: PEDIDO IMPORTE NETO | G6: COSTE RECURSOS | H6: HORAS | I6: RIESGOS | J6: GARANTÍA | K6: GASTOS | L6: COMPRAS | M6: COSTE DIRECTO | N6: MARGEN DIRECTO | O6: MARGEN BRUTO
B7: PROYECCION DEL PROYECTO SIN REESTIMACIONES | F7: =SUM(F12,F36) -> 465000 | G7: =SUM(G12,G36) -> 356584.84 | H7: =SUM(H12,H36) -> 14256 | I7: =SUM(I12,I36) -> 3565.85 | J7: =SUM(J12,J36) -> 0 | K7: =SUM(K12,K36) -> 0 | L7: =SUM(L12,L36) -> 0 | M7: =SUM(G7,I7,J7,K7,L7) -> 360150.69 | N7: =IF(F7=0,0,(F7-G7-J7-K7-I7-L7)/F7) -> 0.22548239 | O7: =IF(F7=0,0,(F7-G7/UTILIZACION-I7/UTILIZACION-J7/UTILIZACION-K7-L7)/F7) -> 0.16718536
B8: LINEA BASE ACTUAL - PROYECCION DEL PROYECTO FINAL | F8: =F7 -> 465000 | G8: =G7+G37 -> 356584.84 | H8: =H7+H37 -> 14256 | I8: =I7+I37 -> 3565.85 | J8: =J7+J37 -> 0 | K8: =K7+K37 -> 0 | L8: =L7+L37 -> 0 | M8: =M7+M37 -> 360150.69 | N8: =IF(F8=0,0,(F8-G8-J8-K8-I8-L8)/F8) -> 0.22548239 | O8: =IF(F8=0,0,(F8-G8/UTILIZACION-I8/UTILIZACION-J8/UTILIZACION-K8-L8)/F8) -> 0.16718536 | P8: {=margendirectobaselineactual} -> 104849.31
B10: BASELINE INICIAL | U10: pneta | V10: operac | W10: coste r. | X10: reservas | Y10: gastos | Z10: compras | AA10: Venta
C11: FECHA | D11: LÍNEA DE PEDIDO | E11: DESCRIPCIÓN | F11: IMPORTE NETO | G11: COSTE RECURSOS | H11: HORAS | I11: RIESGOS | J11: GARANTÍA | K11: GASTOS | L11: COMPRAS | M11: COSTE DIRECTO | N11: MARGEN DIRECTO | O11: MARGEN BRUTO
D12: 10 | E12: Apertura contrato | F12: ='Project Infor'!C28 -> 465000 | G12: ='Project Infor'!C30 -> 356584.84 | H12: ='Project Infor'!C29 -> 14256 | I12: ='Project Infor'!C31 -> 3565.85 | J12: ='Project Infor'!C32 -> 0 | K12: ='Project Infor'!C33 -> 0 | L12: ='Project Infor'!C34 -> 0 | M12: =SUM(G12,I12,J12,K12,L12) -> 360150.69 | N12: =IF(F12=0,0,(F12-G12-J12-K12-I12-L12)/F12) -> 0.22548239 | O12: =IF(F12=0,0,(F12-G12/UTILIZACION-I12/UTILIZACION-J12/UTILIZACION-K12-L12)/F12) -> 0.16718536 | T12: *** Ocultar estos datos en la versión definitiva
B14: Cambios sobre la BASELINE INICIAL | U14: pneta | V14: operac | W14: coste r. | X14: reservas | Y14: gastos | Z14: compras | AA14: Venta
B15: TIPO CAMBIO | C15: FECHA | D15: LÍNEA DE PEDIDO | E15: DESCRIPCIÓN | F15: PEDIDO IMPORTE NETO | G15: COSTE RECURSOS | H15: HORAS | I15: RIESGOS | J15: GARANTÍA | K15: GASTOS | L15: COMPRAS | M15: COSTE DIRECTO | N15: MARGEN DIRECTO | O15: MARGEN BRUTO | P15: AUTORIZADO POR CCO | R15: DATOS ADICIONALES AMPLIACION
M16: =SUM(G16,I16,J16,K16,L16) -> 0 | N16: =IF(F16=0,0,(F16-G16-J16-K16-I16-L16)/F16) -> 0 | O16: =IF(F16=0,0,(F16-G16/UTILIZACION-I16/UTILIZACION-J16/UTILIZACION-K16-L16)/F16) -> 0 | R16: ej:otro cliente, PO asociada, … | T16: =IF(C16<>"",IF((YEAR(C16)&MONTH(C16))<(YEAR(Inicio)&MONTH(Inicio)),YEAR(Inicio)&MONTH(Inicio),YEAR(C16)&MONTH(C16)),YEAR(C16)&MONTH(C16)) -> 19001 | U16: =AA16-Y16-X16-W16 -> 104849.31 | W16: =$G$12+SUM($G$16:G16) -> 356584.84 | X16: =$I$12+SUM($I$16:I16)+$J$12+SUM($J$16:J16) -> 3565.85 | Y16: =$K$12+SUM($K$16:K16) -> 0 | Z16: =$L$12+SUM($L$16:L16) -> 0 | AA16: =$F$12+SUM($F$16:F16) -> 465000
M17: =SUM(G17,I17,J17,K17,L17) -> 0 | N17: =IF(F17=0,0,(F17-G17-J17-K17-I17-L17)/F17) -> 0 | O17: =IF(F17=0,0,(F17-G17/UTILIZACION-I17/UTILIZACION-J17/UTILIZACION-K17-L17)/F17) -> 0 | T17: =IF(C17<>"",IF((YEAR(C17)&MONTH(C17))<(YEAR(Inicio)&MONTH(Inicio)),YEAR(Inicio)&MONTH(Inicio),YEAR(C17)&MONTH(C17)),YEAR(C17)&MONTH(C17)) -> 19001 | U17: =AA17-Y17-X17-W17 -> 104849.31 | W17: =$G$12+SUM($G$16:G17) -> 356584.84 | X17: =$I$12+SUM($I$16:I17)+$J$12+SUM($J$16:J17) -> 3565.85 | Y17: =$K$12+SUM($K$16:K17) -> 0 | Z17: =$L$12+SUM($L$16:L17) -> 0 | AA17: =$F$12+SUM($F$16:F17) -> 465000
M18: =SUM(G18,I18,J18,K18,L18) -> 0 | N18: =IF(F18=0,0,(F18-G18-J18-K18-I18-L18)/F18) -> 0 | O18: =IF(F18=0,0,(F18-G18/UTILIZACION-I18/UTILIZACION-J18/UTILIZACION-K18-L18)/F18) -> 0 | T18: =IF(C18<>"",IF((YEAR(C18)&MONTH(C18))<(YEAR(Inicio)&MONTH(Inicio)),YEAR(Inicio)&MONTH(Inicio),YEAR(C18)&MONTH(C18)),YEAR(C18)&MONTH(C18)) -> 19001 | U18: =AA18-Y18-X18-W18 -> 104849.31 | W18: =$G$12+SUM($G$16:G18) -> 356584.84 | X18: =$I$12+SUM($I$16:I18)+$J$12+SUM($J$16:J18) -> 3565.85 | Y18: =$K$12+SUM($K$16:K18) -> 0 | Z18: =$L$12+SUM($L$16:L18) -> 0 | AA18: =$F$12+SUM($F$16:F18) -> 465000
M19: =SUM(G19,I19,J19,K19,L19) -> 0 | N19: =IF(F19=0,0,(F19-G19-J19-K19-I19-L19)/F19) -> 0 | O19: =IF(F19=0,0,(F19-G19/UTILIZACION-I19/UTILIZACION-J19/UTILIZACION-K19-L19)/F19) -> 0 | T19: =IF(C19<>"",IF((YEAR(C19)&MONTH(C19))<(YEAR(Inicio)&MONTH(Inicio)),YEAR(Inicio)&MONTH(Inicio),YEAR(C19)&MONTH(C19)),YEAR(C19)&MONTH(C19)) -> 19001 | U19: =AA19-Y19-X19-W19 -> 104849.31 | W19: =$G$12+SUM($G$16:G19) -> 356584.84 | X19: =$I$12+SUM($I$16:I19)+$J$12+SUM($J$16:J19) -> 3565.85 | Y19: =$K$12+SUM($K$16:K19) -> 0 | Z19: =$L$12+SUM($L$16:L19) -> 0 | AA19: =$F$12+SUM($F$16:F19) -> 465000
M20: =SUM(G20,I20,J20,K20,L20) -> 0 | N20: =IF(F20=0,0,(F20-G20-J20-K20-I20-L20)/F20) -> 0 | O20: =IF(F20=0,0,(F20-G20/UTILIZACION-I20/UTILIZACION-J20/UTILIZACION-K20-L20)/F20) -> 0 | T20: =IF(C20<>"",IF((YEAR(C20)&MONTH(C20))<(YEAR(Inicio)&MONTH(Inicio)),YEAR(Inicio)&MONTH(Inicio),YEAR(C20)&MONTH(C20)),YEAR(C20)&MONTH(C20)) -> 19001 | U20: =AA20-Y20-X20-W20 -> 104849.31 | W20: =$G$12+SUM($G$16:G20) -> 356584.84 | X20: =$I$12+SUM($I$16:I20)+$J$12+SUM($J$16:J20) -> 3565.85 | Y20: =$K$12+SUM($K$16:K20) -> 0 | Z20: =$L$12+SUM($L$16:L20) -> 0 | AA20: =$F$12+SUM($F$16:F20) -> 465000
M21: =SUM(G21,I21,J21,K21,L21) -> 0 | N21: =IF(F21=0,0,(F21-G21-J21-K21-I21-L21)/F21) -> 0 | O21: =IF(F21=0,0,(F21-G21/UTILIZACION-I21/UTILIZACION-J21/UTILIZACION-K21-L21)/F21) -> 0 | T21: =IF(C21<>"",IF((YEAR(C21)&MONTH(C21))<(YEAR(Inicio)&MONTH(Inicio)),YEAR(Inicio)&MONTH(Inicio),YEAR(C21)&MONTH(C21)),YEAR(C21)&MONTH(C21)) -> 19001 | U21: =AA21-Y21-X21-W21 -> 104849.31 | W21: =$G$12+SUM($G$16:G21) -> 356584.84 | X21: =$I$12+SUM($I$16:I21)+$J$12+SUM($J$16:J21) -> 3565.85 | Y21: =$K$12+SUM($K$16:K21) -> 0 | Z21: =$L$12+SUM($L$16:L21) -> 0 | AA21: =$F$12+SUM($F$16:F21) -> 465000
M22: =SUM(G22,I22,J22,K22,L22) -> 0 | N22: =IF(F22=0,0,(F22-G22-J22-K22-I22-L22)/F22) -> 0 | O22: =IF(F22=0,0,(F22-G22/UTILIZACION-I22/UTILIZACION-J22/UTILIZACION-K22-L22)/F22) -> 0 | T22: =IF(C22<>"",IF((YEAR(C22)&MONTH(C22))<(YEAR(Inicio)&MONTH(Inicio)),YEAR(Inicio)&MONTH(Inicio),YEAR(C22)&MONTH(C22)),YEAR(C22)&MONTH(C22)) -> 19001 | U22: =AA22-Y22-X22-W22 -> 104849.31 | W22: =$G$12+SUM($G$16:G22) -> 356584.84 | X22: =$I$12+SUM($I$16:I22)+$J$12+SUM($J$16:J22) -> 3565.85 | Y22: =$K$12+SUM($K$16:K22) -> 0 | Z22: =$L$12+SUM($L$16:L22) -> 0 | AA22: =$F$12+SUM($F$16:F22) -> 465000
M23: =SUM(G23,I23,J23,K23,L23) -> 0 | N23: =IF(F23=0,0,(F23-G23-J23-K23-I23-L23)/F23) -> 0 | O23: =IF(F23=0,0,(F23-G23/UTILIZACION-I23/UTILIZACION-J23/UTILIZACION-K23-L23)/F23) -> 0 | T23: =IF(C23<>"",IF((YEAR(C23)&MONTH(C23))<(YEAR(Inicio)&MONTH(Inicio)),YEAR(Inicio)&MONTH(Inicio),YEAR(C23)&MONTH(C23)),YEAR(C23)&MONTH(C23)) -> 19001 | U23: =AA23-Y23-X23-W23 -> 104849.31 | W23: =$G$12+SUM($G$16:G23) -> 356584.84 | X23: =$I$12+SUM($I$16:I23)+$J$12+SUM($J$16:J23) -> 3565.85 | Y23: =$K$12+SUM($K$16:K23) -> 0 | Z23: =$L$12+SUM($L$16:L23) -> 0 | AA23: =$F$12+SUM($F$16:F23) -> 465000
M24: =SUM(G24,I24,J24,K24,L24) -> 0 | N24: =IF(F24=0,0,(F24-G24-J24-K24-I24-L24)/F24) -> 0 | O24: =IF(F24=0,0,(F24-G24/UTILIZACION-I24/UTILIZACION-J24/UTILIZACION-K24-L24)/F24) -> 0 | T24: =IF(C24<>"",IF((YEAR(C24)&MONTH(C24))<(YEAR(Inicio)&MONTH(Inicio)),YEAR(Inicio)&MONTH(Inicio),YEAR(C24)&MONTH(C24)),YEAR(C24)&MONTH(C24)) -> 19001 | U24: =AA24-Y24-X24-W24 -> 104849.31 | W24: =$G$12+SUM($G$16:G24) -> 356584.84 | X24: =$I$12+SUM($I$16:I24)+$J$12+SUM($J$16:J24) -> 3565.85 | Y24: =$K$12+SUM($K$16:K24) -> 0 | Z24: =$L$12+SUM($L$16:L24) -> 0 | AA24: =$F$12+SUM($F$16:F24) -> 465000
M25: =SUM(G25,I25,J25,K25,L25) -> 0 | N25: =IF(F25=0,0,(F25-G25-J25-K25-I25-L25)/F25) -> 0 | O25: =IF(F25=0,0,(F25-G25/UTILIZACION-I25/UTILIZACION-J25/UTILIZACION-K25-L25)/F25) -> 0 | T25: =IF(C25<>"",IF((YEAR(C25)&MONTH(C25))<(YEAR(Inicio)&MONTH(Inicio)),YEAR(Inicio)&MONTH(Inicio),YEAR(C25)&MONTH(C25)),YEAR(C25)&MONTH(C25)) -> 19001 | U25: =AA25-Y25-X25-W25 -> 104849.31 | W25: =$G$12+SUM($G$16:G25) -> 356584.84 | X25: =$I$12+SUM($I$16:I25)+$J$12+SUM($J$16:J25) -> 3565.85 | Y25: =$K$12+SUM($K$16:K25) -> 0 | Z25: =$L$12+SUM($L$16:L25) -> 0 | AA25: =$F$12+SUM($F$16:F25) -> 465000
M26: =SUM(G26,I26,J26,K26,L26) -> 0 | N26: =IF(F26=0,0,(F26-G26-J26-K26-I26-L26)/F26) -> 0 | O26: =IF(F26=0,0,(F26-G26/UTILIZACION-I26/UTILIZACION-J26/UTILIZACION-K26-L26)/F26) -> 0 | T26: =IF(C26<>"",IF((YEAR(C26)&MONTH(C26))<(YEAR(Inicio)&MONTH(Inicio)),YEAR(Inicio)&MONTH(Inicio),YEAR(C26)&MONTH(C26)),YEAR(C26)&MONTH(C26)) -> 19001 | U26: =AA26-Y26-X26-W26 -> 104849.31 | W26: =$G$12+SUM($G$16:G26) -> 356584.84 | X26: =$I$12+SUM($I$16:I26)+$J$12+SUM($J$16:J26) -> 3565.85 | Y26: =$K$12+SUM($K$16:K26) -> 0 | Z26: =$L$12+SUM($L$16:L26) -> 0 | AA26: =$F$12+SUM($F$16:F26) -> 465000
M27: =SUM(G27,I27,J27,K27,L27) -> 0 | N27: =IF(F27=0,0,(F27-G27-J27-K27-I27-L27)/F27) -> 0 | O27: =IF(F27=0,0,(F27-G27/UTILIZACION-I27/UTILIZACION-J27/UTILIZACION-K27-L27)/F27) -> 0 | T27: =IF(C27<>"",IF((YEAR(C27)&MONTH(C27))<(YEAR(Inicio)&MONTH(Inicio)),YEAR(Inicio)&MONTH(Inicio),YEAR(C27)&MONTH(C27)),YEAR(C27)&MONTH(C27)) -> 19001 | U27: =AA27-Y27-X27-W27 -> 104849.31 | W27: =$G$12+SUM($G$16:G27) -> 356584.84 | X27: =$I$12+SUM($I$16:I27)+$J$12+SUM($J$16:J27) -> 3565.85 | Y27: =$K$12+SUM($K$16:K27) -> 0 | Z27: =$L$12+SUM($L$16:L27) -> 0 | AA27: =$F$12+SUM($F$16:F27) -> 465000
M28: =SUM(G28,I28,J28,K28,L28) -> 0 | N28: =IF(F28=0,0,(F28-G28-J28-K28-I28-L28)/F28) -> 0 | O28: =IF(F28=0,0,(F28-G28/UTILIZACION-I28/UTILIZACION-J28/UTILIZACION-K28-L28)/F28) -> 0 | T28: =IF(C28<>"",IF((YEAR(C28)&MONTH(C28))<(YEAR(Inicio)&MONTH(Inicio)),YEAR(Inicio)&MONTH(Inicio),YEAR(C28)&MONTH(C28)),YEAR(C28)&MONTH(C28)) -> 19001 | U28: =AA28-Y28-X28-W28 -> 104849.31 | W28: =$G$12+SUM($G$16:G28) -> 356584.84 | X28: =$I$12+SUM($I$16:I28)+$J$12+SUM($J$16:J28) -> 3565.85 | Y28: =$K$12+SUM($K$16:K28) -> 0 | Z28: =$L$12+SUM($L$16:L28) -> 0 | AA28: =$F$12+SUM($F$16:F28) -> 465000
... M35: =SUM(G35,I35,J35,K35,L35) -> 0 | N35: =IF(F35=0,0,(F35-G35-J35-K35-I35-L35)/F35) -> 0 | O35: =IF(F35=0,0,(F35-G35/UTILIZACION-I35/UTILIZACION-J35/UTILIZACION-K35-L35)/F35) -> 0 | T35: =IF(C35<>"",IF((YEAR(C35)&MONTH(C35))<(YEAR(Inicio)&MONTH(Inicio)),YEAR(Inicio)&MONTH(Inicio),YEAR(C35)&MONTH(C35)),YEAR(C35)&MONTH(C35)) -> 19001 | U35: =AA35-Y35-X35-W35 -> 104849.31 | W35: =$G$12+SUM($G$16:G35) -> 356584.84 | X35: =$I$12+SUM($I$16:I35)+$J$12+SUM($J$16:J35) -> 3565.85 | Y35: =$K$12+SUM($K$16:K35) -> 0 | Z35: =$L$12+SUM($L$16:L35) -> 0 | AA35: =$F$12+SUM($F$16:F35) -> 465000
B36: TOTAL AMPLIACIONES | F36: =SUMIF(B16:B35,"AMPLIACION",F16:F35) -> 0 | G36: =SUMIF(B16:B35,"AMPLIACION",G16:G35) -> 0 | H36: =SUMIF(B16:B35,"AMPLIACION",H16:H35) -> 0 | I36: =SUMIF(B16:B35,"AMPLIACION",I16:I35) -> 0 | J36: =SUMIF(B16:B35,"AMPLIACION",J16:J35) -> 0 | K36: =SUMIF(B16:B35,"AMPLIACION",K16:K35) -> 0 | L36: =SUMIF(B16:B35,"AMPLIACION",L16:L35) -> 0 | M36: =SUM(G36,I36,J36,K36,L36) -> 0 | N36: =IF(F36=0,0,(F36-G36-J36-K36-I36-L36)/F36) -> 0 | O36: =IF(F36=0,0,(F36-G36/0.93-I36/0.93-J36/0.93-K36-L36)/F36) -> 0
B37: TOTAL REESTIMACIONES | F37: =SUMIF(B16:B35,"REESTIMACION",F16:F35) -> 0 | G37: =SUMIF(B16:B35,"REESTIMACION",G16:G35) -> 0 | H37: =SUMIF(B16:B35,"REESTIMACION",H16:H35) -> 0 | I37: =SUMIF(B16:B35,"REESTIMACION",I16:I35) -> 0 | J37: =SUMIF(B16:B35,"REESTIMACION",J16:J35) -> 0 | K37: =SUMIF(B16:B35,"REESTIMACION",K16:K35) -> 0 | L37: =SUMIF(B16:B35,"REESTIMACION",L16:L35) -> 0 | M37: =SUM(G37,I37,J37,K37,L37) -> 0 | N37: =IF(F37=0,0,(F37-G37-J37-K37-I37-L37)/F37) -> 0 | O37: =IF(F37=0,0,(F37-G37/0.93-I37/0.93-J37/0.93-K37-L37)/F37) -> 0
B48: Comentarios adicionales Cost Overview
B49: <dd/mm/aaaa> comentario <dd/mm/aaaa> comentario <dd/mm/aaaa> comentario

Sheet Resources
B2: WBS-Element | C2: ='Project Infor'!C10 -> ZEV-ATE0012-1001 | D2: ='Project Infor'!C11 -> Lote 2: Núcleo Estructural Java
B5: Equipo GETRONICS. Costes hora por perfil. | E5: (!) IMPORTANTE: se debe indicar si cada perfil es o no INTERCO
B6: COD EMPLEADO | C6: INICIALES | D6: INTERCO | E6: ROL | G6: 46023 | H6: 46054 | I6: 46082 | J6: 46113 | K6: 46143 | L6: 46174 | M6: 46204 | N6: 46235 | O6: 46266 | P6: 46296 | Q6: 46327 | R6: 46357 | S6: 46388 | T6: 46419 | U6: 46447 | V6: 46478 | W6: 46508 | X6: 46539 | Y6: 46569 | Z6: 46600 | AA6: 46631 | AB6: 46661 | AC6: 46692 | AD6: 46722 | AE6: 46753 | AF6: 46784 | AG6: 46813 | AH6: 46844 | AI6: 46874 | AJ6: 46905 | AK6: 46935 | AL6: 46966 | AM6: 46997 | AN6: 47027 | AO6: 47058 | AP6: 47088 | AQ6: 47119 | AR6: 47150 | AS6: 47178 | AT6: 47209 | AU6: 47239 | AV6: 47270 | AW6: 47300 | AX6: 47331 | AY6: 47362 | AZ6: 47392 | BA6: 47423 | BB6: 47453 | BC6: =EOMONTH(BB6,1) -> 47514 | BD6: =EOMONTH(BC6,1) -> 47542 | BE6: =EOMONTH(BD6,1) -> 47573 | BF6: =EOMONTH(BE6,1) -> 47603 | BG6: =EOMONTH(BF6,1) -> 47634 | BH6: =EOMONTH(BG6,1) -> 47664 | BI6: =EOMONTH(BH6,1) -> 47695 | BJ6: =EOMONTH(BI6,1) -> 47726 | ... BN6: =EOMONTH(BM6,1) -> 47848
B7: E92012 | C7: AP | D7: NO | E7: Susana Matarranz | F7: Coste/hora | G7: 32.84 | H7: 32.84 | I7: 32.84 | J7: 32.84 | K7: 32.84 | L7: 32.84 | M7: 32.84 | N7: 32.84 | O7: 32.84 | P7: 32.84 | Q7: 32.84 | R7: 32.84 | S7: 32.84 | T7: 32.84 | U7: 32.84 | V7: 32.84 | W7: 32.84 | X7: 32.84 | Y7: 32.84 | Z7: 32.84 | AA7: 32.84 | AB7: 32.84 | AC7: 32.84 | AD7: 32.84 | AE7: 32.84 | AF7: 32.84 | AG7: 32.84 | AH7: 32.84 | AI7: 32.84 | AJ7: 32.84 | AK7: 32.84 | AL7: 32.84 | AM7: 32.84 | AN7: 32.84 | AO7: 32.84 | AP7: 32.84 | AQ7: 32.84 | AR7: 32.84 | AS7: 32.84 | AT7: 32.84 | AU7: 32.84 | AV7: 32.84 | AW7: 32.84 | AX7: 32.84 | AY7: 32.84 | AZ7: 32.84 | BA7: 32.84 | BB7: 32.84
B8: E92012 | C8: AP | D8: NO | E8: Susana Matarranz | F8: Tarifa venta (Hora o Jornada) | G8: 44.347015 | H8: 44.347015 | I8: 44.347015 | J8: 44.347015 | K8: 44.347015 | L8: 44.347015 | M8: 44.347015 | N8: 44.347015 | O8: 44.347015 | P8: 44.347015 | Q8: 44.347015 | R8: 44.347015 | S8: 44.347015 | T8: 44.347015 | U8: 44.347015 | V8: 44.347015 | W8: 44.347015 | X8: 44.347015 | Y8: 44.347015 | Z8: 44.347015 | AA8: 44.347015 | AB8: 44.347015 | AC8: 44.347015 | AD8: 44.347015 | AE8: 44.347015 | AF8: 44.347015 | AG8: 44.347015 | AH8: 44.347015 | AI8: 44.347015 | AJ8: 44.347015 | AK8: 44.347015 | AL8: 44.347015 | AM8: 44.347015 | AN8: 44.347015 | AO8: 44.347015 | AP8: 44.347015 | AQ8: 44.347015 | AR8: 44.347015 | AS8: 44.347015 | AT8: 44.347015 | AU8: 44.347015 | AV8: 44.347015 | AW8: 44.347015 | AX8: 44.347015 | AY8: 44.347015 | AZ8: 44.347015 | BA8: 44.347015 | BB8: 44.347015
B9: E92011 | C9: PR | D9: NO | E9: Jorge Puertas | F9: Coste/hora | G9: 15.17 | H9: 15.17 | I9: 15.17 | J9: 15.17 | K9: 15.17 | L9: 15.17 | M9: 15.17 | N9: 15.17 | O9: 15.17 | P9: 15.17 | Q9: 15.17 | R9: 15.17 | S9: 15.17 | T9: 15.17 | U9: 15.17 | V9: 15.17 | W9: 15.17 | X9: 15.17 | Y9: 15.17 | Z9: 15.17 | AA9: 15.17 | AB9: 15.17 | AC9: 15.17 | AD9: 15.17 | AE9: 15.17 | AF9: 15.17 | AG9: 15.17 | AH9: 15.17 | AI9: 15.17 | AJ9: 15.17 | AK9: 15.17 | AL9: 15.17 | AM9: 15.17 | AN9: 15.17 | AO9: 15.17 | AP9: 15.17 | AQ9: 15.17 | AR9: 15.17 | AS9: 15.17 | AT9: 15.17 | AU9: 15.17 | AV9: 15.17 | AW9: 15.17 | AX9: 15.17 | AY9: 15.17 | AZ9: 15.17 | BA9: 15.17 | BB9: 15.17
B10: E92011 | C10: PR | D10: NO | E10: Jorge Puertas | F10: Tarifa venta (Hora o Jornada) | G10: 20.485505 | H10: 20.485505 | I10: 20.485505 | J10: 20.485505 | K10: 20.485505 | L10: 20.485505 | M10: 20.485505 | N10: 20.485505 | O10: 20.485505 | P10: 20.485505 | Q10: 20.485505 | R10: 20.485505 | S10: 20.485505 | T10: 20.485505 | U10: 20.485505 | V10: 20.485505 | W10: 20.485505 | X10: 20.485505 | Y10: 20.485505 | Z10: 20.485505 | AA10: 20.485505 | AB10: 20.485505 | AC10: 20.485505 | AD10: 20.485505 | AE10: 20.485505 | AF10: 20.485505 | AG10: 20.485505 | AH10: 20.485505 | AI10: 20.485505 | AJ10: 20.485505 | AK10: 20.485505 | AL10: 20.485505 | AM10: 20.485505 | AN10: 20.485505 | AO10: 20.485505 | AP10: 20.485505 | AQ10: 20.485505 | AR10: 20.485505 | AS10: 20.485505 | AT10: 20.485505 | AU10: 20.485505 | AV10: 20.485505 | AW10: 20.485505 | AX10: 20.485505 | AY10: 20.485505 | AZ10: 20.485505 | BA10: 20.485505 | BB10: 20.485505
B11: E92013 | C11: AP | D11: NO | E11: Sopore especializado | F11: Coste/hora | G11: 20 | H11: 20 | I11: 20 | J11: 20 | K11: 20 | L11: 20 | M11: 20 | N11: 20 | O11: 20 | P11: 20 | Q11: 20 | R11: 20 | S11: 20 | T11: 20 | U11: 20 | V11: 20 | W11: 20 | X11: 20 | Y11: 20 | Z11: 20 | AA11: 20 | AB11: 20 | AC11: 20 | AD11: 20 | AE11: 20 | AF11: 20 | AG11: 20 | AH11: 20 | AI11: 20 | AJ11: 20 | AK11: 20 | AL11: 20 | AM11: 20 | AN11: 20 | AO11: 20 | AP11: 20 | AQ11: 20 | AR11: 20 | AS11: 20 | AT11: 20 | AU11: 20 | AV11: 20 | AW11: 20 | AX11: 20 | AY11: 20 | AZ11: 20 | BA11: 20 | BB11: 20
B12: E92013 | C12: AP | D12: NO | E12: Sopore especializado | F12: Tarifa venta (Hora o Jornada) | G12: 27.009375 | H12: 27.009375 | I12: 27.009375 | J12: 27.009375 | K12: 27.009375 | L12: 27.009375 | M12: 27.009375 | N12: 27.009375 | O12: 27.009375 | P12: 27.009375 | Q12: 27.009375 | R12: 27.009375 | S12: 27.009375 | T12: 27.009375 | U12: 27.009375 | V12: 27.009375 | W12: 27.009375 | X12: 27.009375 | Y12: 27.009375 | Z12: 27.009375 | AA12: 27.009375 | AB12: 27.009375 | AC12: 27.009375 | AD12: 27.009375 | AE12: 27.009375 | AF12: 27.009375 | AG12: 27.009375 | AH12: 27.009375 | AI12: 27.009375 | AJ12: 27.009375 | AK12: 27.009375 | AL12: 27.009375 | AM12: 27.009375 | AN12: 27.009375 | AO12: 27.009375 | AP12: 27.009375 | AQ12: 27.009375 | AR12: 27.009375 | AS12: 27.009375 | AT12: 27.009375 | AU12: 27.009375 | AV12: 27.009375 | AW12: 27.009375 | AX12: 27.009375 | AY12: 27.009375 | AZ12: 27.009375 | BA12: 27.009375 | BB12: 27.009375
F13: Coste/hora
F14: Tarifa venta (Hora o Jornada)
F15: Coste/hora
F16: Tarifa venta (Hora o Jornada)
F17: Coste/hora
F18: Tarifa venta (Hora o Jornada)
F19: Coste/hora
F20: Tarifa venta (Hora o Jornada)
F21: Coste/hora
F22: Tarifa venta (Hora o Jornada)
F23: Coste/hora
F24: Tarifa venta (Hora o Jornada)
... F36: Tarifa venta (Hora o Jornada)
B45: Tipo de Roles
B46: COD | C46: DESCRIPCION
B47: PM | C47: Project Manager
B48: CO | C48: Consultor
B49: ANF | C49: Analista Funcional
B50: AP | C50: Analista Programador
B51: PR | C51: Programador
B52: TEST | C52: Tester
B53: ARQ | C53: Arquitecto
B54: SO | C54: Soporte
B55: TS | C55: Tecnico de sistemas
B56: INST | C56: Tecnico Instalaciones
B57: CAU | C57: Soporte CAU
... B61: DG | C61: Diseño Gráfico

Sheet Cost Planning
B2: WBS-Element | C2: ='Project Infor'!C10 -> ZEV-ATE0012-1001 | D2: ='Project Infor'!C11 -> Lote 2: Núcleo Estructural Java
B5: Equipo GETRONICS | D5: COSTE TOTAL RECURSOS BASELINE | F5: =costerecursosbaselineactual -> 356584.84 | H5: PENDIENTE DE PLANIFICAR | J5: =F5-SUM(F40:BO41) -> 15651.16 | L5: PENDIENTE DE PEDIDO | N5: =-(pedidobaselineactual-SUM(H44:BO44)-SUM(H62:BO62)-SUM(H78:BO78)) -> -4604
H7: =IF(H8>EOMONTH(FIN,0),"Fin",IF(H8>FECHA,"Prev","Real")) -> Real | I7: =IF(I8>EOMONTH(FIN,0),"Fin",IF(I8>FECHA,"Prev","Real")) -> Real | J7: =IF(J8>EOMONTH(FIN,0),"Fin",IF(J8>FECHA,"Prev","Real")) -> Real | K7: =IF(K8>EOMONTH(FIN,0),"Fin",IF(K8>FECHA,"Prev","Real")) -> Real | L7: =IF(L8>EOMONTH(FIN,0),"Fin",IF(L8>FECHA,"Prev","Real")) -> Real | M7: =IF(M8>EOMONTH(FIN,0),"Fin",IF(M8>FECHA,"Prev","Real")) -> Real | N7: =IF(N8>EOMONTH(FIN,0),"Fin",IF(N8>FECHA,"Prev","Real")) -> Prev | O7: =IF(O8>EOMONTH(FIN,0),"Fin",IF(O8>FECHA,"Prev","Real")) -> Prev | ... BO7: =IF(BO8>EOMONTH(FIN,0),"Fin",IF(BO8>FECHA,"Prev","Real")) -> Fin
B8: COD EMPLEADO | C8: INICIALES | D8: INTERCO | E8: ROL | F8: CODIGO INTERCO | H8: 46023 | I8: 46054 | J8: 46082 | K8: 46113 | L8: 46143 | M8: 46174 | N8: 46204 | O8: 46235 | P8: 46266 | Q8: 46296 | R8: 46327 | S8: 46357 | T8: 46388 | U8: 46419 | V8: 46447 | W8: 46478 | X8: 46508 | Y8: 46539 | Z8: 46569 | AA8: 46600 | AB8: 46631 | AC8: 46661 | AD8: 46692 | AE8: 46722 | AF8: 46753 | AG8: 46784 | AH8: 46813 | AI8: 46844 | AJ8: 46874 | AK8: 46905 | AL8: 46935 | AM8: 46966 | AN8: 46997 | AO8: 47027 | AP8: 47058 | AQ8: 47088 | AR8: 47119 | AS8: 47150 | AT8: 47178 | AU8: 47209 | AV8: 47239 | AW8: 47270 | AX8: 47300 | AY8: 47331 | AZ8: 47362 | BA8: 47392 | BB8: 47423 | BC8: 47453 | BD8: =EOMONTH(BC8,1) -> 47514 | BE8: =EOMONTH(BD8,1) -> 47542 | BF8: =EOMONTH(BE8,1) -> 47573 | BG8: =EOMONTH(BF8,1) -> 47603 | BH8: =EOMONTH(BG8,1) -> 47634 | BI8: =EOMONTH(BH8,1) -> 47664 | BJ8: =EOMONTH(BI8,1) -> 47695 | BK8: =EOMONTH(BJ8,1) -> 47726 | ... BO8: =EOMONTH(BN8,1) -> 47848
B9: HORAS REALES RECURSOS entidad PROYECTO + INTERCO | F9: ='Project Infor'!C46 -> 0 | H9: =SUMIF($G$10:$G$39,"Horas Reales",H$10:H$39) -> 297 | I9: =SUMIF($G$10:$G$39,"Horas Reales",I$10:I$39) -> 297 | J9: =SUMIF($G$10:$G$39,"Horas Reales",J$10:J$39) -> 297 | K9: =SUMIF($G$10:$G$39,"Horas Reales",K$10:K$39) -> 297 | L9: =SUMIF($G$10:$G$39,"Horas Reales",L$10:L$39) -> 297 | M9: =SUMIF($G$10:$G$39,"Horas Reales",M$10:M$39) -> 297 | N9: =SUMIF($G$10:$G$39,"Horas Reales",N$10:N$39) -> 297 | O9: =SUMIF($G$10:$G$39,"Horas Reales",O$10:O$39) -> 297 | ... BO9: =SUMIF($G$10:$G$39,"Horas Reales",BO$10:BO$39) -> 0
B10: E92012 | C10: AP | D10: NO | E10: Susana Matarranz | G10: Horas Reales | H10: 145.16667 | I10: 145.16667 | J10: 145.16667 | K10: 145.16667 | L10: 145.16667 | M10: 145.16667 | N10: 145.16667 | O10: 145.16667 | P10: 145.16667 | Q10: 145.16667 | R10: 145.16667 | S10: 145.16667 | T10: 145.16667 | U10: 145.16667 | V10: 145.16667 | W10: 145.16667 | X10: 145.16667 | Y10: 145.16667 | Z10: 145.16667 | AA10: 145.16667 | AB10: 145.16667 | AC10: 145.16667 | AD10: 145.16667 | AE10: 145.16667 | AF10: 145.16667 | AG10: 145.16667 | AH10: 145.16667 | AI10: 145.16667 | AJ10: 145.16667 | AK10: 145.16667 | AL10: 145.16667 | AM10: 145.16667 | AN10: 145.16667 | AO10: 145.16667 | AP10: 145.16667 | AQ10: 145.16667 | AR10: 145.16667 | AS10: 145.16667 | AT10: 145.16667 | AU10: 145.16667 | AV10: 145.16667 | AW10: 145.16667 | AX10: 145.16667 | AY10: 145.16667 | AZ10: 145.16667 | BA10: 145.16667 | BB10: 145.16667 | BC10: 145.16667
B11: E92012 | C11: AP | D11: NO | E11: Susana Matarranz | G11: Horas/Jornadas Facturables | H11: 145.16667 | I11: 145.16667 | J11: 145.16667 | K11: 145.16667 | L11: 145.16667 | M11: 145.16667 | N11: 145.16667 | O11: 145.16667 | P11: 145.16667 | Q11: 145.16667 | R11: 145.16667 | S11: 145.16667 | T11: 145.16667 | U11: 145.16667 | V11: 145.16667 | W11: 145.16667 | X11: 145.16667 | Y11: 145.16667 | Z11: 145.16667 | AA11: 145.16667 | AB11: 145.16667 | AC11: 145.16667 | AD11: 145.16667 | AE11: 145.16667 | AF11: 145.16667 | AG11: 145.16667 | AH11: 145.16667 | AI11: 145.16667 | AJ11: 145.16667 | AK11: 145.16667 | AL11: 145.16667 | AM11: 145.16667 | AN11: 145.16667 | AO11: 145.16667 | AP11: 145.16667 | AQ11: 145.16667 | AR11: 145.16667 | AS11: 145.16667 | AT11: 145.16667 | AU11: 145.16667 | AV11: 145.16667 | AW11: 145.16667 | AX11: 145.16667 | AY11: 145.16667 | AZ11: 145.16667 | BA11: 145.16667 | BB11: 145.16667 | BC11: 145.16667
B12: E92011 | C12: PR | D12: NO | E12: Jorge Puertas | G12: Horas Reales | H12: 145.16667 | I12: 145.16667 | J12: 145.16667 | K12: 145.16667 | L12: 145.16667 | M12: 145.16667 | N12: 145.16667 | O12: 145.16667 | P12: 145.16667 | Q12: 145.16667 | R12: 145.16667 | S12: 145.16667 | T12: 145.16667 | U12: 145.16667 | V12: 145.16667 | W12: 145.16667 | X12: 145.16667 | Y12: 145.16667 | Z12: 145.16667 | AA12: 145.16667 | AB12: 145.16667 | AC12: 145.16667 | AD12: 145.16667 | AE12: 145.16667 | AF12: 145.16667 | AG12: 145.16667 | AH12: 145.16667 | AI12: 145.16667 | AJ12: 145.16667 | AK12: 145.16667 | AL12: 145.16667 | AM12: 145.16667 | AN12: 145.16667 | AO12: 145.16667 | AP12: 145.16667 | AQ12: 145.16667 | AR12: 145.16667 | AS12: 145.16667 | AT12: 145.16667 | AU12: 145.16667 | AV12: 145.16667 | AW12: 145.16667 | AX12: 145.16667 | AY12: 145.16667 | AZ12: 145.16667 | BA12: 145.16667 | BB12: 145.16667 | BC12: 145.16667
B13: E92011 | C13: PR | D13: NO | E13: Jorge Puertas | G13: Horas/Jornadas Facturables | H13: 145.16667 | I13: 145.16667 | J13: 145.16667 | K13: 145.16667 | L13: 145.16667 | M13: 145.16667 | N13: 145.16667 | O13: 145.16667 | P13: 145.16667 | Q13: 145.16667 | R13: 145.16667 | S13: 145.16667 | T13: 145.16667 | U13: 145.16667 | V13: 145.16667 | W13: 145.16667 | X13: 145.16667 | Y13: 145.16667 | Z13: 145.16667 | AA13: 145.16667 | AB13: 145.16667 | AC13: 145.16667 | AD13: 145.16667 | AE13: 145.16667 | AF13: 145.16667 | AG13: 145.16667 | AH13: 145.16667 | AI13: 145.16667 | AJ13: 145.16667 | AK13: 145.16667 | AL13: 145.16667 | AM13: 145.16667 | AN13: 145.16667 | AO13: 145.16667 | AP13: 145.16667 | AQ13: 145.16667 | AR13: 145.16667 | AS13: 145.16667 | AT13: 145.16667 | AU13: 145.16667 | AV13: 145.16667 | AW13: 145.16667 | AX13: 145.16667 | AY13: 145.16667 | AZ13: 145.16667 | BA13: 145.16667 | BB13: 145.16667 | BC13: 145.16667
B14: E92013 | C14: AP | D14: NO | E14: Sopore especializado | G14: Horas Reales | H14: 6.6666667 | I14: 6.6666667 | J14: 6.6666667 | K14: 6.6666667 | L14: 6.6666667 | M14: 6.6666667 | N14: 6.6666667 | O14: 6.6666667 | P14: 6.6666667 | Q14: 6.6666667 | R14: 6.6666667 | S14: 6.6666667 | T14: 6.6666667 | U14: 6.6666667 | V14: 6.6666667 | W14: 6.6666667 | X14: 6.6666667 | Y14: 6.6666667 | Z14: 6.6666667 | AA14: 6.6666667 | AB14: 6.6666667 | AC14: 6.6666667 | AD14: 6.6666667 | AE14: 6.6666667 | AF14: 6.6666667 | AG14: 6.6666667 | AH14: 6.6666667 | AI14: 6.6666667 | AJ14: 6.6666667 | AK14: 6.6666667 | AL14: 6.6666667 | AM14: 6.6666667 | AN14: 6.6666667 | AO14: 6.6666667 | AP14: 6.6666667 | AQ14: 6.6666667 | AR14: 6.6666667 | AS14: 6.6666667 | AT14: 6.6666667 | AU14: 6.6666667 | AV14: 6.6666667 | AW14: 6.6666667 | AX14: 6.6666667 | AY14: 6.6666667 | AZ14: 6.6666667 | BA14: 6.6666667 | BB14: 6.6666667 | BC14: 6.6666667
B15: E92013 | C15: AP | D15: NO | E15: Sopore especializado | G15: Horas/Jornadas Facturables | H15: 6.6666667 | I15: 6.6666667 | J15: 6.6666667 | K15: 6.6666667 | L15: 6.6666667 | M15: 6.6666667 | N15: 6.6666667 | O15: 6.6666667 | P15: 6.6666667 | Q15: 6.6666667 | R15: 6.6666667 | S15: 6.6666667 | T15: 6.6666667 | U15: 6.6666667 | V15: 6.6666667 | W15: 6.6666667 | X15: 6.6666667 | Y15: 6.6666667 | Z15: 6.6666667 | AA15: 6.6666667 | AB15: 6.6666667 | AC15: 6.6666667 | AD15: 6.6666667 | AE15: 6.6666667 | AF15: 6.6666667 | AG15: 6.6666667 | AH15: 6.6666667 | AI15: 6.6666667 | AJ15: 6.6666667 | AK15: 6.6666667 | AL15: 6.6666667 | AM15: 6.6666667 | AN15: 6.6666667 | AO15: 6.6666667 | AP15: 6.6666667 | AQ15: 6.6666667 | AR15: 6.6666667 | AS15: 6.6666667 | AT15: 6.6666667 | AU15: 6.6666667 | AV15: 6.6666667 | AW15: 6.6666667 | AX15: 6.6666667 | AY15: 6.6666667 | AZ15: 6.6666667 | BA15: 6.6666667 | BB15: 6.6666667 | BC15: 6.6666667
G16: Horas Reales
G17: Horas/Jornadas Facturables
G18: Horas Reales
G19: Horas/Jornadas Facturables
G20: Horas Reales
G21: Horas/Jornadas Facturables
G22: Horas Reales
G23: Horas/Jornadas Facturables
G24: Horas Reales
G25: Horas/Jornadas Facturables
G26: Horas Reales
G27: Horas/Jornadas Facturables
... G39: Horas/Jornadas Facturables
B40: COSTE TOTAL RECURSOS entidad PROYECTO (euros) | F40: ='Project Infor'!C47 -> 0 | H40: {=SUMPRODUCT(($D$10:$D$39="NO")*1,($G$10:$G$39="Horas Reales")*1,H$10:H$39,Resources!G7:G36)+H42} -> 7102.785 | I40: {=SUMPRODUCT(($D$10:$D$39="NO")*1,($G$10:$G$39="Horas Reales")*1,I$10:I$39,Resources!H7:H36)+I42} -> 7102.785 | J40: {=SUMPRODUCT(($D$10:$D$39="NO")*1,($G$10:$G$39="Horas Reales")*1,J$10:J$39,Resources!I7:I36)+J42} -> 7102.785 | K40: {=SUMPRODUCT(($D$10:$D$39="NO")*1,($G$10:$G$39="Horas Reales")*1,K$10:K$39,Resources!J7:J36)+K42} -> 7102.785 | L40: {=SUMPRODUCT(($D$10:$D$39="NO")*1,($G$10:$G$39="Horas Reales")*1,L$10:L$39,Resources!K7:K36)+L42} -> 7102.785 | M40: {=SUMPRODUCT(($D$10:$D$39="NO")*1,($G$10:$G$39="Horas Reales")*1,M$10:M$39,Resources!L7:L36)+M42} -> 7102.785 | N40: {=SUMPRODUCT(($D$10:$D$39="NO")*1,($G$10:$G$39="Horas Reales")*1,N$10:N$39,Resources!M7:M36)+N42} -> 7102.785 | O40: {=SUMPRODUCT(($D$10:$D$39="NO")*1,($G$10:$G$39="Horas Reales")*1,O$10:O$39,Resources!N7:N36)+O42} -> 7102.785 | ... BO40: {=SUMPRODUCT(($D$10:$D$39="NO")*1,($G$10:$G$39="Horas Reales")*1,BO$10:BO$39,Resources!BN7:BN36)+BO42} -> 0
B41: COSTE TOTAL RECURSOS INTERCO (euros) | H41: {=SUMPRODUCT(($D$10:$D$39="INTERCO")*1,($G$10:$G$39="Horas Reales")*1,H$10:H$39,Resources!G7:G36)+H43} -> 0 | I41: {=SUMPRODUCT(($D$10:$D$39="INTERCO")*1,($G$10:$G$39="Horas Reales")*1,I$10:I$39,Resources!H7:H36)+I43} -> 0 | J41: {=SUMPRODUCT(($D$10:$D$39="INTERCO")*1,($G$10:$G$39="Horas Reales")*1,J$10:J$39,Resources!I7:I36)+J43} -> 0 | K41: {=SUMPRODUCT(($D$10:$D$39="INTERCO")*1,($G$10:$G$39="Horas Reales")*1,K$10:K$39,Resources!J7:J36)+K43} -> 0 | L41: {=SUMPRODUCT(($D$10:$D$39="INTERCO")*1,($G$10:$G$39="Horas Reales")*1,L$10:L$39,Resources!K7:K36)+L43} -> 0 | M41: {=SUMPRODUCT(($D$10:$D$39="INTERCO")*1,($G$10:$G$39="Horas Reales")*1,M$10:M$39,Resources!L7:L36)+M43} -> 0 | N41: {=SUMPRODUCT(($D$10:$D$39="INTERCO")*1,($G$10:$G$39="Horas Reales")*1,N$10:N$39,Resources!M7:M36)+N43} -> 0 | O41: {=SUMPRODUCT(($D$10:$D$39="INTERCO")*1,($G$10:$G$39="Horas Reales")*1,O$10:O$39,Resources!N7:N36)+O43} -> 0 | ... BO41: {=SUMPRODUCT(($D$10:$D$39="INTERCO")*1,($G$10:$G$39="Horas Reales")*1,BO$10:BO$39,Resources!BN7:BN36)+BO43} -> 0
C42: AJUSTE con SAP (en EUROS) para perfiles NO INTERCO
C43: AJUSTE con SAP (en EUROS) para perfiles INTERCO
B44: VENTA TOTAL HORAS/JORNADAS FACTURABLES (euros) | H44: {=SUMPRODUCT(($G$10:$G$39="Horas/Jornadas Facturables")*1,H$10:H$39,Resources!G7:G36)} -> 9591.5833 | I44: {=SUMPRODUCT(($G$10:$G$39="Horas/Jornadas Facturables")*1,I$10:I$39,Resources!H7:H36)} -> 9591.5833 | J44: {=SUMPRODUCT(($G$10:$G$39="Horas/Jornadas Facturables")*1,J$10:J$39,Resources!I7:I36)} -> 9591.5833 | K44: {=SUMPRODUCT(($G$10:$G$39="Horas/Jornadas Facturables")*1,K$10:K$39,Resources!J7:J36)} -> 9591.5833 | L44: {=SUMPRODUCT(($G$10:$G$39="Horas/Jornadas Facturables")*1,L$10:L$39,Resources!K7:K36)} -> 9591.5833 | M44: {=SUMPRODUCT(($G$10:$G$39="Horas/Jornadas Facturables")*1,M$10:M$39,Resources!L7:L36)} -> 9591.5833 | N44: {=SUMPRODUCT(($G$10:$G$39="Horas/Jornadas Facturables")*1,N$10:N$39,Resources!M7:M36)} -> 9591.5833 | O44: {=SUMPRODUCT(($G$10:$G$39="Horas/Jornadas Facturables")*1,O$10:O$39,Resources!N7:N36)} -> 9591.5833 | ... BO44: {=SUMPRODUCT(($G$10:$G$39="Horas/Jornadas Facturables")*1,BO$10:BO$39,Resources!BN7:BN36)} -> 0
D46: PLANIFICADO BASELINE | E46: PENDIENTE DE PLANIFICAR | H46: ='Project Infor'!C8 -> 46023 | I46: =EOMONTH(H46,1) -> 46081 | J46: =EOMONTH(I46,1) -> 46112 | K46: =EOMONTH(J46,1) -> 46142 | L46: =EOMONTH(K46,1) -> 46173 | M46: =EOMONTH(L46,1) -> 46203 | N46: =EOMONTH(M46,1) -> 46234 | O46: =EOMONTH(N46,1) -> 46265 | P46: =EOMONTH(O46,1) -> 46295 | ... BO46: =EOMONTH(BN46,1) -> 47848
B47: RIESGOS | C47: "accrual future loss" | D47: ='Cost Overview'!I8 -> 3565.85 | E47: =D47-SUM(H47:BO47) -> 0 | BC47: 3565.85
B48: GARANTIA | C48: "Warranty Provisions" | D48: ='Cost Overview'!J8 -> 0 | E48: =D48-SUM(H48:BO48) -> 0 | BC48: 0
B50: GASTOS | D50: COSTE TOTAL GASTOS BASELINE | F50: ='Cost Overview'!K8 -> 0 | H50: PENDIENTE DE PLANIFICAR | J50: =F50-SUM(F61:BO61) -> 0 | L50: (!) El coste de GASTOS planificado es mayor que el de la BASELINE
B52: TIPO GASTO | C52: DESCRIPCION GASTO | D52: INFORMACION ADICIONAL | F52: REFACTURABLE | G52: MARGEN | H52: ='Project Infor'!C8 -> 46023 | I52: =EOMONTH(H52,1) -> 46081 | J52: =EOMONTH(I52,1) -> 46112 | K52: =EOMONTH(J52,1) -> 46142 | L52: =EOMONTH(K52,1) -> 46173 | M52: =EOMONTH(L52,1) -> 46203 | N52: =EOMONTH(M52,1) -> 46234 | O52: =EOMONTH(N52,1) -> 46265 | P52: =EOMONTH(O52,1) -> 46295 | ... BO52: =EOMONTH(BN52,1) -> 47848
BP53: =1/(1-G53) -> 1
BP54: =1/(1-G54) -> 1
BP55: =1/(1-G55) -> 1
BP56: =1/(1-G56) -> 1
BP57: =1/(1-G57) -> 1
BP58: =1/(1-G58) -> 1
BP59: =1/(1-G59) -> 1
BP60: =1/(1-G60) -> 1
B61: TOTAL GASTOS | H61: =SUM(H53:H60) -> 0 | I61: =SUM(I53:I60) -> 0 | J61: =SUM(J53:J60) -> 0 | K61: =SUM(K53:K60) -> 0 | L61: =SUM(L53:L60) -> 0 | M61: =SUM(M53:M60) -> 0 | N61: =SUM(N53:N60) -> 0 | O61: =SUM(O53:O60) -> 0 | ... BO61: =SUM(BO53:BO60) -> 0
B62: VENTA GASTOS REFACTURABLES | H62: {=SUMPRODUCT(($F$53:$F$60="SI")*1,$BP$53:$BP$60,H53:H60)} -> 0 | I62: {=SUMPRODUCT(($F$53:$F$60="SI")*1,$BP$53:$BP$60,I53:I60)} -> 0 | J62: {=SUMPRODUCT(($F$53:$F$60="SI")*1,$BP$53:$BP$60,J53:J60)} -> 0 | K62: {=SUMPRODUCT(($F$53:$F$60="SI")*1,$BP$53:$BP$60,K53:K60)} -> 0 | L62: {=SUMPRODUCT(($F$53:$F$60="SI")*1,$BP$53:$BP$60,L53:L60)} -> 0 | M62: {=SUMPRODUCT(($F$53:$F$60="SI")*1,$BP$53:$BP$60,M53:M60)} -> 0 | N62: {=SUMPRODUCT(($F$53:$F$60="SI")*1,$BP$53:$BP$60,N53:N60)} -> 0 | O62: {=SUMPRODUCT(($F$53:$F$60="SI")*1,$BP$53:$BP$60,O53:O60)} -> 0 | ... BO62: {=SUMPRODUCT(($F$53:$F$60="SI")*1,$BP$53:$BP$60,BO53:BO60)} -> 0
B64: COMPRAS | D64: COSTE TOTAL COMPRAS BASELINE | F64: ='Cost Overview'!L8 -> 0 | H64: PENDIENTE DE PLANIFICAR | J64: =F64-SUM(F77:BO77) -> 0 | L64: (!) El coste de COMPRAS planificado es mayor que el de la BASELINE
B66: PROVEEDOR | C66: DESCRIPCION COMPRA | D66: PO COMPRA | E66: INFOR ARIBA | F66: REFACTURABLE | G66: MARGEN | H66: ='Project Infor'!C8 -> 46023 | I66: =EOMONTH(H66,1) -> 46081 | J66: =EOMONTH(I66,1) -> 46112 | K66: =EOMONTH(J66,1) -> 46142 | L66: =EOMONTH(K66,1) -> 46173 | M66: =EOMONTH(L66,1) -> 46203 | N66: =EOMONTH(M66,1) -> 46234 | O66: =EOMONTH(N66,1) -> 46265 | P66: =EOMONTH(O66,1) -> 46295 | ... BO66: =EOMONTH(BN66,1) -> 47848
BP67: =1/(1-G67) -> 1
BP68: =1/(1-G68) -> 1
BP69: =1/(1-G69) -> 1
BP70: =1/(1-G70) -> 1
BP71: =1/(1-G71) -> 1
BP72: =1/(1-G72) -> 1
BP73: =1/(1-G73) -> 1
BP74: =1/(1-G74) -> 1
BP75: =1/(1-G75) -> 1
BP76: =1/(1-G76) -> 1
B77: TOTAL COMPRAS | H77: =SUM(H67:H76) -> 0 | I77: =SUM(I67:I76) -> 0 | J77: =SUM(J67:J76) -> 0 | K77: =SUM(K67:K76) -> 0 | L77: =SUM(L67:L76) -> 0 | M77: =SUM(M67:M76) -> 0 | N77: =SUM(N67:N76) -> 0 | O77: =SUM(O67:O76) -> 0 | ... BO77: =SUM(BO67:BO76) -> 0
B78: VENTA COMPRAS REFACTURABLES | H78: {=SUMPRODUCT(($F$67:$F$76="SI")*1,$BP$67:$BP$76,H67:H76)} -> 0 | I78: {=SUMPRODUCT(($F$67:$F$76="SI")*1,$BP$67:$BP$76,I67:I76)} -> 0 | J78: {=SUMPRODUCT(($F$67:$F$76="SI")*1,$BP$67:$BP$76,J67:J76)} -> 0 | K78: {=SUMPRODUCT(($F$67:$F$76="SI")*1,$BP$67:$BP$76,K67:K76)} -> 0 | L78: {=SUMPRODUCT(($F$67:$F$76="SI")*1,$BP$67:$BP$76,L67:L76)} -> 0 | M78: {=SUMPRODUCT(($F$67:$F$76="SI")*1,$BP$67:$BP$76,M67:M76)} -> 0 | N78: {=SUMPRODUCT(($F$67:$F$76="SI")*1,$BP$67:$BP$76,N67:N76)} -> 0 | O78: {=SUMPRODUCT(($F$67:$F$76="SI")*1,$BP$67:$BP$76,O67:O76)} -> 0 | ... BO78: {=SUMPRODUCT(($F$67:$F$76="SI")*1,$BP$67:$BP$76,BO67:BO76)} -> 0
B88: Tipos Gasto
B89: Travelling Expenses
B90: Recruitment Fees
B91: Trainning Costs
B92: Salaries varios (becas,…)
B93: Fees
B94: Otros

Sheet Monthly View
B2: WBS-Element | C2: ='Project Infor'!C10 -> ZEV-ATE0012-1001 | D2: ='Project Infor'!C11 -> Lote 2: Núcleo Estructural Java | I2: (!) La VENTA total planificada excede el PEDIDO | M2: ='Cost Planning'!N5 -> -4604
E4: =IF(E5>EOMONTH(FIN,0),"Fin",IF(E5>FECHA,"Prev","Real")) -> Real | F4: =IF(F5>EOMONTH(FIN,0),"Fin",IF(F5>FECHA,"Prev","Real")) -> Real | G4: =IF(G5>EOMONTH(FIN,0),"Fin",IF(G5>FECHA,"Prev","Real")) -> Real | H4: =IF(H5>EOMONTH(FIN,0),"Fin",IF(H5>FECHA,"Prev","Real")) -> Real | I4: =IF(I5>EOMONTH(FIN,0),"Fin",IF(I5>FECHA,"Prev","Real")) -> Real | J4: =IF(J5>EOMONTH(FIN,0),"Fin",IF(J5>FECHA,"Prev","Real")) -> Real | K4: =IF(K5>EOMONTH(FIN,0),"Fin",IF(K5>FECHA,"Prev","Real")) -> Prev | L4: =IF(L5>EOMONTH(FIN,0),"Fin",IF(L5>FECHA,"Prev","Real")) -> Prev | ... BL4: =IF(BL5>EOMONTH(FIN,0),"Fin",IF(BL5>FECHA,"Prev","Real")) -> Fin
B5: LINEA BASE ACTUAL | D5: INICIAL | E5: 46023 | F5: 46054 | G5: 46082 | H5: 46113 | I5: 46143 | J5: 46174 | K5: 46204 | L5: 46235 | M5: 46266 | N5: 46296 | O5: 46327 | P5: 46357 | Q5: 46388 | R5: 46419 | S5: 46447 | T5: 46478 | U5: 46508 | V5: 46539 | W5: 46569 | X5: 46600 | Y5: 46631 | Z5: 46661 | AA5: 46692 | AB5: 46722 | AC5: 46753 | AD5: 46784 | AE5: 46813 | AF5: 46844 | AG5: 46874 | AH5: 46905 | AI5: 46935 | AJ5: 46966 | AK5: 46997 | AL5: 47027 | AM5: 47058 | AN5: 47088 | AO5: 47119 | AP5: 47150 | AQ5: 47178 | AR5: 47209 | AS5: 47239 | AT5: 47270 | AU5: 47300 | AV5: 47331 | AW5: 47362 | AX5: 47392 | AY5: 47423 | AZ5: 47453 | BA5: =EOMONTH(AZ5,1) -> 47514 | BB5: =EOMONTH(BA5,1) -> 47542 | BC5: =EOMONTH(BB5,1) -> 47573 | BD5: =EOMONTH(BC5,1) -> 47603 | BE5: =EOMONTH(BD5,1) -> 47634 | BF5: =EOMONTH(BE5,1) -> 47664 | BG5: =EOMONTH(BF5,1) -> 47695 | BH5: =EOMONTH(BG5,1) -> 47726 | ... BL5: =EOMONTH(BK5,1) -> 47848
B6: + INGRESOS PREVISTOS | D6: ='Project Infor'!C28 -> 465000 | E6: =D6+SUMIF('Cost Overview'!$T$16:$T$35,(YEAR(E$5)&MONTH(E$5)),'Cost Overview'!$F$16:$F$35) -> 465000 | F6: =E6+SUMIF('Cost Overview'!$T$16:$T$35,(YEAR(F$5)&MONTH(F$5)),'Cost Overview'!$F$16:$F$35) -> 465000 | G6: =F6+SUMIF('Cost Overview'!$T$16:$T$35,(YEAR(G$5)&MONTH(G$5)),'Cost Overview'!$F$16:$F$35) -> 465000 | H6: =G6+SUMIF('Cost Overview'!$T$16:$T$35,(YEAR(H$5)&MONTH(H$5)),'Cost Overview'!$F$16:$F$35) -> 465000 | I6: =H6+SUMIF('Cost Overview'!$T$16:$T$35,(YEAR(I$5)&MONTH(I$5)),'Cost Overview'!$F$16:$F$35) -> 465000 | J6: =I6+SUMIF('Cost Overview'!$T$16:$T$35,(YEAR(J$5)&MONTH(J$5)),'Cost Overview'!$F$16:$F$35) -> 465000 | K6: =J6+SUMIF('Cost Overview'!$T$16:$T$35,(YEAR(K$5)&MONTH(K$5)),'Cost Overview'!$F$16:$F$35) -> 465000 | L6: =K6+SUMIF('Cost Overview'!$T$16:$T$35,(YEAR(L$5)&MONTH(L$5)),'Cost Overview'!$F$16:$F$35) -> 465000 | ... BL6: =BK6+SUMIF('Cost Overview'!$T$16:$T$35,(YEAR(BL$5)&MONTH(BL$5)),'Cost Overview'!$F$16:$F$35) -> 465000
B7: HORAS | D7: ='Project Infor'!C29 -> 14256 | E7: =D7+SUMIF('Cost Overview'!$T$16:$T$35,(YEAR(E$5)&MONTH(E$5)),'Cost Overview'!$H$16:$H$35) -> 14256 | F7: =E7+SUMIF('Cost Overview'!$T$16:$T$35,(YEAR(F$5)&MONTH(F$5)),'Cost Overview'!$H$16:$H$35) -> 14256 | G7: =F7+SUMIF('Cost Overview'!$T$16:$T$35,(YEAR(G$5)&MONTH(G$5)),'Cost Overview'!$H$16:$H$35) -> 14256 | H7: =G7+SUMIF('Cost Overview'!$T$16:$T$35,(YEAR(H$5)&MONTH(H$5)),'Cost Overview'!$H$16:$H$35) -> 14256 | I7: =H7+SUMIF('Cost Overview'!$T$16:$T$35,(YEAR(I$5)&MONTH(I$5)),'Cost Overview'!$H$16:$H$35) -> 14256 | J7: =I7+SUMIF('Cost Overview'!$T$16:$T$35,(YEAR(J$5)&MONTH(J$5)),'Cost Overview'!$H$16:$H$35) -> 14256 | K7: =J7+SUMIF('Cost Overview'!$T$16:$T$35,(YEAR(K$5)&MONTH(K$5)),'Cost Overview'!$H$16:$H$35) -> 14256 | L7: =K7+SUMIF('Cost Overview'!$T$16:$T$35,(YEAR(L$5)&MONTH(L$5)),'Cost Overview'!$H$16:$H$35) -> 14256 | ... BL7: =BK7+SUMIF('Cost Overview'!$T$16:$T$35,(YEAR(BL$5)&MONTH(BL$5)),'Cost Overview'!$H$16:$H$35) -> 14256
B8: - COSTE RECURSOS | D8: ='Project Infor'!C30 -> 356584.84 | E8: =D8+SUMIF('Cost Overview'!$T$16:$T$35,(YEAR(E$5)&MONTH(E$5)),'Cost Overview'!$G$16:$G$35) -> 356584.84 | F8: =E8+SUMIF('Cost Overview'!$T$16:$T$35,(YEAR(F$5)&MONTH(F$5)),'Cost Overview'!$G$16:$G$35) -> 356584.84 | G8: =F8+SUMIF('Cost Overview'!$T$16:$T$35,(YEAR(G$5)&MONTH(G$5)),'Cost Overview'!$G$16:$G$35) -> 356584.84 | H8: =G8+SUMIF('Cost Overview'!$T$16:$T$35,(YEAR(H$5)&MONTH(H$5)),'Cost Overview'!$G$16:$G$35) -> 356584.84 | I8: =H8+SUMIF('Cost Overview'!$T$16:$T$35,(YEAR(I$5)&MONTH(I$5)),'Cost Overview'!$G$16:$G$35) -> 356584.84 | J8: =I8+SUMIF('Cost Overview'!$T$16:$T$35,(YEAR(J$5)&MONTH(J$5)),'Cost Overview'!$G$16:$G$35) -> 356584.84 | K8: =J8+SUMIF('Cost Overview'!$T$16:$T$35,(YEAR(K$5)&MONTH(K$5)),'Cost Overview'!$G$16:$G$35) -> 356584.84 | L8: =K8+SUMIF('Cost Overview'!$T$16:$T$35,(YEAR(L$5)&MONTH(L$5)),'Cost Overview'!$G$16:$G$35) -> 356584.84 | ... BL8: =BK8+SUMIF('Cost Overview'!$T$16:$T$35,(YEAR(BL$5)&MONTH(BL$5)),'Cost Overview'!$G$16:$G$35) -> 356584.84
B9: - RIESGOS | D9: ='Project Infor'!C31 -> 3565.85 | E9: =D9+SUMIF('Cost Overview'!$T$16:$T$35,(YEAR(E$5)&MONTH(E$5)),'Cost Overview'!$I$16:$I$35) -> 3565.85 | F9: =E9+SUMIF('Cost Overview'!$T$16:$T$35,(YEAR(F$5)&MONTH(F$5)),'Cost Overview'!$I$16:$I$35) -> 3565.85 | G9: =F9+SUMIF('Cost Overview'!$T$16:$T$35,(YEAR(G$5)&MONTH(G$5)),'Cost Overview'!$I$16:$I$35) -> 3565.85 | H9: =G9+SUMIF('Cost Overview'!$T$16:$T$35,(YEAR(H$5)&MONTH(H$5)),'Cost Overview'!$I$16:$I$35) -> 3565.85 | I9: =H9+SUMIF('Cost Overview'!$T$16:$T$35,(YEAR(I$5)&MONTH(I$5)),'Cost Overview'!$I$16:$I$35) -> 3565.85 | J9: =I9+SUMIF('Cost Overview'!$T$16:$T$35,(YEAR(J$5)&MONTH(J$5)),'Cost Overview'!$I$16:$I$35) -> 3565.85 | K9: =J9+SUMIF('Cost Overview'!$T$16:$T$35,(YEAR(K$5)&MONTH(K$5)),'Cost Overview'!$I$16:$I$35) -> 3565.85 | L9: =K9+SUMIF('Cost Overview'!$T$16:$T$35,(YEAR(L$5)&MONTH(L$5)),'Cost Overview'!$I$16:$I$35) -> 3565.85 | ... BL9: =BK9+SUMIF('Cost Overview'!$T$16:$T$35,(YEAR(BL$5)&MONTH(BL$5)),'Cost Overview'!$I$16:$I$35) -> 3565.85
B10: - GARANTIA | D10: ='Project Infor'!C32 -> 0 | E10: =D10+SUMIF('Cost Overview'!$T$16:$T$35,(YEAR(E$5)&MONTH(E$5)),'Cost Overview'!$J$16:$J$35) -> 0 | F10: =E10+SUMIF('Cost Overview'!$T$16:$T$35,(YEAR(F$5)&MONTH(F$5)),'Cost Overview'!$J$16:$J$35) -> 0 | G10: =F10+SUMIF('Cost Overview'!$T$16:$T$35,(YEAR(G$5)&MONTH(G$5)),'Cost Overview'!$J$16:$J$35) -> 0 | H10: =G10+SUMIF('Cost Overview'!$T$16:$T$35,(YEAR(H$5)&MONTH(H$5)),'Cost Overview'!$J$16:$J$35) -> 0 | I10: =H10+SUMIF('Cost Overview'!$T$16:$T$35,(YEAR(I$5)&MONTH(I$5)),'Cost Overview'!$J$16:$J$35) -> 0 | J10: =I10+SUMIF('Cost Overview'!$T$16:$T$35,(YEAR(J$5)&MONTH(J$5)),'Cost Overview'!$J$16:$J$35) -> 0 | K10: =J10+SUMIF('Cost Overview'!$T$16:$T$35,(YEAR(K$5)&MONTH(K$5)),'Cost Overview'!$J$16:$J$35) -> 0 | L10: =K10+SUMIF('Cost Overview'!$T$16:$T$35,(YEAR(L$5)&MONTH(L$5)),'Cost Overview'!$J$16:$J$35) -> 0 | ... BL10: =BK10+SUMIF('Cost Overview'!$T$16:$T$35,(YEAR(BL$5)&MONTH(BL$5)),'Cost Overview'!$J$16:$J$35) -> 0
B11: - GASTOS | D11: ='Project Infor'!C33 -> 0 | E11: =D11+SUMIF('Cost Overview'!$T$16:$T$35,(YEAR(E$5)&MONTH(E$5)),'Cost Overview'!$K$16:$K$35) -> 0 | F11: =E11+SUMIF('Cost Overview'!$T$16:$T$35,(YEAR(F$5)&MONTH(F$5)),'Cost Overview'!$K$16:$K$35) -> 0 | G11: =F11+SUMIF('Cost Overview'!$T$16:$T$35,(YEAR(G$5)&MONTH(G$5)),'Cost Overview'!$K$16:$K$35) -> 0 | H11: =G11+SUMIF('Cost Overview'!$T$16:$T$35,(YEAR(H$5)&MONTH(H$5)),'Cost Overview'!$K$16:$K$35) -> 0 | I11: =H11+SUMIF('Cost Overview'!$T$16:$T$35,(YEAR(I$5)&MONTH(I$5)),'Cost Overview'!$K$16:$K$35) -> 0 | J11: =I11+SUMIF('Cost Overview'!$T$16:$T$35,(YEAR(J$5)&MONTH(J$5)),'Cost Overview'!$K$16:$K$35) -> 0 | K11: =J11+SUMIF('Cost Overview'!$T$16:$T$35,(YEAR(K$5)&MONTH(K$5)),'Cost Overview'!$K$16:$K$35) -> 0 | L11: =K11+SUMIF('Cost Overview'!$T$16:$T$35,(YEAR(L$5)&MONTH(L$5)),'Cost Overview'!$K$16:$K$35) -> 0 | ... BL11: =BK11+SUMIF('Cost Overview'!$T$16:$T$35,(YEAR(BL$5)&MONTH(BL$5)),'Cost Overview'!$K$16:$K$35) -> 0
B12: - COMPRAS | D12: ='Project Infor'!C34 -> 0 | E12: =D12+SUMIF('Cost Overview'!$T$16:$T$35,(YEAR(E$5)&MONTH(E$5)),'Cost Overview'!$L$16:$L$35) -> 0 | F12: =E12+SUMIF('Cost Overview'!$T$16:$T$35,(YEAR(F$5)&MONTH(F$5)),'Cost Overview'!$L$16:$L$35) -> 0 | G12: =F12+SUMIF('Cost Overview'!$T$16:$T$35,(YEAR(G$5)&MONTH(G$5)),'Cost Overview'!$L$16:$L$35) -> 0 | H12: =G12+SUMIF('Cost Overview'!$T$16:$T$35,(YEAR(H$5)&MONTH(H$5)),'Cost Overview'!$L$16:$L$35) -> 0 | I12: =H12+SUMIF('Cost Overview'!$T$16:$T$35,(YEAR(I$5)&MONTH(I$5)),'Cost Overview'!$L$16:$L$35) -> 0 | J12: =I12+SUMIF('Cost Overview'!$T$16:$T$35,(YEAR(J$5)&MONTH(J$5)),'Cost Overview'!$L$16:$L$35) -> 0 | K12: =J12+SUMIF('Cost Overview'!$T$16:$T$35,(YEAR(K$5)&MONTH(K$5)),'Cost Overview'!$L$16:$L$35) -> 0 | L12: =K12+SUMIF('Cost Overview'!$T$16:$T$35,(YEAR(L$5)&MONTH(L$5)),'Cost Overview'!$L$16:$L$35) -> 0 | ... BL12: =BK12+SUMIF('Cost Overview'!$T$16:$T$35,(YEAR(BL$5)&MONTH(BL$5)),'Cost Overview'!$L$16:$L$35) -> 0
B13: COSTE DIRECTO | D13: =SUM(D8:D12) -> 360150.69 | E13: =SUM(E8:E12) -> 360150.69 | F13: =SUM(F8:F12) -> 360150.69 | G13: =SUM(G8:G12) -> 360150.69 | H13: =SUM(H8:H12) -> 360150.69 | I13: =SUM(I8:I12) -> 360150.69 | J13: =SUM(J8:J12) -> 360150.69 | K13: =SUM(K8:K12) -> 360150.69 | ... BL13: =SUM(BL8:BL12) -> 360150.69
B14: MARGEN DIRECTO (euros) | D14: =D6-D13 -> 104849.31 | E14: =E6-E13 -> 104849.31 | F14: =F6-F13 -> 104849.31 | G14: =G6-G13 -> 104849.31 | H14: =H6-H13 -> 104849.31 | I14: =I6-I13 -> 104849.31 | J14: =J6-J13 -> 104849.31 | K14: =K6-K13 -> 104849.31 | ... BL14: =BL6-BL13 -> 104849.31
B15: MARGEN DIRECTO (%) | D15: =IF(D6=0,0,(D6-D13)/D6) -> 0.22548239 | E15: =IF(E6=0,0,(E6-E13)/E6) -> 0.22548239 | F15: =IF(F6=0,0,(F6-F13)/F6) -> 0.22548239 | G15: =IF(G6=0,0,(G6-G13)/G6) -> 0.22548239 | H15: =IF(H6=0,0,(H6-H13)/H6) -> 0.22548239 | I15: =IF(I6=0,0,(I6-I13)/I6) -> 0.22548239 | J15: =IF(J6=0,0,(J6-J13)/J6) -> 0.22548239 | K15: =IF(K6=0,0,(K6-K13)/K6) -> 0.22548239 | ... BL15: =IF(BL6=0,0,(BL6-BL13)/BL6) -> 0.22548239
B17: REALIZADO + PREVISTO MES | E17: ='Project Infor'!C8 -> 46023 | F17: =EOMONTH(E17,1) -> 46081 | G17: =EOMONTH(F17,1) -> 46112 | H17: =EOMONTH(G17,1) -> 46142 | I17: =EOMONTH(H17,1) -> 46173 | J17: =EOMONTH(I17,1) -> 46203 | K17: =EOMONTH(J17,1) -> 46234 | L17: =EOMONTH(K17,1) -> 46265 | M17: =EOMONTH(L17,1) -> 46295 | ... BL17: =EOMONTH(BK17,1) -> 47848
B18: VENTA | E18: ='Cost Planning'!H44+'Cost Planning'!H62+'Cost Planning'!H78 -> 9591.5833 | F18: ='Cost Planning'!I44+'Cost Planning'!I62+'Cost Planning'!I78 -> 9591.5833 | G18: ='Cost Planning'!J44+'Cost Planning'!J62+'Cost Planning'!J78 -> 9591.5833 | H18: ='Cost Planning'!K44+'Cost Planning'!K62+'Cost Planning'!K78 -> 9591.5833 | I18: ='Cost Planning'!L44+'Cost Planning'!L62+'Cost Planning'!L78 -> 9591.5833 | J18: ='Cost Planning'!M44+'Cost Planning'!M62+'Cost Planning'!M78 -> 9591.5833 | K18: ='Cost Planning'!N44+'Cost Planning'!N62+'Cost Planning'!N78 -> 9591.5833 | L18: ='Cost Planning'!O44+'Cost Planning'!O62+'Cost Planning'!O78 -> 9591.5833 | ... BL18: ='Cost Planning'!BO44+'Cost Planning'!BO62+'Cost Planning'!BO78 -> 0
B19: HORAS | E19: =E31-D31 -> 297 | F19: =F31-E31 -> 297 | G19: =G31-F31 -> 297 | H19: =H31-G31 -> 297 | I19: =I31-H31 -> 297 | J19: =J31-I31 -> 297 | K19: =K31-J31 -> 297 | L19: =L31-K31 -> 297 | ... BL19: =BL31-BK31 -> 0
B20: - COSTE RECURSOS | E20: =E32-D32 -> 7102.785 | F20: =F32-E32 -> 7102.785 | G20: =G32-F32 -> 7102.785 | H20: =H32-G32 -> 7102.785 | I20: =I32-H32 -> 7102.785 | J20: =J32-I32 -> 7102.785 | K20: =K32-J32 -> 7102.785 | L20: =L32-K32 -> 7102.785 | ... BL20: =BL32-BK32 -> 0
B21: - RIESGOS | E21: =E33-D33 -> 0 | F21: =F33-E33 -> 0 | G21: =G33-F33 -> 0 | H21: =H33-G33 -> 0 | I21: =I33-H33 -> 0 | J21: =J33-I33 -> 0 | K21: =K33-J33 -> 0 | L21: =L33-K33 -> 0 | ... BL21: =BL33-BK33 -> 0
B22: - GARANTIA | E22: =E34-D34 -> 0 | F22: =F34-E34 -> 0 | G22: =G34-F34 -> 0 | H22: =H34-G34 -> 0 | I22: =I34-H34 -> 0 | J22: =J34-I34 -> 0 | K22: =K34-J34 -> 0 | L22: =L34-K34 -> 0 | ... BL22: =BL34-BK34 -> 0
B23: - GASTOS | E23: =E35-D35 -> 0 | F23: =F35-E35 -> 0 | G23: =G35-F35 -> 0 | H23: =H35-G35 -> 0 | I23: =I35-H35 -> 0 | J23: =J35-I35 -> 0 | K23: =K35-J35 -> 0 | L23: =L35-K35 -> 0 | ... BL23: =BL35-BK35 -> 0
B24: - COMPRAS | E24: =E36-D36 -> 0 | F24: =F36-E36 -> 0 | G24: =G36-F36 -> 0 | H24: =H36-G36 -> 0 | I24: =I36-H36 -> 0 | J24: =J36-I36 -> 0 | K24: =K36-J36 -> 0 | L24: =L36-K36 -> 0 | ... BL24: =BL36-BK36 -> 0
B25: COSTE DIRECTO | E25: =SUM(E20:E24) -> 7102.785 | F25: =SUM(F20:F24) -> 7102.785 | G25: =SUM(G20:G24) -> 7102.785 | H25: =SUM(H20:H24) -> 7102.785 | I25: =SUM(I20:I24) -> 7102.785 | J25: =SUM(J20:J24) -> 7102.785 | K25: =SUM(K20:K24) -> 7102.785 | L25: =SUM(L20:L24) -> 7102.785 | ... BL25: =SUM(BL20:BL24) -> 0
B26: MARGEN DIRECTO (euros) | E26: =E18-E25 -> 2488.7983 | F26: =F18-F25 -> 2488.7983 | G26: =G18-G25 -> 2488.7983 | H26: =H18-H25 -> 2488.7983 | I26: =I18-I25 -> 2488.7983 | J26: =J18-J25 -> 2488.7983 | K26: =K18-K25 -> 2488.7983 | L26: =L18-L25 -> 2488.7983 | ... BL26: =BL18-BL25 -> 0
B27: MARGEN DIRECTO (%) | E27: =IF(E18=0,0,(E18-SUM(E20,E21,E22,E23,E24))/E18) -> 0.25947732 | F27: =IF(F18=0,0,(F18-SUM(F20,F21,F22,F23,F24))/F18) -> 0.25947732 | G27: =IF(G18=0,0,(G18-SUM(G20,G21,G22,G23,G24))/G18) -> 0.25947732 | H27: =IF(H18=0,0,(H18-SUM(H20,H21,H22,H23,H24))/H18) -> 0.25947732 | I27: =IF(I18=0,0,(I18-SUM(I20,I21,I22,I23,I24))/I18) -> 0.25947732 | J27: =IF(J18=0,0,(J18-SUM(J20,J21,J22,J23,J24))/J18) -> 0.25947732 | K27: =IF(K18=0,0,(K18-SUM(K20,K21,K22,K23,K24))/K18) -> 0.25947732 | L27: =IF(L18=0,0,(L18-SUM(L20,L21,L22,L23,L24))/L18) -> 0.25947732 | ... BL27: =IF(BL18=0,0,(BL18-SUM(BL20,BL21,BL22,BL23,BL24))/BL18) -> 0
B29: REALIZADO + PREVISTO ACUMULADO | D29: ANTERIOR | E29: ='Project Infor'!C8 -> 46023 | F29: =EOMONTH(E29,1) -> 46081 | G29: =EOMONTH(F29,1) -> 46112 | H29: =EOMONTH(G29,1) -> 46142 | I29: =EOMONTH(H29,1) -> 46173 | J29: =EOMONTH(I29,1) -> 46203 | K29: =EOMONTH(J29,1) -> 46234 | L29: =EOMONTH(K29,1) -> 46265 | M29: =EOMONTH(L29,1) -> 46295 | ... BL29: =EOMONTH(BK29,1) -> 47848
B30: VENTA ACUMULADA | D30: ='Project Infor'!C45 -> 0 | E30: =IF(E40,E40,D30+E18) -> 9591.5833 | F30: =IF(F40,F40,E30+F18) -> 19183.167 | G30: =IF(G40,G40,F30+G18) -> 28774.75 | H30: =IF(H40,H40,G30+H18) -> 38366.333 | I30: =IF(I40,I40,H30+I18) -> 47957.917 | J30: =IF(J40,J40,I30+J18) -> 57549.5 | K30: =IF(K40,K40,J30+K18) -> 67141.083 | L30: =IF(L40,L40,K30+L18) -> 76732.667 | ... BL30: =IF(BL40,BL40,BK30+BL18) -> 465000
B31: HORAS | D31: ='Project Infor'!C46 -> 0 | E31: =D31+LOOKUP(E$5,'Cost Planning'!$H$8:$BO$8,'Cost Planning'!$H$9:$BO$9) -> 297 | F31: =E31+LOOKUP(F$5,'Cost Planning'!$H$8:$BO$8,'Cost Planning'!$H$9:$BO$9) -> 594 | G31: =F31+LOOKUP(G$5,'Cost Planning'!$H$8:$BO$8,'Cost Planning'!$H$9:$BO$9) -> 891 | H31: =G31+LOOKUP(H$5,'Cost Planning'!$H$8:$BO$8,'Cost Planning'!$H$9:$BO$9) -> 1188 | I31: =H31+LOOKUP(I$5,'Cost Planning'!$H$8:$BO$8,'Cost Planning'!$H$9:$BO$9) -> 1485 | J31: =I31+LOOKUP(J$5,'Cost Planning'!$H$8:$BO$8,'Cost Planning'!$H$9:$BO$9) -> 1782 | K31: =J31+LOOKUP(K$5,'Cost Planning'!$H$8:$BO$8,'Cost Planning'!$H$9:$BO$9) -> 2079 | L31: =K31+LOOKUP(L$5,'Cost Planning'!$H$8:$BO$8,'Cost Planning'!$H$9:$BO$9) -> 2376 | ... BL31: =BK31+LOOKUP(BL$5,'Cost Planning'!$H$8:$BO$8,'Cost Planning'!$H$9:$BO$9) -> 14256
B32: - COSTE RECURSOS ACUMULADO | D32: ='Project Infor'!C47 -> 0 | E32: =D32+LOOKUP(E$5,'Cost Planning'!$H$8:$BO$8,'Cost Planning'!$H$40:$BO$40)+LOOKUP(E$5,'Cost Planning'!$H$8:$BO$8,'Cost Planning'!$H$41:$BO$41) -> 7102.785 | F32: =E32+LOOKUP(F$5,'Cost Planning'!$H$8:$BO$8,'Cost Planning'!$H$40:$BO$40)+LOOKUP(F$5,'Cost Planning'!$H$8:$BO$8,'Cost Planning'!$H$41:$BO$41) -> 14205.57 | G32: =F32+LOOKUP(G$5,'Cost Planning'!$H$8:$BO$8,'Cost Planning'!$H$40:$BO$40)+LOOKUP(G$5,'Cost Planning'!$H$8:$BO$8,'Cost Planning'!$H$41:$BO$41) -> 21308.355 | H32: =G32+LOOKUP(H$5,'Cost Planning'!$H$8:$BO$8,'Cost Planning'!$H$40:$BO$40)+LOOKUP(H$5,'Cost Planning'!$H$8:$BO$8,'Cost Planning'!$H$41:$BO$41) -> 28411.14 | I32: =H32+LOOKUP(I$5,'Cost Planning'!$H$8:$BO$8,'Cost Planning'!$H$40:$BO$40)+LOOKUP(I$5,'Cost Planning'!$H$8:$BO$8,'Cost Planning'!$H$41:$BO$41) -> 35513.925 | J32: =I32+LOOKUP(J$5,'Cost Planning'!$H$8:$BO$8,'Cost Planning'!$H$40:$BO$40)+LOOKUP(J$5,'Cost Planning'!$H$8:$BO$8,'Cost Planning'!$H$41:$BO$41) -> 42616.71 | K32: =J32+LOOKUP(K$5,'Cost Planning'!$H$8:$BO$8,'Cost Planning'!$H$40:$BO$40)+LOOKUP(K$5,'Cost Planning'!$H$8:$BO$8,'Cost Planning'!$H$41:$BO$41) -> 49719.495 | L32: =K32+LOOKUP(L$5,'Cost Planning'!$H$8:$BO$8,'Cost Planning'!$H$40:$BO$40)+LOOKUP(L$5,'Cost Planning'!$H$8:$BO$8,'Cost Planning'!$H$41:$BO$41) -> 56822.28 | ... BL32: =BK32+LOOKUP(BL$5,'Cost Planning'!$H$8:$BO$8,'Cost Planning'!$H$40:$BO$40)+LOOKUP(BL$5,'Cost Planning'!$H$8:$BO$8,'Cost Planning'!$H$41:$BO$41) -> 340933.68
B33: - RIESGOS | E33: =D33+LOOKUP(E$5,'Cost Planning'!$H$8:$BO$8,'Cost Planning'!$H$47:$BO$47) -> 0 | F33: =E33+LOOKUP(F$5,'Cost Planning'!$H$8:$BO$8,'Cost Planning'!$H$47:$BO$47) -> 0 | G33: =F33+LOOKUP(G$5,'Cost Planning'!$H$8:$BO$8,'Cost Planning'!$H$47:$BO$47) -> 0 | H33: =G33+LOOKUP(H$5,'Cost Planning'!$H$8:$BO$8,'Cost Planning'!$H$47:$BO$47) -> 0 | I33: =H33+LOOKUP(I$5,'Cost Planning'!$H$8:$BO$8,'Cost Planning'!$H$47:$BO$47) -> 0 | J33: =I33+LOOKUP(J$5,'Cost Planning'!$H$8:$BO$8,'Cost Planning'!$H$47:$BO$47) -> 0 | K33: =J33+LOOKUP(K$5,'Cost Planning'!$H$8:$BO$8,'Cost Planning'!$H$47:$BO$47) -> 0 | L33: =K33+LOOKUP(L$5,'Cost Planning'!$H$8:$BO$8,'Cost Planning'!$H$47:$BO$47) -> 0 | ... BL33: =BK33+LOOKUP(BL$5,'Cost Planning'!$H$8:$BO$8,'Cost Planning'!$H$47:$BO$47) -> 3565.85
B34: - GARANTIA | E34: =D34+LOOKUP(E$5,'Cost Planning'!$H$8:$BO$8,'Cost Planning'!$H$48:$BO$48) -> 0 | F34: =E34+LOOKUP(F$5,'Cost Planning'!$H$8:$BO$8,'Cost Planning'!$H$48:$BO$48) -> 0 | G34: =F34+LOOKUP(G$5,'Cost Planning'!$H$8:$BO$8,'Cost Planning'!$H$48:$BO$48) -> 0 | H34: =G34+LOOKUP(H$5,'Cost Planning'!$H$8:$BO$8,'Cost Planning'!$H$48:$BO$48) -> 0 | I34: =H34+LOOKUP(I$5,'Cost Planning'!$H$8:$BO$8,'Cost Planning'!$H$48:$BO$48) -> 0 | J34: =I34+LOOKUP(J$5,'Cost Planning'!$H$8:$BO$8,'Cost Planning'!$H$48:$BO$48) -> 0 | K34: =J34+LOOKUP(K$5,'Cost Planning'!$H$8:$BO$8,'Cost Planning'!$H$48:$BO$48) -> 0 | L34: =K34+LOOKUP(L$5,'Cost Planning'!$H$8:$BO$8,'Cost Planning'!$H$48:$BO$48) -> 0 | ... BL34: =BK34+LOOKUP(BL$5,'Cost Planning'!$H$8:$BO$8,'Cost Planning'!$H$48:$BO$48) -> 0
B35: - GASTOS | D35: ='Project Infor'!C48 -> 0 | E35: =D35+LOOKUP(E$5,'Cost Planning'!$H$8:$BO$8,'Cost Planning'!$H$61:$BO$61) -> 0 | F35: =E35+LOOKUP(F$5,'Cost Planning'!$H$8:$BO$8,'Cost Planning'!$H$61:$BO$61) -> 0 | G35: =F35+LOOKUP(G$5,'Cost Planning'!$H$8:$BO$8,'Cost Planning'!$H$61:$BO$61) -> 0 | H35: =G35+LOOKUP(H$5,'Cost Planning'!$H$8:$BO$8,'Cost Planning'!$H$61:$BO$61) -> 0 | I35: =H35+LOOKUP(I$5,'Cost Planning'!$H$8:$BO$8,'Cost Planning'!$H$61:$BO$61) -> 0 | J35: =I35+LOOKUP(J$5,'Cost Planning'!$H$8:$BO$8,'Cost Planning'!$H$61:$BO$61) -> 0 | K35: =J35+LOOKUP(K$5,'Cost Planning'!$H$8:$BO$8,'Cost Planning'!$H$61:$BO$61) -> 0 | L35: =K35+LOOKUP(L$5,'Cost Planning'!$H$8:$BO$8,'Cost Planning'!$H$61:$BO$61) -> 0 | ... BL35: =BK35+LOOKUP(BL$5,'Cost Planning'!$H$8:$BO$8,'Cost Planning'!$H$61:$BO$61) -> 0
B36: - COMPRAS | D36: ='Project Infor'!C49 -> 0 | E36: =D36+LOOKUP(E$5,'Cost Planning'!$H$8:$BO$8,'Cost Planning'!$H$77:$BO$77) -> 0 | F36: =E36+LOOKUP(F$5,'Cost Planning'!$H$8:$BO$8,'Cost Planning'!$H$77:$BO$77) -> 0 | G36: =F36+LOOKUP(G$5,'Cost Planning'!$H$8:$BO$8,'Cost Planning'!$H$77:$BO$77) -> 0 | H36: =G36+LOOKUP(H$5,'Cost Planning'!$H$8:$BO$8,'Cost Planning'!$H$77:$BO$77) -> 0 | I36: =H36+LOOKUP(I$5,'Cost Planning'!$H$8:$BO$8,'Cost Planning'!$H$77:$BO$77) -> 0 | J36: =I36+LOOKUP(J$5,'Cost Planning'!$H$8:$BO$8,'Cost Planning'!$H$77:$BO$77) -> 0 | K36: =J36+LOOKUP(K$5,'Cost Planning'!$H$8:$BO$8,'Cost Planning'!$H$77:$BO$77) -> 0 | L36: =K36+LOOKUP(L$5,'Cost Planning'!$H$8:$BO$8,'Cost Planning'!$H$77:$BO$77) -> 0 | ... BL36: =BK36+LOOKUP(BL$5,'Cost Planning'!$H$8:$BO$8,'Cost Planning'!$H$77:$BO$77) -> 0
B37: COSTE DIRECTO | D37: =SUM(D32:D36) -> 0 | E37: =SUM(E32:E36) -> 7102.785 | F37: =SUM(F32:F36) -> 14205.57 | G37: =SUM(G32:G36) -> 21308.355 | H37: =SUM(H32:H36) -> 28411.14 | I37: =SUM(I32:I36) -> 35513.925 | J37: =SUM(J32:J36) -> 42616.71 | K37: =SUM(K32:K36) -> 49719.495 | ... BL37: =SUM(BL32:BL36) -> 344499.53
B38: MARGEN DIRECTO ACUMULADO (euros) | D38: =D30-D32-D33-D34-D35-D36 -> 0 | E38: =E30-E32-E33-E34-E35-E36 -> 2488.7983 | F38: =F30-F32-F33-F34-F35-F36 -> 4977.5967 | G38: =G30-G32-G33-G34-G35-G36 -> 7466.395 | H38: =H30-H32-H33-H34-H35-H36 -> 9955.1933 | I38: =I30-I32-I33-I34-I35-I36 -> 12443.992 | J38: =J30-J32-J33-J34-J35-J36 -> 14932.79 | K38: =K30-K32-K33-K34-K35-K36 -> 17421.588 | ... BL38: =BL30-BL32-BL33-BL34-BL35-BL36 -> 120500.47
B40: VENTA ACUMULADA REPORTADA SAP | E40: =IF(OFFSET(E4,0,1)="Fin",E6) -> FALSE | F40: =IF(OFFSET(F4,0,1)="Fin",F6) -> FALSE | G40: =IF(OFFSET(G4,0,1)="Fin",G6) -> FALSE | H40: =IF(OFFSET(H4,0,1)="Fin",H6) -> FALSE | I40: =IF(OFFSET(I4,0,1)="Fin",I6) -> FALSE | J40: =IF(OFFSET(J4,0,1)="Fin",J6) -> FALSE | K40: =IF(OFFSET(K4,0,1)="Fin",K6) -> FALSE | L40: =IF(OFFSET(L4,0,1)="Fin",L6) -> FALSE | ... BL40: =IF(OFFSET(BL4,0,1)="Fin",BL6) -> FALSE
B42: FACTURACION EMITIDA/PLANIFICADA | D42: ='Project Infor'!C54 -> 0
B43: FACTURACION ACUMULADA | D43: =D42 -> 0 | E43: =E42+D43 -> 0 | F43: =F42+E43 -> 0 | G43: =G42+F43 -> 0 | H43: =H42+G43 -> 0 | I43: =I42+H43 -> 0 | J43: =J42+I43 -> 0 | K43: =K42+J43 -> 0 | L43: =L42+K43 -> 0 | ... BL43: =BL42+BK43 -> 0
B44: FACTURACION vs VENTA | E44: =E43-E30 -> -9591.5833 | F44: =F43-F30 -> -19183.167 | G44: =G43-G30 -> -28774.75 | H44: =H43-H30 -> -38366.333 | I44: =I43-I30 -> -47957.917 | J44: =J43-J30 -> -57549.5 | K44: =K43-K30 -> -67141.083 | L44: =L43-L30 -> -76732.667 | ... BL44: =BL43-BL30 -> -465000

Sheet Cost Summary
B2: WBS-Element | C2: ='Project Infor'!C10 -> ZEV-ATE0012-1001 | D2: ='Project Infor'!C11 -> Lote 2: Núcleo Estructural Java
D5: PEDIDO IMPORTE NETO | E5: COSTE RECURSOS | F5: HORAS | G5: RIESGOS | H5: GARANTÍA | I5: GASTOS | J5: COMPRAS | K5: COSTE DIRECTO | L5: MARGEN DIRECTO (euros) | M5: MARGEN DIRECTO (%) | N5: MARGEN BRUTO
B6: LINEA BASE INICIAL | D6: ='Cost Overview'!F12 -> 465000 | E6: ='Cost Overview'!G12 -> 356584.84 | F6: ='Cost Overview'!H12 -> 14256 | G6: ='Cost Overview'!I12 -> 3565.85 | H6: ='Cost Overview'!J12 -> 0 | I6: ='Cost Overview'!K12 -> 0 | J6: ='Cost Overview'!L12 -> 0 | K6: =SUM(E6,G6,H6,I6,J6) -> 360150.69 | L6: =D6-K6 -> 104849.31 | M6: =IF(D6=0,0,(D6-E6-H6-I6-G6-J6)/D6) -> 0.22548239 | N6: =IF(D6=0,0,(D6-E6/UTILIZACION-G6/UTILIZACION-H6/UTILIZACION-I6-J6)/D6) -> 0.16718536
B7: LINEA BASE ACTUAL | D7: ='Cost Overview'!F8 -> 465000 | E7: ='Cost Overview'!G8 -> 356584.84 | F7: ='Cost Overview'!H8 -> 14256 | G7: ='Cost Overview'!I8 -> 3565.85 | H7: ='Cost Overview'!J8 -> 0 | I7: ='Cost Overview'!K8 -> 0 | J7: ='Cost Overview'!L8 -> 0 | K7: =SUM(E7,G7,H7,I7,J7) -> 360150.69 | L7: =D7-K7 -> 104849.31 | M7: =IF(D7=0,0,(D7-E7-H7-I7-G7-J7)/D7) -> 0.22548239 | N7: =IF(D7=0,0,(D7-E7/UTILIZACION-G7/UTILIZACION-H7/UTILIZACION-I7-J7)/D7) -> 0.16718536
B8: PROYECCIÓN PROYECTO (REAL + ESTIMADO) | D8: =D7 -> 465000 | E8: =SUM('Cost Planning'!F40:BO41) -> 340933.68 | F8: =SUM('Cost Planning'!F9:BO9) -> 14256 | G8: =SUM('Cost Planning'!H47:BO47) -> 3565.85 | H8: =SUM('Cost Planning'!H48:BO48) -> 0 | I8: =SUM('Cost Planning'!F61:BO61) -> 0 | J8: =SUM('Cost Planning'!F77:BO77) -> 0 | K8: =SUM(E8,G8,H8,I8,J8) -> 344499.53 | L8: =D8-K8 -> 120500.47 | M8: =IF(D8=0,0,(D8-E8-H8-I8-G8-J8)/D8) -> 0.2591408 | N8: =IF(D8=0,0,(D8-E8/UTILIZACION-G8/UTILIZACION-H8/UTILIZACION-I8-J8)/D8) -> 0.2033772
B9: Diferencia de PROYECCION DEL PROYECTO con BASELINE ACTUAL | D9: =IF(D8=0,1,(D8-D7)/D8) -> 0 | E9: =IF(E8=0,1,(E8-E7)/E8) -> -0.045906758 | F9: =IF(F8=0,1,(F8-F7)/F8) -> 0 | G9: =IF(G8=0,1,(G8-G7)/G8) -> 0 | H9: =IF(H8=0,1,(H8-H7)/H8) -> 1 | I9: =IF(I8=0,1,(I8-I7)/I8) -> 1 | J9: =IF(J8=0,1,(J8-J7)/J8) -> 1 | K9: =IF(K8=0,1,(K8-K7)/K8) -> -0.045431586 | L9: =IF(L8=0,1,(L8-L7)/L8) -> 0.12988464 | M9: =M8-M7 -> 0.033658409
B11: REALIZADO | D11: =SUMIF('Monthly View'!$E$4:$BL$4,"Real",'Monthly View'!$E$18:$BL$18)+'Project Infor'!C45 -> 57549.5 | E11: =SUMIF('Monthly View'!$E$4:$BL$4,"Real",'Monthly View'!$E$20:$BL$20)+'Project Infor'!C47 -> 42616.71 | F11: =SUMIF('Monthly View'!$E$4:$BL$4,"Real",'Monthly View'!$E$19:$BL$19)+'Project Infor'!C46 -> 1782 | G11: =SUMIF('Monthly View'!$E$4:$BL$4,"Real",'Monthly View'!$E$21:$BL$21) -> 0 | H11: =SUMIF('Monthly View'!$E$4:$BL$4,"Real",'Monthly View'!$E$22:$BL$22) -> 0 | I11: =SUMIF('Monthly View'!$E$4:$BL$4,"Real",'Monthly View'!$E$23:$BL$23)+'Project Infor'!C48 -> 0 | J11: =SUMIF('Monthly View'!$E$4:$BL$4,"Real",'Monthly View'!$E$24:$BL$24)+'Project Infor'!C49 -> 0 | K11: =SUM(E11,G11,H11,I11,J11) -> 42616.71 | L11: =D11-K11 -> 14932.79 | M11: =IF(D11=0,0,(D11-E11-H11-I11-G11-J11)/D11) -> 0.25947732 | N11: =IF(D11=0,0,(D11-E11/UTILIZACION-G11/UTILIZACION-H11/UTILIZACION-I11-J11)/D11) -> 0.20373905
B12: % Avance | D12: =IF(D11=0,1,(D11/D8)) -> 0.12376237 | E12: =IF(E11=0,1,(E11/E8)) -> 0.125 | F12: =IF(F11=0,1,(F11/F8)) -> 0.125
B17: Comentarios adicionales Cost Summary
B18: Generado por RPA: 2026-05-11 09:11:46 | PPO=20251160543_PPO_CEducación_AMS_SI_Lote 2_v01.xlsm | NumeroSF=20251160543 | Tipo=AT | Campos PPO=7 | Datos SAP/SF del ejemplo: valores de prueba hardcodeados para validacion. | Revisar: campos externos, intercompany y planificacion.

Sheet Ayuda
B2: CORE PC - VENTA POR AVANCE DE COSTES
B4: Pasos para completar el CORE en la apertura de un proyecto
B5: 1) Completar "Project Infor" incluyendo los datos del PPO
B6: 2) Revisar "Cost Overview" con la información de la Baseline Inicial (Fila 10) para que esté ok con PPO
B7: 3) Completar los coste del personal que va a ejecutar el proyecto en "Resources". IMPORTANTE: No indicar Nombre y Apellidos, solo Iniciales. También se debe indicar para cada perfil si es o no INTERCO porque ese dato se utiliza para calcular en coste de cada tipo de perfil y si no se completa no se tiene en cuenta el coste.
B8: 4) Completar el Planning de Horas, Riesgos, Garantía, Gastos y Compras en "Cost Planning". Tendremos avisos sobre lo que no hayamos planificado en cada una de las secciones
B9: 5) En "Monthly View" y "Cost Summary" tendremos la información de arranque del proyecto
B11: Pasos para completar la información mensual
B12: 1) Introducir la Fecha de Reporting en "Project Infor", celda C8
B13: 2) Introducir Ampliaciones y Reestimaciones en "Cost Overview"
B14: 3) Actualizar Costes de Recursos en "Resources". Importante: como nuestros costes puede que no cuadren 100% con los de SAP, si tenemos el dato de los costes mensuales del mes pasado en SAP, metemos la diferencia en "Cost Planning" en las celdas amarillas. Así vamos corrigiendo las diferencias mes a mes. Si la diferencia es signiticativa tendremos que revisar los costes de los recursos por si alguno no está como en SAP. Tambien en Resources tenemos que actualizar la tarifa de venta, ya sea por hora o por jornadas
B15: 4) Actualizar el Planning de Horas Reales y Facturables, Riesgos, Garantía, Gastos y Compras en "Cost Planning". Tendremos avisos sobre lo que no hayamos planificado en cada una de las secciones. Si por ejemplo nos vamos a gastar más en Horas y queremos reestimar Riesgos, tendremos que volver a la pestaña "Cost Overview" para ver qué reestimación sería necesaria. Las Reestimaciones tienen que tener validación por parte de Cost Control & Optimization (CCO).
... B25: Los datos del FORECAST de VENTA aparecen en "Monthly View" - Fila 18. En la pestaña Aux Forecast se puede ir guardando el forecast proporcionado cada mes para tener una vista de la evolución de Forecast.

Sheet aux Billing Plan
B2: WBS-Element | C2: ='Project Infor'!C10 -> ZEV-ATE0012-1001 | D2: ='Project Infor'!C11 -> Lote 2: Núcleo Estructural Java
B5: IMPORTE NETO A FACTURAR | E5: ='Cost Overview'!F8 -> 465000 | F5: (!) Faltan HITOS de FACTURACION por planificar | J5: =E5-F41 -> 465000
B7: TIPO FACTURA | C7: FECHA ESTIMADA FACTURA | D7: DCat | E7: CONCEPTO FACTURA | F7: IMPORTE FACTURA | G7: Currency | H7: IMPUESTOS (%) | I7: IMPORTE más IMPUESTOS | J7: LINEA/S DE PEDIDO | K7: CLIENTE | L7: Ticket support BILLING & COLLECTION | M7: FECHA FACTURA | N7: ENVIO FACTURA | O7: OTRA INFOR FACTURACION | P7: COBRADA
D8: =IF(C8=0," ","Z2") | I8: =IF(F8=0," ",F8+F8*H8)
D9: =IF(C9=0," ","Z2") | I9: =IF(F9=0," ",F9+F9*H9)
D10: =IF(C10=0," ","Z2") | I10: =IF(F10=0," ",F10+F10*H10)
D11: =IF(C11=0," ","Z2") | I11: =IF(F11=0," ",F11+F11*H11)
D12: =IF(C12=0," ","Z2") | I12: =IF(F12=0," ",F12+F12*H12)
D13: =IF(C13=0," ","Z2") | I13: =IF(F13=0," ",F13+F13*H13)
D14: =IF(C14=0," ","Z2") | I14: =IF(F14=0," ",F14+F14*H14)
D15: =IF(C15=0," ","Z2") | I15: =IF(F15=0," ",F15+F15*H15)
D16: =IF(C16=0," ","Z2") | I16: =IF(F16=0," ",F16+F16*H16)
D17: =IF(C17=0," ","Z2") | I17: =IF(F17=0," ",F17+F17*H17)
D18: =IF(C18=0," ","Z2") | I18: =IF(F18=0," ",F18+F18*H18)
D19: =IF(C19=0," ","Z2") | I19: =IF(F19=0," ",F19+F19*H19)
... D40: =IF(C40=0," ","Z2") | I40: =IF(F40=0," ",F40+F40*H40)
B41: TOTAL FACTURACION | F41: =SUM(F8:F40) -> 0 | I41: =SUM(I8:I40) -> 0
B50: Comentarios adicionales Billing Plan
B51: <dd/mm/aaaa> comentario <dd/mm/aaaa> comentario <dd/mm/aaaa> comentario

Sheet aux Forecast
B2: WBS-Element | C2: ='Project Infor'!C10 -> ZEV-ATE0012-1001 | D2: ='Project Infor'!C11 -> Lote 2: Núcleo Estructural Java
B4: Mes Forecast | C4: 44197 | D4: =EOMONTH(C4,1) -> 44255 | E4: =EOMONTH(D4,1) -> 44286 | F4: =EOMONTH(E4,1) -> 44316 | G4: =EOMONTH(F4,1) -> 44347 | H4: =EOMONTH(G4,1) -> 44377 | I4: =EOMONTH(H4,1) -> 44408 | J4: =EOMONTH(I4,1) -> 44439 | K4: =EOMONTH(J4,1) -> 44469 | ... Z4: =EOMONTH(Y4,1) -> 44926
B5: 44197
B6: =EOMONTH(B5,1) -> 44255
B7: =EOMONTH(B6,1) -> 44286
B8: =EOMONTH(B7,1) -> 44316
B9: =EOMONTH(B8,1) -> 44347
B10: =EOMONTH(B9,1) -> 44377
B11: =EOMONTH(B10,1) -> 44408
B12: =EOMONTH(B11,1) -> 44439
B13: =EOMONTH(B12,1) -> 44469
B14: =EOMONTH(B13,1) -> 44500
B15: =EOMONTH(B14,1) -> 44530
B16: =EOMONTH(B15,1) -> 44561
B19: Comentarios adicionales Forecast
B20: <dd/mm/aaaa> comentario <dd/mm/aaaa> comentario <dd/mm/aaaa> comentario

Sheet aux UTE
B2: WBS-Element | C2: ='Project Infor'!C10 -> ZEV-ATE0012-1001 | D2: ='Project Infor'!C11 -> Lote 2: Núcleo Estructural Java
B4: CLIENTE | C4: MINISTERIO | F4: ENTIDADES que forman la UTE | H4: PORCENTAJE | I4: IMPORTE (sin IVA) | J4: INTERLOCUTOR | K4: INFOR ADICIONAL
B5: GERENTE UTE | C5: Nombre Apellidos | F5: Entidad 1 | H5: 0.5 | I5: 5000 | J5: Nombre Apellidos
B6: DENOMINACION UTE | C6: UTE CONNECTIS --- | F6: Entidad 2 | H6: 0.1 | I6: 1000
B7: IMPORTE CONTRATACION (SIN iva) | C7: 10000 | E7: (!) Los IMPORTES por ENTIDADES no coinciden con el TOTAL | F7: Entidad 3 | H7: 0.2 | I7: 2000
F8: Entidad 4 | H8: 0.1 | I8: 1000
F9: Entidad 5 | H9: 0.1 | I9: 1000
C10: (!) Faltan HITOS de FACTURACION por planificar
B12: TIPO FACTURA | C12: FECHA ESTIMADA FACTURA | D12: ENTIDAD que FACTURA | E12: CONCEPTO FACTURA | F12: IMPORTE FACTURA | G12: Currency | H12: IMPUESTOS (%) | I12: IMPORTE más IMPUESTOS | J12: CLIENTE | K12: ENVIADA a utes@getronics.com | L12: FECHA FACTURA | M12: ENVIO FACTURA | N12: OTRA INFOR FACTURACION | O12: COBRADA
B13: FACTURA | C13: 44286 | D13: Entidad 1 | E13: Factura Hito 1 | F13: 3000 | G13: EUR | H13: 0.21 | I13: =IF(F13=0," ",F13+F13*H13) -> 3630 | J13: MINISTERIO | M13: Portal efacturación
D14: =IF(C14=0," ","Z2") | I14: =IF(F14=0," ",F14+F14*H14)
D15: =IF(C15=0," ","Z2") | I15: =IF(F15=0," ",F15+F15*H15)
D16: =IF(C16=0," ","Z2") | I16: =IF(F16=0," ",F16+F16*H16)
D17: =IF(C17=0," ","Z2") | I17: =IF(F17=0," ",F17+F17*H17)
D18: =IF(C18=0," ","Z2") | I18: =IF(F18=0," ",F18+F18*H18)
D19: =IF(C19=0," ","Z2") | I19: =IF(F19=0," ",F19+F19*H19)
D20: =IF(C20=0," ","Z2") | I20: =IF(F20=0," ",F20+F20*H20)
D21: =IF(C21=0," ","Z2") | I21: =IF(F21=0," ",F21+F21*H21)
D22: =IF(C22=0," ","Z2") | I22: =IF(F22=0," ",F22+F22*H22)
D23: =IF(C23=0," ","Z2") | I23: =IF(F23=0," ",F23+F23*H23)
D24: =IF(C24=0," ","Z2") | I24: =IF(F24=0," ",F24+F24*H24)
D25: =IF(C25=0," ","Z2") | I25: =IF(F25=0," ",F25+F25*H25)
... D45: =IF(C45=0," ","Z2") | I45: =IF(F45=0," ",F45+F45*H45)
B46: TOTAL FACTURACION | F46: =SUM(F13:F45) -> 3000 | I46: =SUM(I13:I45) -> 3630
B55: Comentarios adicionales Gestión UTE
B56: <dd/mm/aaaa> comentario <dd/mm/aaaa> comentario <dd/mm/aaaa> comentario

Sheet aux Calendarios
B2: WBS-Element | C2: ='Project Infor'!C10 -> ZEV-ATE0012-1001 | D2: ='Project Infor'!C11 -> Lote 2: Núcleo Estructural Java
B5: CALENDARIO 1 | D5: Descripción calendario
B6: HORAS/JORNADA | C6: HORAS JORNADA | D6: ='Project Infor'!$C$8 -> 46023 | E6: =EOMONTH(D6,1) -> 46081 | F6: =EOMONTH(E6,1) -> 46112 | G6: =EOMONTH(F6,1) -> 46142 | H6: =EOMONTH(G6,1) -> 46173 | I6: =EOMONTH(H6,1) -> 46203 | J6: =EOMONTH(I6,1) -> 46234 | K6: =EOMONTH(J6,1) -> 46265 | L6: =EOMONTH(K6,1) -> 46295 | ... AB6: =EOMONTH(AA6,1) -> 46783
B7: 8.5 | C7: =IF(B7=0,"",CONCATENATE("Jornadas de ",B7," horas: ")) -> Jornadas de 8,5 horas: | D7: 16 | E7: 16 | F7: 16 | G7: 16 | J7: 16
B8: 7 | C8: =IF(B8=0,"",CONCATENATE("Jornadas de ",B8," horas: ")) -> Jornadas de 7 horas: | D8: 3 | E8: 2 | F8: 1 | G8: 4 | H8: 22 | I8: 22 | J8: 5
B9: 6 | C9: =IF(B9=0,"",CONCATENATE("Jornadas de ",B9," horas: ")) -> Jornadas de 6 horas: | D9: 1 | E9: 3 | F9: 1 | G9: 2 | J9: 9
B10: 7.25 | C10: =IF(B10=0,"",CONCATENATE("Jornadas de ",B10," horas: ")) -> Jornadas de 7,25 horas:
B11: 5.25 | C11: =IF(B11=0,"",CONCATENATE("Jornadas de ",B11," horas: ")) -> Jornadas de 5,25 horas: | D11: 2 | F11: 2
C12: TOTAL HORAS MES | D12: =SUMPRODUCT(D7:D11,$B$7:$B$11) -> 173.5 | E12: =SUMPRODUCT(E7:E11,$B$7:$B$11) -> 168 | F12: =SUMPRODUCT(F7:F11,$B$7:$B$11) -> 159.5 | G12: =SUMPRODUCT(G7:G11,$B$7:$B$11) -> 176 | H12: =SUMPRODUCT(H7:H11,$B$7:$B$11) -> 154 | I12: =SUMPRODUCT(I7:I11,$B$7:$B$11) -> 154 | J12: =SUMPRODUCT(J7:J11,$B$7:$B$11) -> 225 | K12: =SUMPRODUCT(K7:K11,$B$7:$B$11) -> 0 | ... AB12: =SUMPRODUCT(AB7:AB11,$B$7:$B$11) -> 0
B15: CALENDARIO 2 | D15: Descripción calendario
B16: HORAS/JORNADA | C16: HORAS JORNADA | D16: ='Project Infor'!$C$8 -> 46023 | E16: =EOMONTH(D16,1) -> 46081 | F16: =EOMONTH(E16,1) -> 46112 | G16: =EOMONTH(F16,1) -> 46142 | H16: =EOMONTH(G16,1) -> 46173 | I16: =EOMONTH(H16,1) -> 46203 | J16: =EOMONTH(I16,1) -> 46234 | K16: =EOMONTH(J16,1) -> 46265 | L16: =EOMONTH(K16,1) -> 46295 | ... AB16: =EOMONTH(AA16,1) -> 46783
B17: 8 | C17: =IF(B17=0,"",CONCATENATE("Jornadas de ",B17," horas: ")) -> Jornadas de 8 horas: | D17: 16
B18: 6 | C18: =IF(B18=0,"",CONCATENATE("Jornadas de ",B18," horas: ")) -> Jornadas de 6 horas: | D18: 3
C19: =IF(B19=0,"",CONCATENATE("Jornadas de ",B19," horas: "))
C21: =IF(B21=0,"",CONCATENATE("Jornadas de ",B21," horas: "))
C22: TOTAL HORAS MES | D22: =SUMPRODUCT(D17:D21,$B$17:$B$21) -> 146 | E22: =SUMPRODUCT(E17:E21,$B$17:$B$21) -> 0 | F22: =SUMPRODUCT(F17:F21,$B$17:$B$21) -> 0 | G22: =SUMPRODUCT(G17:G21,$B$17:$B$21) -> 0 | H22: =SUMPRODUCT(H17:H21,$B$17:$B$21) -> 0 | I22: =SUMPRODUCT(I17:I21,$B$17:$B$21) -> 0 | J22: =SUMPRODUCT(J17:J21,$B$17:$B$21) -> 0 | K22: =SUMPRODUCT(K17:K21,$B$17:$B$21) -> 0 | ... AB22: =SUMPRODUCT(AB17:AB21,$B$17:$B$21) -> 0
B25: CALENDARIO 3 | D25: Descripción calendario
B26: HORAS/JORNADA | C26: HORAS JORNADA | D26: ='Project Infor'!$C$8 -> 46023 | E26: =EOMONTH(D26,1) -> 46081 | F26: =EOMONTH(E26,1) -> 46112 | G26: =EOMONTH(F26,1) -> 46142 | H26: =EOMONTH(G26,1) -> 46173 | I26: =EOMONTH(H26,1) -> 46203 | J26: =EOMONTH(I26,1) -> 46234 | K26: =EOMONTH(J26,1) -> 46265 | L26: =EOMONTH(K26,1) -> 46295 | ... AB26: =EOMONTH(AA26,1) -> 46783
B27: 7 | C27: =IF(B27=0,"",CONCATENATE("Jornadas de ",B27," horas: ")) -> Jornadas de 7 horas: | D27: 22 | E27: 20 | F27: 21 | G27: 21 | H27: 22 | I27: 22 | J27: 22 | K27: 21 | L27: 22 | M27: 16
C28: =IF(B28=0,"",CONCATENATE("Jornadas de ",B28," horas: "))
C29: =IF(B29=0,"",CONCATENATE("Jornadas de ",B29," horas: "))
C31: =IF(B31=0,"",CONCATENATE("Jornadas de ",B31," horas: "))
C32: TOTAL HORAS MES | D32: =SUMPRODUCT(D27:D31,$B$27:$B$31) -> 154 | E32: =SUMPRODUCT(E27:E31,$B$27:$B$31) -> 140 | F32: =SUMPRODUCT(F27:F31,$B$27:$B$31) -> 147 | G32: =SUMPRODUCT(G27:G31,$B$27:$B$31) -> 147 | H32: =SUMPRODUCT(H27:H31,$B$27:$B$31) -> 154 | I32: =SUMPRODUCT(I27:I31,$B$27:$B$31) -> 154 | J32: =SUMPRODUCT(J27:J31,$B$27:$B$31) -> 154 | K32: =SUMPRODUCT(K27:K31,$B$27:$B$31) -> 147 | ... AB32: =SUMPRODUCT(AB27:AB31,$B$27:$B$31) -> 0
B35: CALENDARIO 4 | D35: Descripción calendario
B36: HORAS/JORNADA | C36: HORAS JORNADA | D36: ='Project Infor'!$C$8 -> 46023 | E36: =EOMONTH(D36,1) -> 46081 | F36: =EOMONTH(E36,1) -> 46112 | G36: =EOMONTH(F36,1) -> 46142 | H36: =EOMONTH(G36,1) -> 46173 | I36: =EOMONTH(H36,1) -> 46203 | J36: =EOMONTH(I36,1) -> 46234 | K36: =EOMONTH(J36,1) -> 46265 | L36: =EOMONTH(K36,1) -> 46295 | ... AB36: =EOMONTH(AA36,1) -> 46783
B37: 7 | C37: =IF(B37=0,"",CONCATENATE("Jornadas de ",B37," horas: ")) -> Jornadas de 7 horas: | D37: 22 | E37: 20
C38: =IF(B38=0,"",CONCATENATE("Jornadas de ",B38," horas: "))
C39: =IF(B39=0,"",CONCATENATE("Jornadas de ",B39," horas: "))
C41: =IF(B41=0,"",CONCATENATE("Jornadas de ",B41," horas: "))
C42: TOTAL HORAS MES | D42: =SUMPRODUCT(D37:D41,$B$37:$B$41) -> 154 | E42: =SUMPRODUCT(E37:E41,$B$37:$B$41) -> 140 | F42: =SUMPRODUCT(F37:F41,$B$37:$B$41) -> 0 | G42: =SUMPRODUCT(G37:G41,$B$37:$B$41) -> 0 | H42: =SUMPRODUCT(H37:H41,$B$37:$B$41) -> 0 | I42: =SUMPRODUCT(I37:I41,$B$37:$B$41) -> 0 | J42: =SUMPRODUCT(J37:J41,$B$37:$B$41) -> 0 | K42: =SUMPRODUCT(K37:K41,$B$37:$B$41) -> 0 | ... AB42: =SUMPRODUCT(AB37:AB41,$B$37:$B$41) -> 0
B45: CALENDARIO 5 | D45: Descripción calendario
B46: HORAS/JORNADA | C46: HORAS JORNADA | D46: ='Project Infor'!$C$8 -> 46023 | E46: =EOMONTH(D46,1) -> 46081 | F46: =EOMONTH(E46,1) -> 46112 | G46: =EOMONTH(F46,1) -> 46142 | H46: =EOMONTH(G46,1) -> 46173 | I46: =EOMONTH(H46,1) -> 46203 | J46: =EOMONTH(I46,1) -> 46234 | K46: =EOMONTH(J46,1) -> 46265 | L46: =EOMONTH(K46,1) -> 46295 | ... AB46: =EOMONTH(AA46,1) -> 46783
B47: 7 | C47: =IF(B47=0,"",CONCATENATE("Jornadas de ",B47," horas: ")) -> Jornadas de 7 horas: | D47: 22 | E47: 20
C48: =IF(B48=0,"",CONCATENATE("Jornadas de ",B48," horas: "))
C49: =IF(B49=0,"",CONCATENATE("Jornadas de ",B49," horas: "))
C51: =IF(B51=0,"",CONCATENATE("Jornadas de ",B51," horas: "))
C52: TOTAL HORAS MES | D52: =SUMPRODUCT(D47:D51,$B$47:$B$51) -> 154 | E52: =SUMPRODUCT(E47:E51,$B$47:$B$51) -> 140 | F52: =SUMPRODUCT(F47:F51,$B$47:$B$51) -> 0 | G52: =SUMPRODUCT(G47:G51,$B$47:$B$51) -> 0 | H52: =SUMPRODUCT(H47:H51,$B$47:$B$51) -> 0 | I52: =SUMPRODUCT(I47:I51,$B$47:$B$51) -> 0 | J52: =SUMPRODUCT(J47:J51,$B$47:$B$51) -> 0 | K52: =SUMPRODUCT(K47:K51,$B$47:$B$51) -> 0 | ... AB52: =SUMPRODUCT(AB47:AB51,$B$47:$B$51) -> 0
B55: CALENDARIO 6 | D55: Descripción calendario
B56: HORAS/JORNADA | C56: HORAS JORNADA | D56: ='Project Infor'!$C$8 -> 46023 | E56: =EOMONTH(D56,1) -> 46081 | F56: =EOMONTH(E56,1) -> 46112 | G56: =EOMONTH(F56,1) -> 46142 | H56: =EOMONTH(G56,1) -> 46173 | I56: =EOMONTH(H56,1) -> 46203 | J56: =EOMONTH(I56,1) -> 46234 | K56: =EOMONTH(J56,1) -> 46265 | L56: =EOMONTH(K56,1) -> 46295 | ... AB56: =EOMONTH(AA56,1) -> 46783
C58: =IF(B58=0,"",CONCATENATE("Jornadas de ",B58," horas: "))
C59: =IF(B59=0,"",CONCATENATE("Jornadas de ",B59," horas: "))
C61: =IF(B61=0,"",CONCATENATE("Jornadas de ",B61," horas: "))
C62: TOTAL HORAS MES | D62: =SUMPRODUCT(D57:D61,$B$57:$B$61) -> 0 | E62: =SUMPRODUCT(E57:E61,$B$57:$B$61) -> 0 | F62: =SUMPRODUCT(F57:F61,$B$57:$B$61) -> 0 | G62: =SUMPRODUCT(G57:G61,$B$57:$B$61) -> 0 | H62: =SUMPRODUCT(H57:H61,$B$57:$B$61) -> 0 | I62: =SUMPRODUCT(I57:I61,$B$57:$B$61) -> 0 | J62: =SUMPRODUCT(J57:J61,$B$57:$B$61) -> 0 | K62: =SUMPRODUCT(K57:K61,$B$57:$B$61) -> 0 | ... AB62: =SUMPRODUCT(AB57:AB61,$B$57:$B$61) -> 0
